{
  "type": "Feature",
  "properties": {
    "gn:admin1_code":"13.0",
    "gn:asciiname":"Goubi",
    "gn:country_code":"SN",
    "gn:dem":42,
    "gn:feature_class":"P",
    "gn:feature_code":"PPL",
    "gn:name":"Goubi",
    "gn:population":0,
    "gn:timezone":"Africa/Dakar",
    "iso:country":"SN",
    "name:und_x_variant":[
        "Gouby",
        "Goubij",
        "Goubi"
    ],
    "wof:name":"Goubi",
    "wof:placetype":"locality"
},
  "geometry": {"coordinates":[-15.6078,15.6174],"type":"Point"}
}