{
  "type": "Feature",
  "properties": {
    "gn:admin1_code":"13.0",
    "gn:asciiname":"Sadok",
    "gn:country_code":"SN",
    "gn:dem":43,
    "gn:feature_class":"P",
    "gn:feature_code":"PPL",
    "gn:name":"Sadok",
    "gn:population":0,
    "gn:timezone":"Africa/Dakar",
    "iso:country":"SN",
    "name:deu_x_preferred":[
        "Sadok"
    ],
    "name:pol_x_preferred":[
        "Sadok"
    ],
    "name:rus_x_preferred":[
        "\u0421\u0430\u0434\u043e\u043a"
    ],
    "name:ukr_x_preferred":[
        "\u0421\u0430\u0434\u043e\u043a"
    ],
    "wof:name":"Sadok",
    "wof:placetype":"locality"
},
  "geometry": {"coordinates":[-14.6064,15.6708],"type":"Point"}
}