{
  "type": "Feature",
  "properties": {
    "gn:admin1_code":"18.0",
    "gn:asciiname":"Diemekounda",
    "gn:country_code":"SN",
    "gn:dem":12,
    "gn:feature_class":"P",
    "gn:feature_code":"PPL",
    "gn:name":"Di\u00e9m\u00e9kounda",
    "gn:population":0,
    "gn:timezone":"Africa/Dakar",
    "iso:country":"SN",
    "wof:name":"Diemekounda",
    "wof:placetype":"locality"
},
  "geometry": {"coordinates":[-15.23333,12.86667],"type":"Point"}
}