{
  "type": "Feature",
  "properties": {
    "gn:admin1_code":"7.0",
    "gn:asciiname":"Teprin Un",
    "gn:country_code":"SN",
    "gn:dem":38,
    "gn:feature_class":"P",
    "gn:feature_code":"PPL",
    "gn:name":"T\u00e9prin Un",
    "gn:population":0,
    "gn:timezone":"Africa/Dakar",
    "iso:country":"SN",
    "name:und_x_variant":[
        "T\u00e9prin Un",
        "T\u00e9prin Premier"
    ],
    "wof:lang_x_official":[
        "wol",
        "fra"
    ],
    "wof:lang_x_spoken":[
        "wol",
        "fra"
    ],
    "wof:name":"Teprin Un",
    "wof:placetype":"locality"
},
  "geometry": {"coordinates":[-17.03963,14.66508],"type":"Point"}
}