{
  "type": "Feature",
  "properties": {
    "gn:admin1_code":"16.0",
    "gn:asciiname":"Goui Leum",
    "gn:country_code":"SN",
    "gn:dem":20,
    "gn:feature_class":"P",
    "gn:feature_code":"PPL",
    "gn:name":"Gou\u00ef Leum",
    "gn:population":0,
    "gn:timezone":"Africa/Dakar",
    "iso:country":"SN",
    "name:und_x_variant":[
        "Gouy Lem",
        "Gou\u00ef Leum"
    ],
    "wof:name":"Goui Leum",
    "wof:placetype":"locality"
},
  "geometry": {"coordinates":[-15.73333,14.31667],"type":"Point"}
}