{
  "type": "Feature",
  "properties": {
    "gn:admin1_code":"11.0",
    "gn:asciiname":"Mandoufou Fode",
    "gn:country_code":"SN",
    "gn:dem":58,
    "gn:feature_class":"P",
    "gn:feature_code":"PPL",
    "gn:name":"Mandoufou Fod\u00e9",
    "gn:population":0,
    "gn:timezone":"Africa/Dakar",
    "iso:country":"SN",
    "wof:name":"Mandoufou Fode",
    "wof:placetype":"locality"
},
  "geometry": {"coordinates":[-13.93333,13.01667],"type":"Point"}
}