{
  "type": "Feature",
  "properties": {
    "gn:admin1_code":"18.0",
    "gn:asciiname":"Teranbassi",
    "gn:country_code":"SN",
    "gn:dem":16,
    "gn:feature_class":"P",
    "gn:feature_code":"PPL",
    "gn:name":"Teranbassi",
    "gn:population":0,
    "gn:timezone":"Africa/Dakar",
    "iso:country":"SN",
    "name:und_x_variant":[
        "T\u00e9rambassi Mankagne",
        "Teranbassi"
    ],
    "wof:name":"Teranbassi",
    "wof:placetype":"locality"
},
  "geometry": {"coordinates":[-15.75806,12.56111],"type":"Point"}
}