{
  "type": "Feature",
  "properties": {
    "gn:admin1_code":"3.0",
    "gn:asciiname":"Ouro Medoul",
    "gn:country_code":"SN",
    "gn:dem":52,
    "gn:feature_class":"P",
    "gn:feature_code":"PPL",
    "gn:name":"Ouro M\u00e9doul",
    "gn:population":0,
    "gn:timezone":"Africa/Dakar",
    "iso:country":"SN",
    "wof:name":"Ouro Medoul",
    "wof:placetype":"locality"
},
  "geometry": {"coordinates":[-15.73333,14.88333],"type":"Point"}
}