{
  "type": "Feature",
  "properties": {
    "gn:admin1_code":"11.0",
    "gn:asciiname":"Hamdallai Amadou",
    "gn:cc2":"SN",
    "gn:country_code":"SN",
    "gn:dem":32,
    "gn:feature_class":"P",
    "gn:feature_code":"PPL",
    "gn:name":"Hamdalla\u00ef Amadou",
    "gn:population":0,
    "gn:timezone":"Africa/Dakar",
    "iso:country":"SN",
    "name:und_x_variant":[
        "Hamdallali",
        "Hamdallahi",
        "Hamdalahi",
        "Hamdallaye",
        "Hamdalla\u00ef Amadou"
    ],
    "wof:lang_x_official":[
        "wol",
        "fra"
    ],
    "wof:lang_x_spoken":[
        "wol",
        "fra"
    ],
    "wof:name":"Hamdallai Amadou",
    "wof:placetype":"locality"
},
  "geometry": {"coordinates":[-14.88333,13.08333],"type":"Point"}
}