{
  "type": "Feature",
  "properties": {
    "gn:admin1_code":"5.0",
    "gn:asciiname":"Gourel Bouna",
    "gn:country_code":"SN",
    "gn:dem":107,
    "gn:feature_class":"P",
    "gn:feature_code":"PPL",
    "gn:name":"Gourel Bouna",
    "gn:population":0,
    "gn:timezone":"Africa/Dakar",
    "iso:country":"SN",
    "wof:name":"Gourel Bouna",
    "wof:placetype":"locality"
},
  "geometry": {"coordinates":[-12.4381,14.58462],"type":"Point"}
}