{
  "type": "Feature",
  "properties": {
    "gn:admin1_code":"13.0",
    "gn:asciiname":"Battal",
    "gn:country_code":"SN",
    "gn:dem":36,
    "gn:feature_class":"P",
    "gn:feature_code":"PPL",
    "gn:name":"Battal",
    "gn:population":0,
    "gn:timezone":"Africa/Dakar",
    "iso:country":"SN",
    "name:fas_x_preferred":[
        "\u0628\u062a\u0644"
    ],
    "name:und_x_variant":[
        "Battel",
        "Battal"
    ],
    "name:urd_x_preferred":[
        "\u0628\u0679\u0644"
    ],
    "wof:name":"Battal",
    "wof:placetype":"locality"
},
  "geometry": {"coordinates":[-16.2337,15.2301],"type":"Point"}
}