{
  "type": "Feature",
  "properties": {
    "gn:admin1_code":"14.0",
    "gn:asciiname":"Tiaski",
    "gn:country_code":"SN",
    "gn:dem":38,
    "gn:feature_class":"P",
    "gn:feature_code":"PPL",
    "gn:name":"Tiaski",
    "gn:population":0,
    "gn:timezone":"Africa/Dakar",
    "iso:country":"SN",
    "wof:name":"Tiaski",
    "wof:placetype":"locality"
},
  "geometry": {"coordinates":[-14.2358,15.672],"type":"Point"}
}