{
  "type": "Feature",
  "properties": {
    "gn:admin1_code":"7.0",
    "gn:asciiname":"Ngassiak",
    "gn:country_code":"SN",
    "gn:dem":9,
    "gn:feature_class":"P",
    "gn:feature_code":"PPL",
    "gn:name":"Ngassiak",
    "gn:population":0,
    "gn:timezone":"Africa/Dakar",
    "iso:country":"SN",
    "wof:name":"Ngassiak",
    "wof:placetype":"locality"
},
  "geometry": {"coordinates":[-16.55,14.53333],"type":"Point"}
}