{
  "type": "Feature",
  "properties": {
    "gn:admin1_code":"14.0",
    "gn:asciiname":"As",
    "gn:country_code":"SN",
    "gn:dem":6,
    "gn:feature_class":"P",
    "gn:feature_code":"PPL",
    "gn:name":"As",
    "gn:population":0,
    "gn:timezone":"Africa/Dakar",
    "iso:country":"SN",
    "wof:name":"As",
    "wof:placetype":"locality"
},
  "geometry": {"coordinates":[-14.97566,16.60868],"type":"Point"}
}