{
  "type": "Feature",
  "properties": {
    "gn:admin1_code":"10.0",
    "gn:asciiname":"Keur Ouak Batio",
    "gn:country_code":"SN",
    "gn:dem":36,
    "gn:feature_class":"P",
    "gn:feature_code":"PPL",
    "gn:name":"Keur Ouak Batio",
    "gn:population":0,
    "gn:timezone":"Africa/Dakar",
    "iso:country":"SN",
    "wof:name":"Keur Ouak Batio",
    "wof:placetype":"locality"
},
  "geometry": {"coordinates":[-16.06667,13.71667],"type":"Point"}
}