{
  "type": "Feature",
  "properties": {
    "gn:admin1_code":"13.0",
    "gn:asciiname":"Toum",
    "gn:country_code":"SN",
    "gn:dem":36,
    "gn:feature_class":"P",
    "gn:feature_code":"PPL",
    "gn:name":"Toum",
    "gn:population":0,
    "gn:timezone":"Africa/Dakar",
    "iso:country":"SN",
    "name:fra_x_preferred":[
        "Toum"
    ],
    "name:hye_x_preferred":[
        "\u054f\u0578\u0578\u0582\u0574"
    ],
    "name:nld_x_preferred":[
        "Toum"
    ],
    "name:por_x_preferred":[
        "Toum"
    ],
    "name:spa_x_preferred":[
        "Toum"
    ],
    "name:vie_x_preferred":[
        "Toum"
    ],
    "wof:name":"Toum",
    "wof:placetype":"locality"
},
  "geometry": {"coordinates":[-14.9981,15.17],"type":"Point"}
}