{
  "type": "Feature",
  "properties": {
    "gn:admin1_code":"18.0",
    "gn:asciiname":"Kandimba",
    "gn:country_code":"SN",
    "gn:dem":7,
    "gn:feature_class":"P",
    "gn:feature_code":"PPL",
    "gn:name":"Kandimba",
    "gn:population":0,
    "gn:timezone":"Africa/Dakar",
    "iso:country":"SN",
    "wof:name":"Kandimba",
    "wof:placetype":"locality"
},
  "geometry": {"coordinates":[-15.66667,13.23333],"type":"Point"}
}