{
  "type": "Feature",
  "properties": {
    "gn:admin1_code":"13.0",
    "gn:asciiname":"Renda",
    "gn:country_code":"SN",
    "gn:dem":49,
    "gn:feature_class":"P",
    "gn:feature_code":"PPL",
    "gn:name":"R\u00e8nda",
    "gn:population":0,
    "gn:timezone":"Africa/Dakar",
    "iso:country":"SN",
    "name:ita_x_preferred":[
        "Renda"
    ],
    "name:por_x_preferred":[
        "Renda"
    ],
    "name:und_x_variant":[
        "Rennda",
        "R\u00e8nda"
    ],
    "wof:name":"Renda",
    "wof:placetype":"locality"
},
  "geometry": {"coordinates":[-15.1963,15.8359],"type":"Point"}
}