{
  "type": "Feature",
  "properties": {
    "gn:admin1_code":"18.0",
    "gn:asciiname":"Bouno",
    "gn:country_code":"SN",
    "gn:dem":4,
    "gn:feature_class":"P",
    "gn:feature_code":"PPL",
    "gn:name":"Bouno",
    "gn:population":0,
    "gn:timezone":"Africa/Dakar",
    "iso:country":"SN",
    "name:und_x_variant":[
        "Bounou",
        "Bonou",
        "Bonu",
        "Bouno"
    ],
    "wof:name":"Bouno",
    "wof:placetype":"locality"
},
  "geometry": {"coordinates":[-15.58972,12.58778],"type":"Point"}
}