{
  "type": "Feature",
  "properties": {
    "gn:admin1_code":"13.0",
    "gn:asciiname":"Ouaki",
    "gn:cc2":"SN",
    "gn:country_code":"SN",
    "gn:dem":47,
    "gn:feature_class":"P",
    "gn:feature_code":"PPL",
    "gn:name":"Ouaki",
    "gn:population":0,
    "gn:timezone":"Africa/Dakar",
    "iso:country":"SN",
    "name:und_x_variant":[
        "Sintiou Ouaki",
        "Ouak\u00e9",
        "Ouaki"
    ],
    "wof:name":"Ouaki",
    "wof:placetype":"locality"
},
  "geometry": {"coordinates":[-16.06667,15.51667],"type":"Point"}
}