{
  "type": "Feature",
  "properties": {
    "gn:admin1_code":"13.0",
    "gn:asciiname":"Tako",
    "gn:cc2":"SN",
    "gn:country_code":"SN",
    "gn:dem":38,
    "gn:feature_class":"P",
    "gn:feature_code":"PPL",
    "gn:name":"Tako",
    "gn:population":0,
    "gn:timezone":"Africa/Dakar",
    "iso:country":"SN",
    "name:und_x_variant":[
        "Keur Semba Taco",
        "Tako"
    ],
    "wof:name":"Tako",
    "wof:placetype":"locality"
},
  "geometry": {"coordinates":[-16.11667000000001,15.63333],"type":"Point"}
}