{
  "type": "Feature",
  "properties": {
    "gn:admin1_code":"5.0",
    "gn:asciiname":"Diamveli",
    "gn:country_code":"SN",
    "gn:dem":52,
    "gn:feature_class":"P",
    "gn:feature_code":"PPL",
    "gn:name":"Diamv\u00e9li",
    "gn:population":0,
    "gn:timezone":"Africa/Dakar",
    "iso:country":"SN",
    "name:und_x_variant":[
        "Dianv\u00e9li",
        "Diamv\u00e9li"
    ],
    "wof:name":"Diamveli",
    "wof:placetype":"locality"
},
  "geometry": {"coordinates":[-12.60746,14.94008],"type":"Point"}
}