{
  "type": "Feature",
  "properties": {
    "gn:admin1_code":"13.0",
    "gn:asciiname":"Loumbodo Fodji",
    "gn:country_code":"SN",
    "gn:dem":55,
    "gn:feature_class":"P",
    "gn:feature_code":"PPL",
    "gn:name":"Loumbodo Fodji",
    "gn:population":0,
    "gn:timezone":"Africa/Dakar",
    "iso:country":"SN",
    "name:und_x_variant":[
        "Loumbodi Fodji",
        "Loumbodo Fodji"
    ],
    "wof:lang_x_official":[
        "wol",
        "fra"
    ],
    "wof:lang_x_spoken":[
        "wol",
        "fra"
    ],
    "wof:name":"Loumbodo Fodji",
    "wof:placetype":"locality"
},
  "geometry": {"coordinates":[-15.9156,15.3683],"type":"Point"}
}