{
  "type": "Feature",
  "properties": {
    "gn:admin1_code":"7.0",
    "gn:asciiname":"Goudiane",
    "gn:cc2":"SN",
    "gn:country_code":"SN",
    "gn:dem":44,
    "gn:feature_class":"P",
    "gn:feature_code":"PPL",
    "gn:name":"Goudiane",
    "gn:population":0,
    "gn:timezone":"Africa/Dakar",
    "iso:country":"SN",
    "name:und_x_variant":[
        "Goundian",
        "Goundiane",
        "Goudiane"
    ],
    "wof:name":"Goudiane",
    "wof:placetype":"locality"
},
  "geometry": {"coordinates":[-16.73333,14.71667],"type":"Point"}
}