{
  "type": "Feature",
  "properties": {
    "gn:admin1_code":"9.0",
    "gn:asciiname":"Lanbanem",
    "gn:country_code":"SN",
    "gn:dem":10,
    "gn:feature_class":"P",
    "gn:feature_code":"PPL",
    "gn:name":"Lanban\u00e8m",
    "gn:population":0,
    "gn:timezone":"Africa/Dakar",
    "iso:country":"SN",
    "wof:name":"Lanbanem",
    "wof:placetype":"locality"
},
  "geometry": {"coordinates":[-16.46667,14.51667],"type":"Point"}
}