{
  "type": "Feature",
  "properties": {
    "gn:admin1_code":"11.0",
    "gn:asciiname":"Madianke",
    "gn:country_code":"SN",
    "gn:dem":41,
    "gn:feature_class":"P",
    "gn:feature_code":"PPL",
    "gn:name":"Madiank\u00e9",
    "gn:population":0,
    "gn:timezone":"Africa/Dakar",
    "iso:country":"SN",
    "wof:name":"Madianke",
    "wof:placetype":"locality"
},
  "geometry": {"coordinates":[-14.95,13.25],"type":"Point"}
}