{
  "type": "Feature",
  "properties": {
    "gn:admin1_code":"9.0",
    "gn:asciiname":"Rhaye Bayar",
    "gn:country_code":"SN",
    "gn:dem":36,
    "gn:feature_class":"P",
    "gn:feature_code":"PPL",
    "gn:name":"Rhaye Bayar",
    "gn:population":0,
    "gn:timezone":"Africa/Dakar",
    "iso:country":"SN",
    "wof:name":"Rhaye Bayar",
    "wof:placetype":"locality"
},
  "geometry": {"coordinates":[-15.91667,14.46667],"type":"Point"}
}