{
  "type": "Feature",
  "properties": {
    "gn:admin1_code":"16.0",
    "gn:asciiname":"Nianguene Kode",
    "gn:country_code":"SN",
    "gn:dem":39,
    "gn:feature_class":"P",
    "gn:feature_code":"PPL",
    "gn:name":"Niangu\u00e8ne Kod\u00e9",
    "gn:population":0,
    "gn:timezone":"Africa/Dakar",
    "iso:country":"SN",
    "name:und_x_variant":[
        "Niangu\u00e8ne Togue",
        "Niangh\u00e8ne",
        "N\u00efangh\u00e9n",
        "Niangu\u00e8ne Kod\u00e9"
    ],
    "wof:name":"Nianguene Kode",
    "wof:placetype":"locality"
},
  "geometry": {"coordinates":[-15.43333,14.11667],"type":"Point"}
}