{
  "type": "Feature",
  "properties": {
    "gn:admin1_code":"13.0",
    "gn:asciiname":"Niem",
    "gn:cc2":"SN",
    "gn:country_code":"SN",
    "gn:dem":38,
    "gn:feature_class":"P",
    "gn:feature_code":"PPL",
    "gn:name":"Ni\u00e8m",
    "gn:population":0,
    "gn:timezone":"Africa/Dakar",
    "iso:country":"SN",
    "name:und_x_variant":[
        "Seignethiou-Ni\u00e9me",
        "Ni\u00e8m"
    ],
    "wof:name":"Niem",
    "wof:placetype":"locality"
},
  "geometry": {"coordinates":[-16.26667,15.61667],"type":"Point"}
}