{
  "type": "Feature",
  "properties": {
    "gn:admin1_code":"12.0",
    "gn:asciiname":"Djringoumane",
    "gn:cc2":"SN",
    "gn:country_code":"SN",
    "gn:dem":2,
    "gn:feature_class":"P",
    "gn:feature_code":"PPL",
    "gn:name":"Djringoumane",
    "gn:population":0,
    "gn:timezone":"Africa/Dakar",
    "iso:country":"SN",
    "name:und_x_variant":[
        "Djiringoumane",
        "Djringoumane"
    ],
    "wof:name":"Djringoumane",
    "wof:placetype":"locality"
},
  "geometry": {"coordinates":[-16.01806,12.85528],"type":"Point"}
}