{
  "type": "Feature",
  "properties": {
    "gn:admin1_code":"13.0",
    "gn:asciiname":"Afe",
    "gn:country_code":"SN",
    "gn:dem":49,
    "gn:feature_class":"P",
    "gn:feature_code":"PPL",
    "gn:name":"Af\u00e9",
    "gn:population":0,
    "gn:timezone":"Africa/Dakar",
    "iso:country":"SN",
    "name:und_x_variant":[
        "Haf\u00e9",
        "Af\u00e9"
    ],
    "wof:name":"Afe",
    "wof:placetype":"locality"
},
  "geometry": {"coordinates":[-15.4272,15.1316],"type":"Point"}
}