{
  "type": "Feature",
  "properties": {
    "gn:admin1_code":"13.0",
    "gn:asciiname":"Balel Sall",
    "gn:country_code":"SN",
    "gn:dem":14,
    "gn:feature_class":"P",
    "gn:feature_code":"PPL",
    "gn:name":"Balel Sall",
    "gn:population":0,
    "gn:timezone":"Africa/Dakar",
    "iso:country":"SN",
    "name:und_x_variant":[
        "Balel Sala",
        "Balel Sall"
    ],
    "wof:name":"Balel Sall",
    "wof:placetype":"locality"
},
  "geometry": {"coordinates":[-15.1367,15.4351],"type":"Point"}
}