{
  "type": "Feature",
  "properties": {
    "gn:admin1_code":"5.0",
    "gn:asciiname":"Sinntiou Hierikounda Kinndemeri",
    "gn:country_code":"SN",
    "gn:dem":79,
    "gn:feature_class":"P",
    "gn:feature_code":"PPL",
    "gn:name":"Sinntiou Hi\u00e9rikounda Kinnd\u00e9m\u00e9ri",
    "gn:population":0,
    "gn:timezone":"Africa/Dakar",
    "iso:country":"SN",
    "name:und_x_variant":[
        "Sinthiou Hi\u00e9ricounda Kinnd\u00e9m\u00e9ri",
        "Sintiou Hi\u00e9rikounda Kinnd\u00e9m\u00e9ri",
        "Sinntiou Hi\u00e9rikounda Kinnd\u00e9m\u00e9ri"
    ],
    "wof:name":"Sinntiou Hierikounda Kinndemeri",
    "wof:placetype":"locality"
},
  "geometry": {"coordinates":[-12.52945,13.47122],"type":"Point"}
}