{
  "type": "Feature",
  "properties": {
    "gn:admin1_code":"12.0",
    "gn:asciiname":"Atioum",
    "gn:country_code":"SN",
    "gn:dem":11,
    "gn:feature_class":"P",
    "gn:feature_code":"PPL",
    "gn:name":"Atioum",
    "gn:population":0,
    "gn:timezone":"Africa/Dakar",
    "iso:country":"SN",
    "wof:name":"Atioum",
    "wof:placetype":"locality"
},
  "geometry": {"coordinates":[-16.07278,12.67472],"type":"Point"}
}