{
  "type": "Feature",
  "properties": {
    "gn:admin1_code":"3.0",
    "gn:asciiname":"Dialit",
    "gn:country_code":"SN",
    "gn:dem":16,
    "gn:feature_class":"P",
    "gn:feature_code":"PPL",
    "gn:name":"Dialit",
    "gn:population":0,
    "gn:timezone":"Africa/Dakar",
    "iso:country":"SN",
    "wof:name":"Dialit",
    "wof:placetype":"locality"
},
  "geometry": {"coordinates":[-16.46667,14.66667],"type":"Point"}
}