{
  "type": "Feature",
  "properties": {
    "gn:admin1_code":"7.0",
    "gn:asciiname":"Medinatoul Mounawara",
    "gn:country_code":"SN",
    "gn:dem":11,
    "gn:feature_class":"P",
    "gn:feature_code":"PPL",
    "gn:name":"M\u00e9dinatoul Mounawara",
    "gn:population":0,
    "gn:timezone":"Africa/Dakar",
    "iso:country":"SN",
    "wof:name":"Medinatoul Mounawara",
    "wof:placetype":"locality"
},
  "geometry": {"coordinates":[-17.01339,14.53089],"type":"Point"}
}