{
  "type": "Feature",
  "properties": {
    "gn:admin1_code":"13.0",
    "gn:asciiname":"Loumbel Deba",
    "gn:country_code":"SN",
    "gn:dem":44,
    "gn:feature_class":"P",
    "gn:feature_code":"PPL",
    "gn:name":"Loumbel D\u00e9ba",
    "gn:population":0,
    "gn:timezone":"Africa/Dakar",
    "iso:country":"SN",
    "name:und_x_variant":[
        "Loumbeul D\u00e9ba",
        "Loumbel D\u00e9ba"
    ],
    "wof:name":"Loumbel Deba",
    "wof:placetype":"locality"
},
  "geometry": {"coordinates":[-15.0208,15.9302],"type":"Point"}
}