{
  "type": "Feature",
  "properties": {
    "gn:admin1_code":"13.0",
    "gn:asciiname":"Touba Belel",
    "gn:country_code":"SN",
    "gn:dem":56,
    "gn:feature_class":"P",
    "gn:feature_code":"PPL",
    "gn:name":"Touba B\u00e9lel",
    "gn:population":0,
    "gn:timezone":"Africa/Dakar",
    "iso:country":"SN",
    "wof:name":"Touba Belel",
    "wof:placetype":"locality"
},
  "geometry": {"coordinates":[-15.83333,15.05],"type":"Point"}
}