{
  "type": "Feature",
  "properties": {
    "gn:admin1_code":"16.0",
    "gn:asciiname":"Gama",
    "gn:country_code":"SN",
    "gn:dem":15,
    "gn:feature_class":"P",
    "gn:feature_code":"PPL",
    "gn:name":"Gama",
    "gn:population":0,
    "gn:timezone":"Africa/Dakar",
    "iso:country":"SN",
    "name:und_x_variant":[
        "Gamma",
        "Gama"
    ],
    "wof:name":"Gama",
    "wof:placetype":"locality"
},
  "geometry": {"coordinates":[-15.65,14.08333],"type":"Point"}
}