{
  "type": "Feature",
  "properties": {
    "gn:admin1_code":"17.0",
    "gn:asciiname":"Niarabourou",
    "gn:country_code":"SN",
    "gn:dem":135,
    "gn:feature_class":"P",
    "gn:feature_code":"PPL",
    "gn:name":"Niarabourou",
    "gn:population":0,
    "gn:timezone":"Africa/Dakar",
    "iso:country":"SN",
    "wof:name":"Niarabourou",
    "wof:placetype":"locality"
},
  "geometry": {"coordinates":[-12.45,12.88333],"type":"Point"}
}