{
  "type": "Feature",
  "properties": {
    "gn:admin1_code":"15.0",
    "gn:asciiname":"Diolol Yalalbe",
    "gn:country_code":"SN",
    "gn:dem":49,
    "gn:feature_class":"P",
    "gn:feature_code":"PPL",
    "gn:name":"Diolol Yalalb\u00e9",
    "gn:population":0,
    "gn:timezone":"Africa/Dakar",
    "iso:country":"SN",
    "name:und_x_variant":[
        "Yalalble",
        "Yalalb\u00e9",
        "Diolol Yalalb\u00e9"
    ],
    "wof:name":"Diolol Yalalbe",
    "wof:placetype":"locality"
},
  "geometry": {"coordinates":[-13.50298,15.84809],"type":"Point"}
}