{
  "type": "Feature",
  "properties": {
    "gn:admin1_code":"14.0",
    "gn:asciiname":"Mbilor",
    "gn:cc2":"SN",
    "gn:country_code":"SN",
    "gn:dem":4,
    "gn:feature_class":"P",
    "gn:feature_code":"PPL",
    "gn:name":"Mbilor",
    "gn:population":0,
    "gn:timezone":"Africa/Dakar",
    "iso:country":"SN",
    "name:und_x_variant":[
        "N\u2019bilor",
        "M\u2019Billor",
        "Mbilor"
    ],
    "wof:name":"Mbilor",
    "wof:placetype":"locality"
},
  "geometry": {"coordinates":[-15.58333,16.51667],"type":"Point"}
}