{
  "type": "Feature",
  "properties": {
    "gn:admin1_code":"5.0",
    "gn:asciiname":"Niala Baoude",
    "gn:country_code":"SN",
    "gn:dem":56,
    "gn:feature_class":"P",
    "gn:feature_code":"PPL",
    "gn:name":"Niala Baoud\u00e9",
    "gn:population":0,
    "gn:timezone":"Africa/Dakar",
    "iso:country":"SN",
    "wof:name":"Niala Baoude",
    "wof:placetype":"locality"
},
  "geometry": {"coordinates":[-13.73333,14.31667],"type":"Point"}
}