{
  "type": "Feature",
  "properties": {
    "gn:admin1_code":"5.0",
    "gn:asciiname":"Sinntial Maboube",
    "gn:country_code":"SN",
    "gn:dem":62,
    "gn:feature_class":"P",
    "gn:feature_code":"PPL",
    "gn:name":"Sinntial Maboub\u00e9",
    "gn:population":0,
    "gn:timezone":"Africa/Dakar",
    "iso:country":"SN",
    "wof:name":"Sinntial Maboube",
    "wof:placetype":"locality"
},
  "geometry": {"coordinates":[-13.35,14.23333],"type":"Point"}
}