{
  "type": "Feature",
  "properties": {
    "gn:admin1_code":"7.0",
    "gn:asciiname":"Pointe-Sarene",
    "gn:country_code":"SN",
    "gn:dem":-9999,
    "gn:feature_class":"P",
    "gn:feature_code":"PPL",
    "gn:name":"Pointe-Sar\u00e8ne",
    "gn:population":0,
    "gn:timezone":"Africa/Dakar",
    "iso:country":"SN",
    "wof:name":"Pointe-Sarene",
    "wof:placetype":"locality"
},
  "geometry": {"coordinates":[-16.91667,14.28333],"type":"Point"}
}