{
  "type": "Feature",
  "properties": {
    "gn:admin1_code":"16.0",
    "gn:asciiname":"Pete",
    "gn:country_code":"SN",
    "gn:dem":40,
    "gn:feature_class":"P",
    "gn:feature_code":"PPL",
    "gn:name":"P\u00e9t\u00e9",
    "gn:population":0,
    "gn:timezone":"Africa/Dakar",
    "iso:country":"SN",
    "name:ceb_x_preferred":[
        "Pete"
    ],
    "name:fra_x_preferred":[
        "Pete"
    ],
    "name:hun_x_preferred":[
        "Pete"
    ],
    "name:jpn_x_preferred":[
        "\u30d4\u30fc\u30c8"
    ],
    "name:nld_x_preferred":[
        "Pete"
    ],
    "name:spa_x_preferred":[
        "Pete"
    ],
    "name:swe_x_preferred":[
        "Pete"
    ],
    "wof:name":"Pete",
    "wof:placetype":"locality"
},
  "geometry": {"coordinates":[-15.45,14.08333],"type":"Point"}
}