{
  "type": "Feature",
  "properties": {
    "gn:admin1_code":"14.0",
    "gn:asciiname":"Baiti Dieye",
    "gn:cc2":"SN",
    "gn:country_code":"SN",
    "gn:dem":14,
    "gn:feature_class":"P",
    "gn:feature_code":"PPL",
    "gn:name":"Ba\u00efti Di\u00e8ye",
    "gn:population":0,
    "gn:timezone":"Africa/Dakar",
    "iso:country":"SN",
    "name:und_x_variant":[
        "Ba\u00efty",
        "Ba\u00efti Di\u00e8ye"
    ],
    "wof:name":"Baiti Dieye",
    "wof:placetype":"locality"
},
  "geometry": {"coordinates":[-16.38332999999999,15.88333],"type":"Point"}
}