{
  "type": "Feature",
  "properties": {
    "gn:admin1_code":"13.0",
    "gn:asciiname":"Koki",
    "gn:country_code":"SN",
    "gn:dem":54,
    "gn:feature_class":"P",
    "gn:feature_code":"PPL",
    "gn:name":"Koki",
    "gn:population":0,
    "gn:timezone":"Africa/Dakar",
    "iso:country":"SN",
    "name:ceb_x_preferred":[
        "Koki"
    ],
    "name:deu_x_preferred":[
        "Koki"
    ],
    "name:ita_x_preferred":[
        "Koki"
    ],
    "name:jpn_x_preferred":[
        "Koki"
    ],
    "name:swe_x_preferred":[
        "Koki"
    ],
    "name:und_x_variant":[
        "Coki"
    ],
    "wof:lang_x_official":[
        "wol",
        "fra"
    ],
    "wof:lang_x_spoken":[
        "wol",
        "fra"
    ],
    "wof:name":"Koki",
    "wof:placetype":"locality"
},
  "geometry": {"coordinates":[-15.9891,15.5048],"type":"Point"}
}