{
  "type": "Feature",
  "properties": {
    "gn:admin1_code":"14.0",
    "gn:asciiname":"Dirimbodial",
    "gn:country_code":"SN",
    "gn:dem":14,
    "gn:feature_class":"P",
    "gn:feature_code":"PPL",
    "gn:name":"Dirimbodial",
    "gn:population":0,
    "gn:timezone":"Africa/Dakar",
    "iso:country":"SN",
    "name:und_x_variant":[
        "Dirimbodia",
        "Dirimbodial"
    ],
    "wof:name":"Dirimbodial",
    "wof:placetype":"locality"
},
  "geometry": {"coordinates":[-13.79785,16.07771],"type":"Point"}
}