{
  "type": "Feature",
  "properties": {
    "gn:admin1_code":"7.0",
    "gn:asciiname":"Salndewas",
    "gn:country_code":"SN",
    "gn:dem":46,
    "gn:feature_class":"P",
    "gn:feature_code":"PPL",
    "gn:name":"Salnd\u00e9was",
    "gn:population":0,
    "gn:timezone":"Africa/Dakar",
    "iso:country":"SN",
    "wof:name":"Salndewas",
    "wof:placetype":"locality"
},
  "geometry": {"coordinates":[-17.12653,14.74011],"type":"Point"}
}