{
  "type": "Feature",
  "properties": {
    "gn:admin1_code":"3.0",
    "gn:asciiname":"Kalom",
    "gn:cc2":"SN",
    "gn:country_code":"SN",
    "gn:dem":30,
    "gn:feature_class":"P",
    "gn:feature_code":"PPL",
    "gn:name":"Kalom",
    "gn:population":0,
    "gn:timezone":"Africa/Dakar",
    "iso:country":"SN",
    "name:und_x_variant":[
        "Kal\u00f4me",
        "Kalom"
    ],
    "wof:name":"Kalom",
    "wof:placetype":"locality"
},
  "geometry": {"coordinates":[-16.35,14.98333],"type":"Point"}
}