{
  "type": "Feature",
  "properties": {
    "gn:admin1_code":"5.0",
    "gn:asciiname":"Sare Ali",
    "gn:cc2":"SN",
    "gn:country_code":"SN",
    "gn:dem":44,
    "gn:feature_class":"P",
    "gn:feature_code":"PPL",
    "gn:name":"Sar\u00e9 Ali",
    "gn:population":0,
    "gn:timezone":"Africa/Dakar",
    "iso:country":"SN",
    "name:und_x_variant":[
        "Sar\u00e9 All",
        "Sar\u00e9 Ali"
    ],
    "wof:name":"Sare Ali",
    "wof:placetype":"locality"
},
  "geometry": {"coordinates":[-14.21667,13.71667],"type":"Point"}
}