{
  "type": "Feature",
  "properties": {
    "gn:admin1_code":"3.0",
    "gn:asciiname":"Darou Tioum",
    "gn:cc2":"SN",
    "gn:country_code":"SN",
    "gn:dem":37,
    "gn:feature_class":"P",
    "gn:feature_code":"PPL",
    "gn:name":"Darou Tioum",
    "gn:population":0,
    "gn:timezone":"Africa/Dakar",
    "iso:country":"SN",
    "name:und_x_variant":[
        "Darou Tbioum",
        "Darou Tioum"
    ],
    "wof:name":"Darou Tioum",
    "wof:placetype":"locality"
},
  "geometry": {"coordinates":[-16.36667000000001,14.88333],"type":"Point"}
}