{
  "type": "Feature",
  "properties": {
    "gn:admin1_code":"7.0",
    "gn:asciiname":"Ndionguene",
    "gn:country_code":"SN",
    "gn:dem":14,
    "gn:feature_class":"P",
    "gn:feature_code":"PPL",
    "gn:name":"Ndiongu\u00e8ne",
    "gn:population":0,
    "gn:timezone":"Africa/Dakar",
    "iso:country":"SN",
    "wof:name":"Ndionguene",
    "wof:placetype":"locality"
},
  "geometry": {"coordinates":[-16.63332999999999,14.75],"type":"Point"}
}