{
  "type": "Feature",
  "properties": {
    "gn:admin1_code":"11.0",
    "gn:asciiname":"Sare Samba Diaboukoye",
    "gn:country_code":"SN",
    "gn:dem":49,
    "gn:feature_class":"P",
    "gn:feature_code":"PPL",
    "gn:name":"Sar\u00e9 Samba Diaboukoye",
    "gn:population":0,
    "gn:timezone":"Africa/Dakar",
    "iso:country":"SN",
    "wof:name":"Sare Samba Diaboukoye",
    "wof:placetype":"locality"
},
  "geometry": {"coordinates":[-14.91667,12.98333],"type":"Point"}
}