{
  "type": "Feature",
  "properties": {
    "gn:admin1_code":"7.0",
    "gn:asciiname":"Molor",
    "gn:country_code":"SN",
    "gn:dem":16,
    "gn:feature_class":"P",
    "gn:feature_code":"PPL",
    "gn:name":"Molor",
    "gn:population":0,
    "gn:timezone":"Africa/Dakar",
    "iso:country":"SN",
    "wof:name":"Molor",
    "wof:placetype":"locality"
},
  "geometry": {"coordinates":[-16.66667,14.71667],"type":"Point"}
}