{
  "type": "Feature",
  "properties": {
    "gn:admin1_code":"3.0",
    "gn:asciiname":"Sessene",
    "gn:country_code":"SN",
    "gn:dem":16,
    "gn:feature_class":"P",
    "gn:feature_code":"PPL",
    "gn:name":"Sess\u00e8ne",
    "gn:population":0,
    "gn:timezone":"Africa/Dakar",
    "iso:country":"SN",
    "wof:name":"Sessene",
    "wof:placetype":"locality"
},
  "geometry": {"coordinates":[-16.48333,14.61667],"type":"Point"}
}