{
  "type": "Feature",
  "properties": {
    "gn:admin1_code":"11.0",
    "gn:asciiname":"Katio",
    "gn:country_code":"SN",
    "gn:dem":7,
    "gn:feature_class":"P",
    "gn:feature_code":"PPL",
    "gn:name":"Katio",
    "gn:population":0,
    "gn:timezone":"Africa/Dakar",
    "iso:country":"SN",
    "wof:name":"Katio",
    "wof:placetype":"locality"
},
  "geometry": {"coordinates":[-16.36667000000001,12.48333],"type":"Point"}
}