{
  "type": "Feature",
  "properties": {
    "gn:admin1_code":"3.0",
    "gn:asciiname":"Ndindi",
    "gn:country_code":"SN",
    "gn:dem":19,
    "gn:feature_class":"P",
    "gn:feature_code":"PPL",
    "gn:name":"Ndindi",
    "gn:population":0,
    "gn:timezone":"Africa/Dakar",
    "iso:country":"SN",
    "name:fra_x_preferred":[
        "Ndindi"
    ],
    "name:rus_x_preferred":[
        "\u041d\u0434\u0438\u043d\u0434\u0438"
    ],
    "name:spa_x_preferred":[
        "Ndindi"
    ],
    "wof:lang_x_official":[
        "wol",
        "fra"
    ],
    "wof:lang_x_spoken":[
        "wol",
        "fra"
    ],
    "wof:name":"Ndindi",
    "wof:placetype":"locality"
},
  "geometry": {"coordinates":[-16.01667,14.73333],"type":"Point"}
}