{
  "type": "Feature",
  "properties": {
    "gn:admin1_code":"7.0",
    "gn:asciiname":"Kiniabour Deux",
    "gn:country_code":"SN",
    "gn:dem":35,
    "gn:feature_class":"P",
    "gn:feature_code":"PPL",
    "gn:name":"Kiniabour Deux",
    "gn:population":0,
    "gn:timezone":"Africa/Dakar",
    "iso:country":"SN",
    "name:und_x_variant":[
        "Kiniabour Deuxi\u00e9me"
    ],
    "wof:name":"Kiniabour Deux",
    "wof:placetype":"locality"
},
  "geometry": {"coordinates":[-17.05898,14.56877],"type":"Point"}
}