{
  "type": "Feature",
  "properties": {
    "gn:admin1_code":"5.0",
    "gn:asciiname":"Oundoundou Amadou Baba",
    "gn:cc2":"SN",
    "gn:country_code":"SN",
    "gn:dem":52,
    "gn:feature_class":"P",
    "gn:feature_code":"PPL",
    "gn:name":"Oundoundou Amadou Baba",
    "gn:population":0,
    "gn:timezone":"Africa/Dakar",
    "iso:country":"SN",
    "name:und_x_variant":[
        "Oundoundou",
        "Oundoundou Amadou Baba"
    ],
    "wof:lang_x_official":[
        "wol",
        "fra"
    ],
    "wof:lang_x_spoken":[
        "wol",
        "fra"
    ],
    "wof:name":"Oundoundou Amadou Baba",
    "wof:placetype":"locality"
},
  "geometry": {"coordinates":[-13.55,13.66667],"type":"Point"}
}