{
  "type": "Feature",
  "properties": {
    "gn:admin1_code":"5.0",
    "gn:asciiname":"Bantanani",
    "gn:country_code":"SN",
    "gn:dem":64,
    "gn:feature_class":"P",
    "gn:feature_code":"PPL",
    "gn:name":"Bantanani",
    "gn:population":0,
    "gn:timezone":"Africa/Dakar",
    "iso:country":"SN",
    "wof:name":"Bantanani",
    "wof:placetype":"locality"
},
  "geometry": {"coordinates":[-12.97634,13.72193],"type":"Point"}
}