{
  "type": "Feature",
  "properties": {
    "gn:admin1_code":"12.0",
    "gn:asciiname":"Babonda",
    "gn:country_code":"SN",
    "gn:dem":26,
    "gn:feature_class":"P",
    "gn:feature_code":"PPL",
    "gn:name":"Babonda",
    "gn:population":0,
    "gn:timezone":"Africa/Dakar",
    "iso:country":"SN",
    "wof:name":"Babonda",
    "wof:placetype":"locality"
},
  "geometry": {"coordinates":[-16.27083,12.43278],"type":"Point"}
}