{
  "type": "Feature",
  "properties": {
    "gn:admin1_code":"5.0",
    "gn:asciiname":"Guima",
    "gn:country_code":"SN",
    "gn:dem":65,
    "gn:feature_class":"P",
    "gn:feature_code":"PPL",
    "gn:name":"Guima",
    "gn:population":0,
    "gn:timezone":"Africa/Dakar",
    "iso:country":"SN",
    "name:ces_x_preferred":[
        "Guima"
    ],
    "name:rus_x_preferred":[
        "\u0413\u0438\u043c\u0430"
    ],
    "name:slk_x_preferred":[
        "Guima"
    ],
    "wof:name":"Guima",
    "wof:placetype":"locality"
},
  "geometry": {"coordinates":[-12.81174,14.39845],"type":"Point"}
}