{
  "type": "Feature",
  "properties": {
    "gn:admin1_code":"13.0",
    "gn:asciiname":"Sangue",
    "gn:country_code":"SN",
    "gn:dem":50,
    "gn:feature_class":"P",
    "gn:feature_code":"PPL",
    "gn:name":"Sangu\u00e9",
    "gn:population":0,
    "gn:timezone":"Africa/Dakar",
    "iso:country":"SN",
    "name:und_x_variant":[
        "Sanghu\u00e9",
        "Sangu\u00e9"
    ],
    "wof:name":"Sangue",
    "wof:placetype":"locality"
},
  "geometry": {"coordinates":[-15.3845,15.0933],"type":"Point"}
}