{
  "type": "Feature",
  "properties": {
    "gn:admin1_code":"17.0",
    "gn:asciiname":"Wamba",
    "gn:country_code":"SN",
    "gn:dem":177,
    "gn:feature_class":"P",
    "gn:feature_code":"PPL",
    "gn:name":"Wamba",
    "gn:population":0,
    "gn:timezone":"Africa/Dakar",
    "iso:country":"SN",
    "name:und_x_variant":[
        "Wanba",
        "Wamba"
    ],
    "wof:name":"Wamba",
    "wof:placetype":"locality"
},
  "geometry": {"coordinates":[-11.58856,12.48746],"type":"Point"}
}