{
  "type": "Feature",
  "properties": {
    "gn:admin1_code":"17.0",
    "gn:asciiname":"Wamba",
    "gn:country_code":"SN",
    "gn:dem":177,
    "gn:feature_class":"P",
    "gn:feature_code":"PPL",
    "gn:name":"Wamba",
    "gn:population":0,
    "gn:timezone":"Africa/Dakar",
    "iso:country":"SN",
    "name:ceb_x_preferred":[
        "Wamba"
    ],
    "name:deu_x_preferred":[
        "Wamba"
    ],
    "name:eus_x_preferred":[
        "Wamba"
    ],
    "name:fra_x_preferred":[
        "Wamba"
    ],
    "name:glg_x_preferred":[
        "Wamba"
    ],
    "name:hye_x_preferred":[
        "\u054e\u0561\u0574\u0562\u0561"
    ],
    "name:ita_x_preferred":[
        "Wamba"
    ],
    "name:nld_x_preferred":[
        "Wamba"
    ],
    "name:por_x_preferred":[
        "Vamba"
    ],
    "name:ron_x_preferred":[
        "Wamba"
    ],
    "name:rus_x_preferred":[
        "\u0412\u0430\u043c\u0431\u0430"
    ],
    "name:spa_x_preferred":[
        "Wamba"
    ],
    "name:swe_x_preferred":[
        "Wamba"
    ],
    "name:und_x_variant":[
        "Wanba"
    ],
    "name:vie_x_preferred":[
        "Wamba"
    ],
    "name:war_x_preferred":[
        "Wamba"
    ],
    "wof:name":"Wamba",
    "wof:placetype":"locality"
},
  "geometry": {"coordinates":[-11.58856,12.48746],"type":"Point"}
}