{
  "type": "Feature",
  "properties": {
    "gn:admin1_code":"13.0",
    "gn:asciiname":"Gande Ko",
    "gn:country_code":"SN",
    "gn:dem":45,
    "gn:feature_class":"P",
    "gn:feature_code":"PPL",
    "gn:name":"Gand\u00e9 K\u00f4",
    "gn:population":0,
    "gn:timezone":"Africa/Dakar",
    "iso:country":"SN",
    "wof:name":"Gande Ko",
    "wof:placetype":"locality"
},
  "geometry": {"coordinates":[-15.7731,15.5845],"type":"Point"}
}