{
  "type": "Feature",
  "properties": {
    "gn:admin1_code":"13.0",
    "gn:asciiname":"Boukoul",
    "gn:country_code":"SN",
    "gn:dem":54,
    "gn:feature_class":"P",
    "gn:feature_code":"PPL",
    "gn:name":"Boukoul",
    "gn:population":0,
    "gn:timezone":"Africa/Dakar",
    "iso:country":"SN",
    "wof:name":"Boukoul",
    "wof:placetype":"locality"
},
  "geometry": {"coordinates":[-15.9659,15.5121],"type":"Point"}
}