{
  "type": "Feature",
  "properties": {
    "gn:admin1_code":"11.0",
    "gn:asciiname":"Tiankou",
    "gn:country_code":"SN",
    "gn:dem":34,
    "gn:feature_class":"P",
    "gn:feature_code":"PPL",
    "gn:name":"Tiankou",
    "gn:population":0,
    "gn:timezone":"Africa/Dakar",
    "iso:country":"SN",
    "wof:name":"Tiankou",
    "wof:placetype":"locality"
},
  "geometry": {"coordinates":[-13.85,12.91667],"type":"Point"}
}