{
  "type": "Feature",
  "properties": {
    "gn:admin1_code":"12.0",
    "gn:asciiname":"Komboli",
    "gn:cc2":"SN",
    "gn:country_code":"SN",
    "gn:dem":20,
    "gn:feature_class":"P",
    "gn:feature_code":"PPL",
    "gn:name":"Komboli",
    "gn:population":0,
    "gn:timezone":"Africa/Dakar",
    "iso:country":"SN",
    "name:und_x_variant":[
        "Badtionkoto Komboli",
        "Komboli"
    ],
    "wof:lang_x_official":[
        "wol",
        "fra"
    ],
    "wof:lang_x_spoken":[
        "wol",
        "fra"
    ],
    "wof:name":"Komboli",
    "wof:placetype":"locality"
},
  "geometry": {"coordinates":[-16.28333,13.11667],"type":"Point"}
}