{
  "type": "Feature",
  "properties": {
    "gn:admin1_code":"18.0",
    "gn:asciiname":"Baghanga",
    "gn:country_code":"SN",
    "gn:dem":24,
    "gn:feature_class":"P",
    "gn:feature_code":"PPL",
    "gn:name":"Baghanga",
    "gn:population":0,
    "gn:timezone":"Africa/Dakar",
    "iso:country":"SN",
    "name:und_x_variant":[
        "Baganga",
        "Baghanga"
    ],
    "wof:name":"Baghanga",
    "wof:placetype":"locality"
},
  "geometry": {"coordinates":[-15.98333,12.73333],"type":"Point"}
}