{
  "type": "Feature",
  "properties": {
    "gn:admin1_code":"1.0",
    "gn:asciiname":"Mbaw",
    "gn:country_code":"SN",
    "gn:dem":5,
    "gn:feature_class":"P",
    "gn:feature_code":"PPL",
    "gn:name":"Mbaw",
    "gn:population":0,
    "gn:timezone":"Africa/Dakar",
    "iso:country":"SN",
    "name:und_x_variant":[
        "Grand Mbao",
        "M\u2019Ba\u00f4",
        "Mbaw",
        "M'bao"
    ],
    "wof:name":"Mbaw",
    "wof:placetype":"locality"
},
  "geometry": {"coordinates":[-17.3274,14.73192],"type":"Point"}
}