{
  "type": "Feature",
  "properties": {
    "iso:country":"SN",
    "name:fra_x_preferred":[
        "Pout"
    ],
    "name:und_x_variant":[
        "Put"
    ],
    "qs:gn_country":"SN",
    "qs:gn_fcode":"PPL",
    "qs:gn_pop":17752,
    "qs:name":"Pout",
    "qs:name_adm0":"S\u00e9n\u00e9gal",
    "qs:name_adm1":"Thi\u00e8s",
    "qs:photos":0,
    "qs:photos_1k":0,
    "qs:photos_9k":1,
    "qs:photos_9r":1,
    "qs:photos_all":1,
    "qs:photos_sr":0,
    "qs:placetype":"Town",
    "qs:pop_sr":"6",
    "qs:woe_adm0":23424943,
    "wd:wordcount":71,
    "wof:name":"Pout",
    "wof:placetype":"locality",
    "wof:population":17752
},
  "geometry": {"coordinates":[-17.06107,14.77099],"type":"Point"}
}