{
  "type": "Feature",
  "properties": {
    "gn:admin1_code":"5.0",
    "gn:asciiname":"Bantangueul",
    "gn:country_code":"SN",
    "gn:dem":25,
    "gn:feature_class":"P",
    "gn:feature_code":"PPL",
    "gn:name":"Bantangueul",
    "gn:population":0,
    "gn:timezone":"Africa/Dakar",
    "iso:country":"SN",
    "wof:name":"Bantangueul",
    "wof:placetype":"locality"
},
  "geometry": {"coordinates":[-14.01667,13.96667],"type":"Point"}
}