{
  "type": "Feature",
  "properties": {
    "gn:admin1_code":"5.0",
    "gn:asciiname":"Sayansoutou",
    "gn:country_code":"SN",
    "gn:dem":80,
    "gn:feature_class":"P",
    "gn:feature_code":"PPL",
    "gn:name":"Sayansoutou",
    "gn:population":0,
    "gn:timezone":"Africa/Dakar",
    "iso:country":"SN",
    "name:und_x_variant":[
        "Sa\u00efsoutou",
        "Sa\u00efnsoutou",
        "Sayansoutou"
    ],
    "wof:name":"Sayansoutou",
    "wof:placetype":"locality"
},
  "geometry": {"coordinates":[-11.64424,13.39143],"type":"Point"}
}