{
  "type": "Feature",
  "properties": {
    "gn:admin1_code":"7.0",
    "gn:asciiname":"Keur Sini Diao",
    "gn:cc2":"SN",
    "gn:country_code":"SN",
    "gn:dem":33,
    "gn:feature_class":"P",
    "gn:feature_code":"PPL",
    "gn:name":"Keur Sini Diao",
    "gn:population":0,
    "gn:timezone":"Africa/Dakar",
    "iso:country":"SN",
    "name:und_x_variant":[
        "Keur Simi Diao",
        "Keur Sini Diao"
    ],
    "wof:name":"Keur Sini Diao",
    "wof:placetype":"locality"
},
  "geometry": {"coordinates":[-16.35,15.11667],"type":"Point"}
}