{
  "type": "Feature",
  "properties": {
    "gn:admin1_code":"3.0",
    "gn:asciiname":"Dimbou",
    "gn:cc2":"SN",
    "gn:country_code":"SN",
    "gn:dem":38,
    "gn:feature_class":"P",
    "gn:feature_code":"PPL",
    "gn:name":"Dimbou",
    "gn:population":0,
    "gn:timezone":"Africa/Dakar",
    "iso:country":"SN",
    "name:und_x_variant":[
        "Ndimbou",
        "Dimbou"
    ],
    "wof:name":"Dimbou",
    "wof:placetype":"locality"
},
  "geometry": {"coordinates":[-16.26667,14.85],"type":"Point"}
}