{
  "type": "Feature",
  "properties": {
    "gn:admin1_code":"13.0",
    "gn:asciiname":"Ndialo",
    "gn:cc2":"SN",
    "gn:country_code":"SN",
    "gn:dem":39,
    "gn:feature_class":"P",
    "gn:feature_code":"PPL",
    "gn:name":"Ndialo",
    "gn:population":0,
    "gn:timezone":"Africa/Dakar",
    "iso:country":"SN",
    "name:und_x_variant":[
        "N\u2019Dialor",
        "Ndialo"
    ],
    "wof:name":"Ndialo",
    "wof:placetype":"locality"
},
  "geometry": {"coordinates":[-16.31667,15.38333],"type":"Point"}
}