{
  "type": "Feature",
  "properties": {
    "gn:admin1_code":"16.0",
    "gn:asciiname":"Allouki",
    "gn:country_code":"SN",
    "gn:dem":16,
    "gn:feature_class":"P",
    "gn:feature_code":"PPL",
    "gn:name":"Allouki",
    "gn:population":0,
    "gn:timezone":"Africa/Dakar",
    "iso:country":"SN",
    "wof:name":"Allouki",
    "wof:placetype":"locality"
},
  "geometry": {"coordinates":[-15.38333,14.18333],"type":"Point"}
}