{
  "type": "Feature",
  "properties": {
    "gn:admin1_code":"12.0",
    "gn:asciiname":"Boudody Escale",
    "gn:country_code":"SN",
    "gn:dem":10,
    "gn:feature_class":"P",
    "gn:feature_code":"PPLL",
    "gn:name":"Boudody Escale",
    "gn:population":0,
    "gn:timezone":"Africa/Dakar",
    "iso:country":"SN",
    "wof:name":"Boudody Escale",
    "wof:placetype":"locality"
},
  "geometry": {"coordinates":[-16.27056,12.58528],"type":"Point"}
}