{
  "type": "Feature",
  "properties": {
    "gn:admin1_code":"13.0",
    "gn:asciiname":"Mogre",
    "gn:country_code":"SN",
    "gn:dem":16,
    "gn:feature_class":"P",
    "gn:feature_code":"PPL",
    "gn:name":"Mogr\u00e9",
    "gn:population":0,
    "gn:timezone":"Africa/Dakar",
    "iso:country":"SN",
    "name:und_x_variant":[
        "Maugr\u00e9",
        "Mogr\u00e9"
    ],
    "wof:name":"Mogre",
    "wof:placetype":"locality"
},
  "geometry": {"coordinates":[-15.024,15.3184],"type":"Point"}
}