{
  "type": "Feature",
  "properties": {
    "gn:admin1_code":"5.0",
    "gn:asciiname":"Diana",
    "gn:country_code":"SN",
    "gn:dem":48,
    "gn:feature_class":"P",
    "gn:feature_code":"PPL",
    "gn:name":"Diana",
    "gn:population":0,
    "gn:timezone":"Africa/Dakar",
    "iso:country":"SN",
    "name:und_x_variant":[
        "Dianra",
        "Diana"
    ],
    "wof:name":"Diana",
    "wof:placetype":"locality"
},
  "geometry": {"coordinates":[-12.86194,13.53981],"type":"Point"}
}