{
  "type": "Feature",
  "properties": {
    "iso:country":"SN",
    "name:ara_x_preferred":[
        "\u062a\u064a\u0641\u0648\u0627\u0646"
    ],
    "name:deu_x_preferred":[
        "Tivaouane"
    ],
    "name:eng_x_preferred":[
        "Tivaouane"
    ],
    "name:fra_x_preferred":[
        "Tivaouane"
    ],
    "name:hun_x_preferred":[
        "Tivaouane"
    ],
    "name:ita_x_preferred":[
        "Tivaouane"
    ],
    "name:jpn_x_preferred":[
        "\u30c6\u30a3\u30d0\u30ef\u30f3"
    ],
    "name:nld_x_preferred":[
        "Tivaouane"
    ],
    "name:pol_x_preferred":[
        "Tivaouane"
    ],
    "name:por_x_preferred":[
        "Tivaouane"
    ],
    "name:rus_x_preferred":[
        "\u0422\u0438\u0432\u0430\u0443\u0430\u043d"
    ],
    "name:swe_x_preferred":[
        "Tivaouane"
    ],
    "name:und_x_variant":[
        "Tiwawan"
    ],
    "name:zho_x_preferred":[
        "\u8482\u74e6\u74e6\u5167"
    ],
    "qs:gn_country":"SN",
    "qs:gn_fcode":"PPL",
    "qs:gn_pop":0,
    "qs:name":"Tivaouane",
    "qs:name_adm0":"S\u00e9n\u00e9gal",
    "qs:name_adm1":"Thi\u00e8s",
    "qs:photos":25,
    "qs:photos_1k":5,
    "qs:photos_9k":1,
    "qs:photos_9r":1,
    "qs:photos_all":25,
    "qs:photos_sr":1,
    "qs:placetype":"Town",
    "qs:pop_sr":"0",
    "qs:woe_adm0":23424943,
    "wd:wordcount":374,
    "wof:lang_x_official":[
        "wol",
        "fra"
    ],
    "wof:lang_x_spoken":[
        "wol",
        "fra"
    ],
    "wof:name":"Tivaouane",
    "wof:placetype":"locality"
},
  "geometry": {"coordinates":[-16.93972,14.97444],"type":"Point"}
}