{
  "type": "Feature",
  "properties": {
    "gn:admin1_code":"15.0",
    "gn:asciiname":"Tiatol",
    "gn:country_code":"SN",
    "gn:dem":41,
    "gn:feature_class":"P",
    "gn:feature_code":"PPL",
    "gn:name":"Tiatol",
    "gn:population":0,
    "gn:timezone":"Africa/Dakar",
    "iso:country":"SN",
    "wof:name":"Tiatol",
    "wof:placetype":"locality"
},
  "geometry": {"coordinates":[-14.2743,15.0048],"type":"Point"}
}