{
  "type": "Feature",
  "properties": {
    "gn:admin1_code":"1.0",
    "gn:asciiname":"Hann-Plage",
    "gn:country_code":"SN",
    "gn:dem":14,
    "gn:feature_class":"P",
    "gn:feature_code":"PPL",
    "gn:name":"Hann-Plage",
    "gn:population":0,
    "gn:timezone":"Africa/Dakar",
    "iso:country":"SN",
    "wof:name":"Hann-Plage",
    "wof:placetype":"locality"
},
  "geometry": {"coordinates":[-17.43643,14.71984],"type":"Point"}
}