{
  "type": "Feature",
  "properties": {
    "gn:admin1_code":"9.0",
    "gn:asciiname":"Simal",
    "gn:cc2":"SN",
    "gn:country_code":"SN",
    "gn:dem":3,
    "gn:feature_class":"P",
    "gn:feature_code":"PPL",
    "gn:name":"Simal",
    "gn:population":0,
    "gn:timezone":"Africa/Dakar",
    "iso:country":"SN",
    "name:ceb_x_preferred":[
        "Simal"
    ],
    "name:swe_x_preferred":[
        "Simal"
    ],
    "name:und_x_variant":[
        "Simel"
    ],
    "wof:name":"Simal",
    "wof:placetype":"locality"
},
  "geometry": {"coordinates":[-16.65,14.15],"type":"Point"}
}