{
  "type": "Feature",
  "properties": {
    "gn:admin1_code":"16.0",
    "gn:asciiname":"Taba",
    "gn:country_code":"SN",
    "gn:dem":26,
    "gn:feature_class":"P",
    "gn:feature_code":"PPL",
    "gn:name":"Taba",
    "gn:population":0,
    "gn:timezone":"Africa/Dakar",
    "iso:country":"SN",
    "name:ceb_x_preferred":[
        "Taba"
    ],
    "name:deu_x_preferred":[
        "Taba"
    ],
    "name:fra_x_preferred":[
        "Taba"
    ],
    "name:nld_x_preferred":[
        "Taba"
    ],
    "name:spa_x_preferred":[
        "Taba"
    ],
    "name:swe_x_preferred":[
        "Taba"
    ],
    "wof:lang_x_official":[
        "wol",
        "fra"
    ],
    "wof:lang_x_spoken":[
        "wol",
        "fra"
    ],
    "wof:name":"Taba",
    "wof:placetype":"locality"
},
  "geometry": {"coordinates":[-14.98333,14.28333],"type":"Point"}
}