{
  "type": "Feature",
  "properties": {
    "gn:admin1_code":"13.0",
    "gn:asciiname":"Bouli",
    "gn:country_code":"SN",
    "gn:dem":47,
    "gn:feature_class":"P",
    "gn:feature_code":"PPL",
    "gn:name":"Bouli",
    "gn:population":0,
    "gn:timezone":"Africa/Dakar",
    "iso:country":"SN",
    "name:dan_x_preferred":[
        "Bouli"
    ],
    "name:fra_x_preferred":[
        "Bouli"
    ],
    "name:pol_x_preferred":[
        "Bouli"
    ],
    "name:wuu_x_preferred":[
        "\u96ea\u4eba\u6ce2\u5229"
    ],
    "name:zho_x_preferred":[
        "\u96ea\u4eba\u6ce2\u5229"
    ],
    "wof:lang_x_official":[
        "wol",
        "fra"
    ],
    "wof:lang_x_spoken":[
        "wol",
        "fra"
    ],
    "wof:name":"Bouli",
    "wof:placetype":"locality"
},
  "geometry": {"coordinates":[-15.8297,15.5384],"type":"Point"}
}