{
  "type": "Feature",
  "properties": {
    "gn:admin1_code":"12.0",
    "gn:asciiname":"Diegoun",
    "gn:cc2":"SN",
    "gn:country_code":"SN",
    "gn:dem":14,
    "gn:feature_class":"P",
    "gn:feature_code":"PPL",
    "gn:name":"Di\u00e9goun",
    "gn:population":0,
    "gn:timezone":"Africa/Dakar",
    "iso:country":"SN",
    "name:und_x_variant":[
        "Diagouine",
        "Di\u00e9goune",
        "Diagoune",
        "Diagoun",
        "Di\u00e9goun"
    ],
    "wof:name":"Diegoun",
    "wof:placetype":"locality"
},
  "geometry": {"coordinates":[-16.3675,12.83667],"type":"Point"}
}