{
  "type": "Feature",
  "properties": {
    "gn:admin1_code":"13.0",
    "gn:asciiname":"Belkagne",
    "gn:country_code":"SN",
    "gn:dem":32,
    "gn:feature_class":"P",
    "gn:feature_code":"PPL",
    "gn:name":"Belkagne",
    "gn:population":0,
    "gn:timezone":"Africa/Dakar",
    "iso:country":"SN",
    "wof:name":"Belkagne",
    "wof:placetype":"locality"
},
  "geometry": {"coordinates":[-14.8637,15.4171],"type":"Point"}
}