{
  "type": "Feature",
  "properties": {
    "gn:admin1_code":"15.0",
    "gn:asciiname":"Mayel Ndangam",
    "gn:country_code":"SN",
    "gn:dem":72,
    "gn:feature_class":"P",
    "gn:feature_code":"PPL",
    "gn:name":"Mayel Ndangam",
    "gn:population":0,
    "gn:timezone":"Africa/Dakar",
    "iso:country":"SN",
    "wof:name":"Mayel Ndangam",
    "wof:placetype":"locality"
},
  "geometry": {"coordinates":[-12.90869,14.68487],"type":"Point"}
}