{
  "type": "Feature",
  "properties": {
    "gn:admin1_code":"14.0",
    "gn:asciiname":"Kope",
    "gn:country_code":"SN",
    "gn:dem":4,
    "gn:feature_class":"P",
    "gn:feature_code":"PPL",
    "gn:name":"Kop\u00e9",
    "gn:population":0,
    "gn:timezone":"Africa/Dakar",
    "iso:country":"SN",
    "wof:name":"Kope",
    "wof:placetype":"locality"
},
  "geometry": {"coordinates":[-14.81774,16.57784],"type":"Point"}
}