{
  "type": "Feature",
  "properties": {
    "gn:admin1_code":"5.0",
    "gn:asciiname":"Maka",
    "gn:cc2":"SN",
    "gn:country_code":"SN",
    "gn:dem":11,
    "gn:feature_class":"P",
    "gn:feature_code":"PPL",
    "gn:name":"Maka",
    "gn:population":0,
    "gn:timezone":"Africa/Dakar",
    "iso:country":"SN",
    "name:ceb_x_preferred":[
        "Maka"
    ],
    "name:deu_x_preferred":[
        "Maka"
    ],
    "name:fra_x_preferred":[
        "Maka"
    ],
    "name:ita_x_preferred":[
        "Maka"
    ],
    "name:jpn_x_preferred":[
        "\u30de\u30ab"
    ],
    "name:rus_x_preferred":[
        "\u041c\u0430\u043a\u0430"
    ],
    "name:slk_x_preferred":[
        "Maka"
    ],
    "name:swe_x_preferred":[
        "Maka"
    ],
    "name:und_x_variant":[
        "Maka-Colibentan"
    ],
    "wof:lang_x_official":[
        "wol",
        "fra"
    ],
    "wof:lang_x_spoken":[
        "wol",
        "fra"
    ],
    "wof:name":"Maka",
    "wof:placetype":"locality"
},
  "geometry": {"coordinates":[-14.28333,13.66667],"type":"Point"}
}