{
  "type": "Feature",
  "properties": {
    "gn:admin1_code":"5.0",
    "gn:asciiname":"Maka",
    "gn:cc2":"SN",
    "gn:country_code":"SN",
    "gn:dem":11,
    "gn:feature_class":"P",
    "gn:feature_code":"PPL",
    "gn:name":"Maka",
    "gn:population":0,
    "gn:timezone":"Africa/Dakar",
    "iso:country":"SN",
    "name:und_x_variant":[
        "Maka-Colibentan",
        "Maka"
    ],
    "wof:name":"Maka",
    "wof:placetype":"locality"
},
  "geometry": {"coordinates":[-14.28333,13.66667],"type":"Point"}
}