{
  "type": "Feature",
  "properties": {
    "gn:admin1_code":"12.0",
    "gn:asciiname":"Batinier",
    "gn:cc2":"SN",
    "gn:country_code":"SN",
    "gn:dem":4,
    "gn:feature_class":"P",
    "gn:feature_code":"PPL",
    "gn:name":"Batini\u00e8r",
    "gn:population":0,
    "gn:timezone":"Africa/Dakar",
    "iso:country":"SN",
    "name:fra_x_preferred":[
        "Batini\u00e8re"
    ],
    "name:und_x_variant":[
        "Batini\u00e8r"
    ],
    "wof:lang_x_official":[
        "wol",
        "fra"
    ],
    "wof:lang_x_spoken":[
        "wol",
        "fra"
    ],
    "wof:name":"Batinier",
    "wof:placetype":"locality"
},
  "geometry": {"coordinates":[-16.48306,12.50083],"type":"Point"}
}