{
  "type": "Feature",
  "properties": {
    "gn:admin1_code":"9.0",
    "gn:asciiname":"Guidine",
    "gn:cc2":"SN",
    "gn:country_code":"SN",
    "gn:dem":9,
    "gn:feature_class":"P",
    "gn:feature_code":"PPL",
    "gn:name":"Guidine",
    "gn:population":0,
    "gn:timezone":"Africa/Dakar",
    "iso:country":"SN",
    "name:und_x_variant":[
        "Guindine",
        "Guindin",
        "Guirdine",
        "Guidine"
    ],
    "wof:name":"Guidine",
    "wof:placetype":"locality"
},
  "geometry": {"coordinates":[-16.33333,14.31667],"type":"Point"}
}