{
  "type": "Feature",
  "properties": {
    "gn:admin1_code":"17.0",
    "gn:asciiname":"Dar Salam",
    "gn:country_code":"SN",
    "gn:dem":163,
    "gn:feature_class":"P",
    "gn:feature_code":"PPL",
    "gn:name":"Dar Salam",
    "gn:population":0,
    "gn:timezone":"Africa/Dakar",
    "iso:country":"SN",
    "name:und_x_variant":[
        "Dar-Salem",
        "Darasalam",
        "Dar Salam"
    ],
    "wof:lang_x_official":[
        "wol",
        "fra"
    ],
    "wof:lang_x_spoken":[
        "wol",
        "fra"
    ],
    "wof:name":"Dar Salam",
    "wof:placetype":"locality"
},
  "geometry": {"coordinates":[-11.67065,12.55106],"type":"Point"}
}