{
  "type": "Feature",
  "properties": {
    "gn:admin1_code":"18.0",
    "gn:asciiname":"Sakar",
    "gn:country_code":"SN",
    "gn:dem":11,
    "gn:feature_class":"P",
    "gn:feature_code":"PPL",
    "gn:name":"Sakar",
    "gn:population":0,
    "gn:timezone":"Africa/Dakar",
    "iso:country":"SN",
    "name:ceb_x_preferred":[
        "Sakar"
    ],
    "name:chu_x_preferred":[
        "\u0421\u0430\u043a\u0430\u0440\u044a"
    ],
    "name:deu_x_preferred":[
        "Sakar"
    ],
    "name:fra_x_preferred":[
        "Sakar"
    ],
    "name:nld_x_preferred":[
        "Sakar"
    ],
    "name:swe_x_preferred":[
        "Sakar"
    ],
    "wof:name":"Sakar",
    "wof:placetype":"locality"
},
  "geometry": {"coordinates":[-15.44083,12.84139],"type":"Point"}
}