{
  "type": "Feature",
  "properties": {
    "gn:admin1_code":"7.0",
    "gn:asciiname":"Sali Portudal",
    "gn:country_code":"SN",
    "gn:dem":12,
    "gn:feature_class":"P",
    "gn:feature_code":"PPL",
    "gn:name":"Sali Portudal",
    "gn:population":0,
    "gn:timezone":"Africa/Dakar",
    "iso:country":"SN",
    "name:und_x_variant":[
        "Pordudal",
        "Sali Portudal",
        "Sali Pordudal",
        "Portudal",
        "Sali-Portugal"
    ],
    "wof:name":"Sali Portudal",
    "wof:placetype":"locality"
},
  "geometry": {"coordinates":[-17.01679,14.44444],"type":"Point"}
}