{
  "type": "Feature",
  "properties": {
    "gn:admin1_code":"10.0",
    "gn:asciiname":"Keur Mboussi",
    "gn:country_code":"SN",
    "gn:dem":26,
    "gn:feature_class":"P",
    "gn:feature_code":"PPL",
    "gn:name":"Keur Mboussi",
    "gn:population":0,
    "gn:timezone":"Africa/Dakar",
    "iso:country":"SN",
    "wof:name":"Keur Mboussi",
    "wof:placetype":"locality"
},
  "geometry": {"coordinates":[-15.86667,14.05],"type":"Point"}
}