{
  "type": "Feature",
  "properties": {
    "gn:admin1_code":"17.0",
    "gn:asciiname":"Mamankanti",
    "gn:country_code":"SN",
    "gn:dem":93,
    "gn:feature_class":"P",
    "gn:feature_code":"PPL",
    "gn:name":"Mamankanti",
    "gn:population":0,
    "gn:timezone":"Africa/Dakar",
    "iso:country":"SN",
    "name:und_x_variant":[
        "Mamankanu",
        "Maniankanti",
        "Mamankanti"
    ],
    "wof:lang_x_official":[
        "wol",
        "fra"
    ],
    "wof:lang_x_spoken":[
        "wol",
        "fra"
    ],
    "wof:name":"Mamankanti",
    "wof:placetype":"locality"
},
  "geometry": {"coordinates":[-12.4423,12.7994],"type":"Point"}
}