{
  "type": "Feature",
  "properties": {
    "gn:admin1_code":"10.0",
    "gn:asciiname":"Tioubene",
    "gn:cc2":"SN",
    "gn:country_code":"SN",
    "gn:dem":29,
    "gn:feature_class":"P",
    "gn:feature_code":"PPL",
    "gn:name":"Tioub\u00e8ne",
    "gn:population":0,
    "gn:timezone":"Africa/Dakar",
    "iso:country":"SN",
    "name:und_x_variant":[
        "Tioubb\u00e9ne",
        "Tioub\u00e8ne"
    ],
    "wof:name":"Tioubene",
    "wof:placetype":"locality"
},
  "geometry": {"coordinates":[-15.98333,13.81667],"type":"Point"}
}