{
  "type": "Feature",
  "properties": {
    "gn:admin1_code":"11.0",
    "gn:asciiname":"Pidiro",
    "gn:country_code":"SN",
    "gn:dem":34,
    "gn:feature_class":"P",
    "gn:feature_code":"PPL",
    "gn:name":"Pidiro",
    "gn:population":0,
    "gn:timezone":"Africa/Dakar",
    "iso:country":"SN",
    "wof:name":"Pidiro",
    "wof:placetype":"locality"
},
  "geometry": {"coordinates":[-14.31667,12.83333],"type":"Point"}
}