{
  "type": "Feature",
  "properties": {
    "gn:admin1_code":"12.0",
    "gn:asciiname":"Kedieto",
    "gn:cc2":"SN",
    "gn:country_code":"SN",
    "gn:dem":8,
    "gn:feature_class":"P",
    "gn:feature_code":"PPL",
    "gn:name":"K\u00e9di\u00e9to",
    "gn:population":0,
    "gn:timezone":"Africa/Dakar",
    "iso:country":"SN",
    "name:und_x_variant":[
        "K\u00e9di\u00e9la",
        "K\u00e9di\u00e9to"
    ],
    "wof:lang_x_official":[
        "wol",
        "fra"
    ],
    "wof:lang_x_spoken":[
        "wol",
        "fra"
    ],
    "wof:name":"Kedieto",
    "wof:placetype":"locality"
},
  "geometry": {"coordinates":[-16.39194,12.67639],"type":"Point"}
}