{
  "type": "Feature",
  "properties": {
    "gn:admin1_code":"11.0",
    "gn:asciiname":"Tiatamine",
    "gn:country_code":"SN",
    "gn:dem":70,
    "gn:feature_class":"P",
    "gn:feature_code":"PPL",
    "gn:name":"Tiatamine",
    "gn:population":0,
    "gn:timezone":"Africa/Dakar",
    "iso:country":"SN",
    "wof:name":"Tiatamine",
    "wof:placetype":"locality"
},
  "geometry": {"coordinates":[-13.86667,12.78333],"type":"Point"}
}