{
  "type": "Feature",
  "properties": {
    "gn:admin1_code":"15.0",
    "gn:asciiname":"Ndouloumadji Founebe",
    "gn:country_code":"SN",
    "gn:dem":24,
    "gn:feature_class":"P",
    "gn:feature_code":"PPL",
    "gn:name":"Ndouloumadji Foun\u00e9b\u00e9",
    "gn:population":0,
    "gn:timezone":"Africa/Dakar",
    "iso:country":"SN",
    "name:und_x_variant":[
        "Ndouloumadji Foun\u00e9b\u00e9",
        "Ndouloum Adji Foun\u00e9b\u00e9"
    ],
    "wof:name":"Ndouloumadji Founebe",
    "wof:placetype":"locality"
},
  "geometry": {"coordinates":[-13.42471,15.82034],"type":"Point"}
}