{
  "type": "Feature",
  "properties": {
    "gn:admin1_code":"12.0",
    "gn:asciiname":"Boutolate",
    "gn:cc2":"SN",
    "gn:country_code":"SN",
    "gn:dem":18,
    "gn:feature_class":"P",
    "gn:feature_code":"PPL",
    "gn:name":"Boutolate",
    "gn:population":0,
    "gn:timezone":"Africa/Dakar",
    "iso:country":"SN",
    "name:und_x_variant":[
        "Boutolat",
        "Boutolate"
    ],
    "wof:name":"Boutolate",
    "wof:placetype":"locality"
},
  "geometry": {"coordinates":[-16.22167,12.83306],"type":"Point"}
}