{
  "type": "Feature",
  "properties": {
    "gn:admin1_code":"16.0",
    "gn:asciiname":"Nganda",
    "gn:country_code":"SN",
    "gn:dem":41,
    "gn:feature_class":"P",
    "gn:feature_code":"PPL",
    "gn:name":"Nganda",
    "gn:population":0,
    "gn:timezone":"Africa/Dakar",
    "iso:country":"SN",
    "name:deu_x_preferred":[
        "Nganda"
    ],
    "name:fra_x_preferred":[
        "Nganda"
    ],
    "wof:name":"Nganda",
    "wof:placetype":"locality"
},
  "geometry": {"coordinates":[-15.41667,13.83333],"type":"Point"}
}