{
  "type": "Feature",
  "properties": {
    "gn:admin1_code":"9.0",
    "gn:asciiname":"Keur Momar Sona",
    "gn:country_code":"SN",
    "gn:dem":22,
    "gn:feature_class":"P",
    "gn:feature_code":"PPL",
    "gn:name":"Keur Momar Sona",
    "gn:population":0,
    "gn:timezone":"Africa/Dakar",
    "iso:country":"SN",
    "wof:name":"Keur Momar Sona",
    "wof:placetype":"locality"
},
  "geometry": {"coordinates":[-16.28333,13.63333],"type":"Point"}
}