{
  "type": "Feature",
  "properties": {
    "gn:admin1_code":"17.0",
    "gn:asciiname":"Bounsankhoba",
    "gn:country_code":"SN",
    "gn:dem":156,
    "gn:feature_class":"P",
    "gn:feature_code":"PPL",
    "gn:name":"Bounsankhoba",
    "gn:population":0,
    "gn:timezone":"Africa/Dakar",
    "iso:country":"SN",
    "name:und_x_variant":[
        "Bounsankoba",
        "Bounsankhoba"
    ],
    "wof:name":"Bounsankhoba",
    "wof:placetype":"locality"
},
  "geometry": {"coordinates":[-12.0239,12.86],"type":"Point"}
}