{
  "type": "Feature",
  "properties": {
    "gn:admin1_code":"15.0",
    "gn:asciiname":"Manael",
    "gn:country_code":"SN",
    "gn:dem":27,
    "gn:feature_class":"P",
    "gn:feature_code":"PPL",
    "gn:name":"Mana\u00e8l",
    "gn:population":0,
    "gn:timezone":"Africa/Dakar",
    "iso:country":"SN",
    "wof:name":"Manael",
    "wof:placetype":"locality"
},
  "geometry": {"coordinates":[-12.5022,15.01155],"type":"Point"}
}