{
  "type": "Feature",
  "properties": {
    "gn:admin1_code":"14.0",
    "gn:asciiname":"Dembe",
    "gn:country_code":"SN",
    "gn:dem":10,
    "gn:feature_class":"P",
    "gn:feature_code":"PPL",
    "gn:name":"Demb\u00e9",
    "gn:population":0,
    "gn:timezone":"Africa/Dakar",
    "iso:country":"SN",
    "name:ceb_x_preferred":[
        "Dembe"
    ],
    "name:swe_x_preferred":[
        "Dembe"
    ],
    "name:und_x_variant":[
        "Danb\u00e9",
        "Demb\u00e9"
    ],
    "wof:name":"Dembe",
    "wof:placetype":"locality"
},
  "geometry": {"coordinates":[-14.57084,16.54202],"type":"Point"}
}