{
  "type": "Feature",
  "properties": {
    "gn:admin1_code":"11.0",
    "gn:asciiname":"Tougoude",
    "gn:cc2":"SN",
    "gn:country_code":"SN",
    "gn:dem":29,
    "gn:feature_class":"P",
    "gn:feature_code":"PPL",
    "gn:name":"Tougoud\u00e9",
    "gn:population":0,
    "gn:timezone":"Africa/Dakar",
    "iso:country":"SN",
    "name:und_x_variant":[
        "Maoub\u00e9",
        "Tougod\u00e9 Maoud\u00e9",
        "Tougoud\u00e9 Maoud\u00e9",
        "Tougoud\u00e9"
    ],
    "wof:lang_x_official":[
        "wol",
        "fra"
    ],
    "wof:lang_x_spoken":[
        "wol",
        "fra"
    ],
    "wof:name":"Tougoude",
    "wof:placetype":"locality"
},
  "geometry": {"coordinates":[-15.05,13.25],"type":"Point"}
}