{
  "type": "Feature",
  "properties": {
    "gn:admin1_code":"5.0",
    "gn:asciiname":"Dabala",
    "gn:country_code":"SN",
    "gn:dem":58,
    "gn:feature_class":"P",
    "gn:feature_code":"PPL",
    "gn:name":"Dabala",
    "gn:population":0,
    "gn:timezone":"Africa/Dakar",
    "iso:country":"SN",
    "wof:name":"Dabala",
    "wof:placetype":"locality"
},
  "geometry": {"coordinates":[-12.87588,13.37124],"type":"Point"}
}