{
  "type": "Feature",
  "properties": {
    "gn:admin1_code":"12.0",
    "gn:asciiname":"Samik Mandjak",
    "gn:cc2":"SN",
    "gn:country_code":"SN",
    "gn:dem":32,
    "gn:feature_class":"P",
    "gn:feature_code":"PPL",
    "gn:name":"Samik Mandjak",
    "gn:population":0,
    "gn:timezone":"Africa/Dakar",
    "iso:country":"SN",
    "name:und_x_variant":[
        "Samlik Mandjak",
        "Samik Mandjak"
    ],
    "wof:name":"Samik Mandjak",
    "wof:placetype":"locality"
},
  "geometry": {"coordinates":[-16.04444,12.48417],"type":"Point"}
}