{
  "type": "Feature",
  "properties": {
    "gn:admin1_code":"3.0",
    "gn:asciiname":"Beto",
    "gn:country_code":"SN",
    "gn:dem":45,
    "gn:feature_class":"P",
    "gn:feature_code":"PPL",
    "gn:name":"B\u00e9to",
    "gn:population":0,
    "gn:timezone":"Africa/Dakar",
    "iso:country":"SN",
    "name:heb_x_preferred":[
        "\u05d1\u05d8\u05d5"
    ],
    "wof:name":"Beto",
    "wof:placetype":"locality"
},
  "geometry": {"coordinates":[-15.96667,14.85],"type":"Point"}
}