{
  "type": "Feature",
  "properties": {
    "gn:admin1_code":"13.0",
    "gn:asciiname":"Tiouniel",
    "gn:country_code":"SN",
    "gn:dem":52,
    "gn:feature_class":"P",
    "gn:feature_code":"PPL",
    "gn:name":"Tiouniel",
    "gn:population":0,
    "gn:timezone":"Africa/Dakar",
    "iso:country":"SN",
    "wof:name":"Tiouniel",
    "wof:placetype":"locality"
},
  "geometry": {"coordinates":[-15.8768,15.1109],"type":"Point"}
}