{
  "type": "Feature",
  "properties": {
    "gn:admin1_code":"16.0",
    "gn:asciiname":"Touba Ngouye",
    "gn:country_code":"SN",
    "gn:dem":17,
    "gn:feature_class":"P",
    "gn:feature_code":"PPL",
    "gn:name":"Touba Ngouye",
    "gn:population":0,
    "gn:timezone":"Africa/Dakar",
    "iso:country":"SN",
    "wof:name":"Touba Ngouye",
    "wof:placetype":"locality"
},
  "geometry": {"coordinates":[-14.75,14.01667],"type":"Point"}
}