{
  "type": "Feature",
  "properties": {
    "gn:admin1_code":"5.0",
    "gn:asciiname":"Boundou Dioe",
    "gn:country_code":"SN",
    "gn:dem":78,
    "gn:feature_class":"P",
    "gn:feature_code":"PPL",
    "gn:name":"Boundou Dio\u00e9",
    "gn:population":0,
    "gn:timezone":"Africa/Dakar",
    "iso:country":"SN",
    "wof:lang_x_official":[
        "wol",
        "fra"
    ],
    "wof:lang_x_spoken":[
        "wol",
        "fra"
    ],
    "wof:name":"Boundou Dioe",
    "wof:placetype":"locality"
},
  "geometry": {"coordinates":[-12.04508,14.19559],"type":"Point"}
}