{
  "type": "Feature",
  "properties": {
    "gn:admin1_code":"12.0",
    "gn:asciiname":"Bofa",
    "gn:country_code":"SN",
    "gn:dem":23,
    "gn:feature_class":"P",
    "gn:feature_code":"PPL",
    "gn:name":"Bofa",
    "gn:population":0,
    "gn:timezone":"Africa/Dakar",
    "iso:country":"SN",
    "wof:name":"Bofa",
    "wof:placetype":"locality"
},
  "geometry": {"coordinates":[-16.13361,12.49056],"type":"Point"}
}