{
  "type": "Feature",
  "properties": {
    "gn:admin1_code":"15.0",
    "gn:asciiname":"Gawdal I",
    "gn:country_code":"SN",
    "gn:dem":15,
    "gn:feature_class":"P",
    "gn:feature_code":"PPL",
    "gn:name":"Gawdal I",
    "gn:population":0,
    "gn:timezone":"Africa/Dakar",
    "iso:country":"SN",
    "name:und_x_variant":[
        "Gaoudal",
        "Gawdal I"
    ],
    "wof:name":"Gawdal I",
    "wof:placetype":"locality"
},
  "geometry": {"coordinates":[-13.43184,16.0483],"type":"Point"}
}