{
  "type": "Feature",
  "properties": {
    "gn:admin1_code":"3.0",
    "gn:asciiname":"Mbaye",
    "gn:country_code":"SN",
    "gn:dem":43,
    "gn:feature_class":"P",
    "gn:feature_code":"PPL",
    "gn:name":"Mbaye",
    "gn:population":0,
    "gn:timezone":"Africa/Dakar",
    "iso:country":"SN",
    "wof:name":"Mbaye",
    "wof:placetype":"locality"
},
  "geometry": {"coordinates":[-16.36667000000001,14.85],"type":"Point"}
}