{
  "type": "Feature",
  "properties": {
    "gn:admin1_code":"16.0",
    "gn:asciiname":"Missira Tioyene",
    "gn:country_code":"SN",
    "gn:dem":35,
    "gn:feature_class":"P",
    "gn:feature_code":"PPL",
    "gn:name":"Missira Tioy\u00e8ne",
    "gn:population":0,
    "gn:timezone":"Africa/Dakar",
    "iso:country":"SN",
    "wof:name":"Missira Tioyene",
    "wof:placetype":"locality"
},
  "geometry": {"coordinates":[-14.88333,14.41667],"type":"Point"}
}