{
  "type": "Feature",
  "properties": {
    "gn:admin1_code":"7.0",
    "gn:asciiname":"Mbendi",
    "gn:country_code":"SN",
    "gn:dem":6,
    "gn:feature_class":"P",
    "gn:feature_code":"PPL",
    "gn:name":"Mb\u00e8ndi",
    "gn:population":0,
    "gn:timezone":"Africa/Dakar",
    "iso:country":"SN",
    "name:und_x_variant":[
        "Mbenndi",
        "Mb\u00e8ndi"
    ],
    "wof:name":"Mbendi",
    "wof:placetype":"locality"
},
  "geometry": {"coordinates":[-17.02962999999999,14.89198],"type":"Point"}
}