{
  "type": "Feature",
  "properties": {
    "gn:admin1_code":"9.0",
    "gn:asciiname":"Djibayala",
    "gn:country_code":"SN",
    "gn:dem":10,
    "gn:feature_class":"P",
    "gn:feature_code":"PPL",
    "gn:name":"Djibayala",
    "gn:population":0,
    "gn:timezone":"Africa/Dakar",
    "iso:country":"SN",
    "wof:name":"Djibayala",
    "wof:placetype":"locality"
},
  "geometry": {"coordinates":[-16.01667,14.23333],"type":"Point"}
}