{
  "type": "Feature",
  "properties": {
    "gn:admin1_code":"13.0",
    "gn:asciiname":"Leve Ngaou",
    "gn:country_code":"SN",
    "gn:dem":24,
    "gn:feature_class":"P",
    "gn:feature_code":"PPL",
    "gn:name":"L\u00e9v\u00e9 Ngaou",
    "gn:population":0,
    "gn:timezone":"Africa/Dakar",
    "iso:country":"SN",
    "name:und_x_variant":[
        "Ngaou",
        "L\u00e9v\u00e9 Ngaou"
    ],
    "wof:name":"Leve Ngaou",
    "wof:placetype":"locality"
},
  "geometry": {"coordinates":[-14.8602,15.2322],"type":"Point"}
}