{
  "type": "Feature",
  "properties": {
    "gn:admin1_code":"7.0",
    "gn:asciiname":"Tialle",
    "gn:country_code":"SN",
    "gn:dem":25,
    "gn:feature_class":"P",
    "gn:feature_code":"PPL",
    "gn:name":"Tiall\u00e9",
    "gn:population":0,
    "gn:timezone":"Africa/Dakar",
    "iso:country":"SN",
    "wof:name":"Tialle",
    "wof:placetype":"locality"
},
  "geometry": {"coordinates":[-16.8012,15.2434],"type":"Point"}
}