{
  "type": "Feature",
  "properties": {
    "gn:admin1_code":"12.0",
    "gn:asciiname":"Yembakana",
    "gn:country_code":"SN",
    "gn:dem":2,
    "gn:feature_class":"P",
    "gn:feature_code":"PPL",
    "gn:name":"Yembakana",
    "gn:population":0,
    "gn:timezone":"Africa/Dakar",
    "iso:country":"SN",
    "wof:name":"Yembakana",
    "wof:placetype":"locality"
},
  "geometry": {"coordinates":[-16.66861,12.43167],"type":"Point"}
}