{
  "type": "Feature",
  "properties": {
    "gn:admin1_code":"17.0",
    "gn:asciiname":"Gourenetere",
    "gn:country_code":"SN",
    "gn:dem":147,
    "gn:feature_class":"P",
    "gn:feature_code":"PPL",
    "gn:name":"Gour\u00e9n\u00e9t\u00e9r\u00e9",
    "gn:population":0,
    "gn:timezone":"Africa/Dakar",
    "iso:country":"SN",
    "name:und_x_variant":[
        "Gour\u00e9 N\u00e9h\u00e9r\u00e9",
        "Komaf\u00e9l\u00e9",
        "Gour\u00e9n\u00e9t\u00e9r\u00e9"
    ],
    "wof:name":"Gourenetere",
    "wof:placetype":"locality"
},
  "geometry": {"coordinates":[-12.5316,12.4013],"type":"Point"}
}