{
  "type": "Feature",
  "properties": {
    "gn:admin1_code":"12.0",
    "gn:asciiname":"Kayelo",
    "gn:cc2":"SN",
    "gn:country_code":"SN",
    "gn:dem":4,
    "gn:feature_class":"P",
    "gn:feature_code":"PPL",
    "gn:name":"Kay\u00e9lo",
    "gn:population":0,
    "gn:timezone":"Africa/Dakar",
    "iso:country":"SN",
    "name:und_x_variant":[
        "Caylo",
        "Kaylo",
        "Kay\u00e9lo"
    ],
    "wof:name":"Kayelo",
    "wof:placetype":"locality"
},
  "geometry": {"coordinates":[-16.74917,12.82472],"type":"Point"}
}