{
  "type": "Feature",
  "properties": {
    "gn:admin1_code":"3.0",
    "gn:asciiname":"Ouadjourou",
    "gn:country_code":"SN",
    "gn:dem":44,
    "gn:feature_class":"P",
    "gn:feature_code":"PPL",
    "gn:name":"Ouadjourou",
    "gn:population":0,
    "gn:timezone":"Africa/Dakar",
    "iso:country":"SN",
    "wof:name":"Ouadjourou",
    "wof:placetype":"locality"
},
  "geometry": {"coordinates":[-15.71667,14.81667],"type":"Point"}
}