{
  "type": "Feature",
  "properties": {
    "gn:admin1_code":"13.0",
    "gn:asciiname":"Kantare",
    "gn:country_code":"SN",
    "gn:dem":39,
    "gn:feature_class":"P",
    "gn:feature_code":"PPL",
    "gn:name":"Kantar\u00e9",
    "gn:population":0,
    "gn:timezone":"Africa/Dakar",
    "iso:country":"SN",
    "name:und_x_variant":[
        "Kantar",
        "Kantara",
        "Kantar\u00e9"
    ],
    "wof:name":"Kantare",
    "wof:placetype":"locality"
},
  "geometry": {"coordinates":[-16.2611,15.1973],"type":"Point"}
}