{
  "type": "Feature",
  "properties": {
    "gn:admin1_code":"15.0",
    "gn:asciiname":"Ouloum Baba",
    "gn:country_code":"SN",
    "gn:dem":31,
    "gn:feature_class":"P",
    "gn:feature_code":"PPL",
    "gn:name":"Ouloum Baba",
    "gn:population":0,
    "gn:timezone":"Africa/Dakar",
    "iso:country":"SN",
    "wof:name":"Ouloum Baba",
    "wof:placetype":"locality"
},
  "geometry": {"coordinates":[-12.62002,15.00214],"type":"Point"}
}