{
  "type": "Feature",
  "properties": {
    "gn:admin1_code":"13.0",
    "gn:asciiname":"Barale Ndiaye",
    "gn:country_code":"SN",
    "gn:dem":21,
    "gn:feature_class":"P",
    "gn:feature_code":"PPL",
    "gn:name":"Baral\u00e9 Ndiaye",
    "gn:population":0,
    "gn:timezone":"Africa/Dakar",
    "iso:country":"SN",
    "name:und_x_variant":[
        "Baral\u00e9 Diaye",
        "Baral\u00e9 Ndiaye"
    ],
    "wof:name":"Barale Ndiaye",
    "wof:placetype":"locality"
},
  "geometry": {"coordinates":[-16.2292,15.8452],"type":"Point"}
}