{
  "type": "Feature",
  "properties": {
    "gn:admin1_code":"14.0",
    "gn:asciiname":"Haire Diamal",
    "gn:country_code":"SN",
    "gn:dem":59,
    "gn:feature_class":"P",
    "gn:feature_code":"PPL",
    "gn:name":"Ha\u00efr\u00e9 Diamal",
    "gn:population":0,
    "gn:timezone":"Africa/Dakar",
    "iso:country":"SN",
    "wof:name":"Haire Diamal",
    "wof:placetype":"locality"
},
  "geometry": {"coordinates":[-14.38198,15.90196],"type":"Point"}
}