{
  "type": "Feature",
  "properties": {
    "gn:admin1_code":"13.0",
    "gn:asciiname":"Ndiare",
    "gn:country_code":"SN",
    "gn:dem":55,
    "gn:feature_class":"P",
    "gn:feature_code":"PPL",
    "gn:name":"Ndiar\u00e9",
    "gn:population":0,
    "gn:timezone":"Africa/Dakar",
    "iso:country":"SN",
    "wof:name":"Ndiare",
    "wof:placetype":"locality"
},
  "geometry": {"coordinates":[-15.8931,15.5264],"type":"Point"}
}