{
  "type": "Feature",
  "properties": {
    "gn:admin1_code":"18.0",
    "gn:asciiname":"Kebeum",
    "gn:country_code":"SN",
    "gn:dem":19,
    "gn:feature_class":"P",
    "gn:feature_code":"PPL",
    "gn:name":"Kebeum",
    "gn:population":0,
    "gn:timezone":"Africa/Dakar",
    "iso:country":"SN",
    "wof:name":"Kebeum",
    "wof:placetype":"locality"
},
  "geometry": {"coordinates":[-15.91667,13.03333],"type":"Point"}
}