{
  "type": "Feature",
  "properties": {
    "gn:admin1_code":"5.0",
    "gn:asciiname":"Goumpeni",
    "gn:country_code":"SN",
    "gn:dem":42,
    "gn:feature_class":"P",
    "gn:feature_code":"PPL",
    "gn:name":"Goump\u00e9ni",
    "gn:population":0,
    "gn:timezone":"Africa/Dakar",
    "iso:country":"SN",
    "wof:name":"Goumpeni",
    "wof:placetype":"locality"
},
  "geometry": {"coordinates":[-12.26227,14.5059],"type":"Point"}
}