{
  "type": "Feature",
  "properties": {
    "gn:admin1_code":"1.0",
    "gn:asciiname":"Les Almadies",
    "gn:country_code":"SN",
    "gn:dem":8,
    "gn:feature_class":"P",
    "gn:feature_code":"PPLL",
    "gn:name":"Les Almadies",
    "gn:population":0,
    "gn:timezone":"Africa/Dakar",
    "iso:country":"SN",
    "wof:name":"Les Almadies",
    "wof:placetype":"locality"
},
  "geometry": {"coordinates":[-17.52568,14.74475],"type":"Point"}
}