{
  "type": "Feature",
  "properties": {
    "gn:admin1_code":"9.0",
    "gn:asciiname":"Nguelou",
    "gn:cc2":"SN",
    "gn:country_code":"SN",
    "gn:dem":29,
    "gn:feature_class":"P",
    "gn:feature_code":"PPL",
    "gn:name":"Ngu\u00e9lou",
    "gn:population":0,
    "gn:timezone":"Africa/Dakar",
    "iso:country":"SN",
    "name:und_x_variant":[
        "Gu\u00e9lou",
        "N\u2019Guellou",
        "Ngu\u00e9lou"
    ],
    "wof:name":"Nguelou",
    "wof:placetype":"locality"
},
  "geometry": {"coordinates":[-15.95,14.36667],"type":"Point"}
}