{
  "type": "Feature",
  "properties": {
    "gn:admin1_code":"7.0",
    "gn:asciiname":"Guediane",
    "gn:cc2":"SN",
    "gn:country_code":"SN",
    "gn:dem":11,
    "gn:feature_class":"P",
    "gn:feature_code":"PPL",
    "gn:name":"Gu\u00e9diane",
    "gn:population":0,
    "gn:timezone":"Africa/Dakar",
    "iso:country":"SN",
    "name:und_x_variant":[
        "Nguidian",
        "Nguidiane",
        "Ngu\u00e9diane",
        "Gu\u00e9diane"
    ],
    "wof:lang_x_official":[
        "wol",
        "fra"
    ],
    "wof:lang_x_spoken":[
        "wol",
        "fra"
    ],
    "wof:name":"Guediane",
    "wof:placetype":"locality"
},
  "geometry": {"coordinates":[-16.71667,14.43333],"type":"Point"}
}