{
  "type": "Feature",
  "properties": {
    "gn:admin1_code":"9.0",
    "gn:asciiname":"Samba Gueye",
    "gn:country_code":"SN",
    "gn:dem":35,
    "gn:feature_class":"P",
    "gn:feature_code":"PPL",
    "gn:name":"Samba Gu\u00e8ye",
    "gn:population":0,
    "gn:timezone":"Africa/Dakar",
    "iso:country":"SN",
    "wof:name":"Samba Gueye",
    "wof:placetype":"locality"
},
  "geometry": {"coordinates":[-16.36667000000001,13.65],"type":"Point"}
}