{
  "type": "Feature",
  "properties": {
    "gn:admin1_code":"7.0",
    "gn:asciiname":"Aramine",
    "gn:cc2":"SN",
    "gn:country_code":"SN",
    "gn:dem":40,
    "gn:feature_class":"P",
    "gn:feature_code":"PPL",
    "gn:name":"Aramine",
    "gn:population":0,
    "gn:timezone":"Africa/Dakar",
    "iso:country":"SN",
    "name:und_x_variant":[
        "Keur Aramin",
        "Aramine"
    ],
    "wof:name":"Aramine",
    "wof:placetype":"locality"
},
  "geometry": {"coordinates":[-16.81667,14.75],"type":"Point"}
}