{
  "type": "Feature",
  "properties": {
    "gn:admin1_code":"7.0",
    "gn:asciiname":"Kayol",
    "gn:country_code":"SN",
    "gn:dem":47,
    "gn:feature_class":"P",
    "gn:feature_code":"PPL",
    "gn:name":"Kayol",
    "gn:population":0,
    "gn:timezone":"Africa/Dakar",
    "iso:country":"SN",
    "name:und_x_variant":[
        "Kayel",
        "Kayol"
    ],
    "wof:name":"Kayol",
    "wof:placetype":"locality"
},
  "geometry": {"coordinates":[-17.09719,14.7595],"type":"Point"}
}