{
  "type": "Feature",
  "properties": {
    "gn:admin1_code":"17.0",
    "gn:asciiname":"Malem",
    "gn:country_code":"SN",
    "gn:dem":198,
    "gn:feature_class":"P",
    "gn:feature_code":"PPL",
    "gn:name":"Malem",
    "gn:population":0,
    "gn:timezone":"Africa/Dakar",
    "iso:country":"SN",
    "name:fra_x_preferred":[
        "Malem"
    ],
    "name:mkd_x_preferred":[
        "\u041c\u0430\u043b\u0435\u043c"
    ],
    "wof:name":"Malem",
    "wof:placetype":"locality"
},
  "geometry": {"coordinates":[-11.89222,12.46361],"type":"Point"}
}