{
  "type": "Feature",
  "properties": {
    "gn:admin1_code":"1.0",
    "gn:asciiname":"Los",
    "gn:country_code":"SN",
    "gn:dem":16,
    "gn:feature_class":"P",
    "gn:feature_code":"PPL",
    "gn:name":"Los",
    "gn:population":0,
    "gn:timezone":"Africa/Dakar",
    "iso:country":"SN",
    "name:bel_x_preferred":[
        "\u041b\u043e\u0441\u044c"
    ],
    "name:ceb_x_preferred":[
        "Los"
    ],
    "name:ces_x_preferred":[
        "Los"
    ],
    "name:deu_x_preferred":[
        "Los"
    ],
    "name:fin_x_preferred":[
        "Los"
    ],
    "name:nld_x_preferred":[
        "Los"
    ],
    "name:nno_x_preferred":[
        "Los"
    ],
    "name:pol_x_preferred":[
        "Los"
    ],
    "name:rus_x_preferred":[
        "\u041b\u043e\u0441\u044c"
    ],
    "name:swe_x_preferred":[
        "Los"
    ],
    "name:ukr_x_preferred":[
        "\u041b\u043e\u0441\u044c"
    ],
    "wof:name":"Los",
    "wof:placetype":"locality"
},
  "geometry": {"coordinates":[-17.16064,14.70144],"type":"Point"}
}