{
  "type": "Feature",
  "properties": {
    "gn:admin1_code":"7.0",
    "gn:asciiname":"Mbidiam Lebou",
    "gn:country_code":"SN",
    "gn:dem":25,
    "gn:feature_class":"P",
    "gn:feature_code":"PPL",
    "gn:name":"Mbidiam L\u00e9bou",
    "gn:population":0,
    "gn:timezone":"Africa/Dakar",
    "iso:country":"SN",
    "wof:name":"Mbidiam Lebou",
    "wof:placetype":"locality"
},
  "geometry": {"coordinates":[-17.07844,14.89157],"type":"Point"}
}