{
  "type": "Feature",
  "properties": {
    "gn:admin1_code":"12.0",
    "gn:asciiname":"Boko",
    "gn:country_code":"SN",
    "gn:dem":3,
    "gn:feature_class":"P",
    "gn:feature_code":"PPL",
    "gn:name":"Boko",
    "gn:population":0,
    "gn:timezone":"Africa/Dakar",
    "iso:country":"SN",
    "name:ceb_x_preferred":[
        "Boko"
    ],
    "name:deu_x_preferred":[
        "Boko"
    ],
    "name:epo_x_preferred":[
        "Boko"
    ],
    "name:fra_x_preferred":[
        "Boko"
    ],
    "name:ido_x_preferred":[
        "Boko"
    ],
    "name:lin_x_preferred":[
        "Boko"
    ],
    "name:swe_x_preferred":[
        "Boko"
    ],
    "wof:name":"Boko",
    "wof:placetype":"locality"
},
  "geometry": {"coordinates":[-16.75556,12.775],"type":"Point"}
}