{
  "type": "Feature",
  "properties": {
    "gn:admin1_code":"14.0",
    "gn:asciiname":"Alo",
    "gn:country_code":"SN",
    "gn:dem":9,
    "gn:feature_class":"P",
    "gn:feature_code":"PPL",
    "gn:name":"Alo",
    "gn:population":0,
    "gn:timezone":"Africa/Dakar",
    "iso:country":"SN",
    "name:ceb_x_preferred":[
        "Alo"
    ],
    "name:deu_x_preferred":[
        "Alo"
    ],
    "name:fra_x_preferred":[
        "Alo"
    ],
    "name:hye_x_preferred":[
        "\u0531\u056c\u0578"
    ],
    "name:ind_x_preferred":[
        "Alo"
    ],
    "name:spa_x_preferred":[
        "Alo"
    ],
    "name:swe_x_preferred":[
        "Alo"
    ],
    "wof:lang_x_official":[
        "wol",
        "fra"
    ],
    "wof:lang_x_spoken":[
        "wol",
        "fra"
    ],
    "wof:name":"Alo",
    "wof:placetype":"locality"
},
  "geometry": {"coordinates":[-14.47133,16.59467],"type":"Point"}
}