{
  "type": "Feature",
  "properties": {
    "gn:admin1_code":"13.0",
    "gn:asciiname":"Ndiao Ndiao",
    "gn:country_code":"SN",
    "gn:dem":39,
    "gn:feature_class":"P",
    "gn:feature_code":"PPL",
    "gn:name":"Ndiao Ndiao",
    "gn:population":0,
    "gn:timezone":"Africa/Dakar",
    "iso:country":"SN",
    "wof:name":"Ndiao Ndiao",
    "wof:placetype":"locality"
},
  "geometry": {"coordinates":[-16.15,15.05],"type":"Point"}
}