{
  "type": "Feature",
  "properties": {
    "gn:admin1_code":"16.0",
    "gn:asciiname":"Boki Baga Pui",
    "gn:country_code":"SN",
    "gn:dem":43,
    "gn:feature_class":"P",
    "gn:feature_code":"PPL",
    "gn:name":"Boki Baga Pui",
    "gn:population":0,
    "gn:timezone":"Africa/Dakar",
    "iso:country":"SN",
    "name:und_x_variant":[
        "Mare Bogui Bard\u00e9",
        "Boki Baga Pui"
    ],
    "wof:name":"Boki Baga Pui",
    "wof:placetype":"locality"
},
  "geometry": {"coordinates":[-15.63333,14.48333],"type":"Point"}
}