{
  "type": "Feature",
  "properties": {
    "gn:admin1_code":"17.0",
    "gn:asciiname":"Lesfello",
    "gn:country_code":"SN",
    "gn:dem":387,
    "gn:feature_class":"P",
    "gn:feature_code":"PPL",
    "gn:name":"L\u00e9sf\u00e9llo",
    "gn:population":0,
    "gn:timezone":"Africa/Dakar",
    "iso:country":"SN",
    "name:und_x_variant":[
        "Le\u00effala",
        "L\u00e9sf\u00e9llo"
    ],
    "wof:name":"Lesfello",
    "wof:placetype":"locality"
},
  "geometry": {"coordinates":[-12.0248,12.4459],"type":"Point"}
}