{
  "type": "Feature",
  "properties": {
    "gn:admin1_code":"16.0",
    "gn:asciiname":"Port Darame",
    "gn:country_code":"SN",
    "gn:dem":46,
    "gn:feature_class":"P",
    "gn:feature_code":"PPL",
    "gn:name":"Port Daram\u00e9",
    "gn:population":0,
    "gn:timezone":"Africa/Dakar",
    "iso:country":"SN",
    "name:und_x_variant":[
        "Por Daram\u00e9",
        "Port Daram\u00e9"
    ],
    "wof:name":"Port Darame",
    "wof:placetype":"locality"
},
  "geometry": {"coordinates":[-15.11667,14.05],"type":"Point"}
}