{
  "type": "Feature",
  "properties": {
    "gn:admin1_code":"17.0",
    "gn:asciiname":"Mbon Peul",
    "gn:country_code":"SN",
    "gn:dem":126,
    "gn:feature_class":"P",
    "gn:feature_code":"PPL",
    "gn:name":"Mbon Peul",
    "gn:population":0,
    "gn:timezone":"Africa/Dakar",
    "iso:country":"SN",
    "name:und_x_variant":[
        "Mbon",
        "Mbon Peul"
    ],
    "wof:name":"Mbon Peul",
    "wof:placetype":"locality"
},
  "geometry": {"coordinates":[-12.8964,12.5574],"type":"Point"}
}