{
  "type": "Feature",
  "properties": {
    "gn:admin1_code":"10.0",
    "gn:asciiname":"Keur Samba Kakoet",
    "gn:cc2":"SN",
    "gn:country_code":"SN",
    "gn:dem":12,
    "gn:feature_class":"P",
    "gn:feature_code":"PPL",
    "gn:name":"Keur Samba Kako\u00e8t",
    "gn:population":0,
    "gn:timezone":"Africa/Dakar",
    "iso:country":"SN",
    "name:und_x_variant":[
        "Keur Samba",
        "Keur Samba Kako\u00e8t"
    ],
    "wof:lang_x_official":[
        "wol",
        "fra"
    ],
    "wof:lang_x_spoken":[
        "wol",
        "fra"
    ],
    "wof:name":"Keur Samba Kakoet",
    "wof:placetype":"locality"
},
  "geometry": {"coordinates":[-16.01667,13.93333],"type":"Point"}
}