{
  "type": "Feature",
  "properties": {
    "gn:admin1_code":"9.0",
    "gn:asciiname":"Dak",
    "gn:country_code":"SN",
    "gn:dem":3,
    "gn:feature_class":"P",
    "gn:feature_code":"PPL",
    "gn:name":"Dak",
    "gn:population":0,
    "gn:timezone":"Africa/Dakar",
    "iso:country":"SN",
    "wof:name":"Dak",
    "wof:placetype":"locality"
},
  "geometry": {"coordinates":[-16.63332999999999,14.28333],"type":"Point"}
}