{
  "type": "Feature",
  "properties": {
    "gn:admin1_code":"18.0",
    "gn:asciiname":"Yaran",
    "gn:country_code":"SN",
    "gn:dem":39,
    "gn:feature_class":"P",
    "gn:feature_code":"PPL",
    "gn:name":"Yaran",
    "gn:population":0,
    "gn:timezone":"Africa/Dakar",
    "iso:country":"SN",
    "wof:name":"Yaran",
    "wof:placetype":"locality"
},
  "geometry": {"coordinates":[-15.52056,12.51361],"type":"Point"}
}