{
  "type": "Feature",
  "properties": {
    "gn:admin1_code":"5.0",
    "gn:asciiname":"Bagadadji",
    "gn:country_code":"SN",
    "gn:dem":41,
    "gn:feature_class":"P",
    "gn:feature_code":"PPL",
    "gn:name":"Bagadadji",
    "gn:population":0,
    "gn:timezone":"Africa/Dakar",
    "iso:country":"SN",
    "name:und_x_variant":[
        "Bakadadji",
        "Bagadadji"
    ],
    "wof:name":"Bagadadji",
    "wof:placetype":"locality"
},
  "geometry": {"coordinates":[-13.00094,13.42321],"type":"Point"}
}