{
  "type": "Feature",
  "properties": {
    "gn:admin1_code":"12.0",
    "gn:asciiname":"Koubanao",
    "gn:country_code":"SN",
    "gn:dem":10,
    "gn:feature_class":"P",
    "gn:feature_code":"PPL",
    "gn:name":"Koubanao",
    "gn:population":0,
    "gn:timezone":"Africa/Dakar",
    "iso:country":"SN",
    "wof:name":"Koubanao",
    "wof:placetype":"locality"
},
  "geometry": {"coordinates":[-16.09,12.66639],"type":"Point"}
}