{
  "type": "Feature",
  "properties": {
    "gn:admin1_code":"11.0",
    "gn:asciiname":"Bareguessin",
    "gn:country_code":"SN",
    "gn:dem":17,
    "gn:feature_class":"P",
    "gn:feature_code":"PPL",
    "gn:name":"Bar\u00e9guessin",
    "gn:population":0,
    "gn:timezone":"Africa/Dakar",
    "iso:country":"SN",
    "wof:name":"Bareguessin",
    "wof:placetype":"locality"
},
  "geometry": {"coordinates":[-16.38332999999999,13.01667],"type":"Point"}
}