{
  "type": "Feature",
  "properties": {
    "gn:admin1_code":"15.0",
    "gn:asciiname":"Tianiato",
    "gn:country_code":"SN",
    "gn:dem":29,
    "gn:feature_class":"P",
    "gn:feature_code":"PPL",
    "gn:name":"Tianiato",
    "gn:population":0,
    "gn:timezone":"Africa/Dakar",
    "iso:country":"SN",
    "name:und_x_variant":[
        "Tianialo",
        "Tianiaf",
        "Tianiato"
    ],
    "wof:name":"Tianiato",
    "wof:placetype":"locality"
},
  "geometry": {"coordinates":[-12.69591,15.04006],"type":"Point"}
}