{
  "type": "Feature",
  "properties": {
    "gn:admin1_code":"15.0",
    "gn:asciiname":"Bokeladji",
    "gn:country_code":"SN",
    "gn:dem":29,
    "gn:feature_class":"P",
    "gn:feature_code":"PPL",
    "gn:name":"Bok\u00e9ladji",
    "gn:population":0,
    "gn:timezone":"Africa/Dakar",
    "iso:country":"SN",
    "name:und_x_variant":[
        "Bokiladji",
        "Bok\u00e9ladji"
    ],
    "wof:name":"Bokeladji",
    "wof:placetype":"locality"
},
  "geometry": {"coordinates":[-12.74672,15.05734],"type":"Point"}
}