{
  "type": "Feature",
  "properties": {
    "gn:admin1_code":"14.0",
    "gn:asciiname":"Tidji",
    "gn:country_code":"SN",
    "gn:dem":8,
    "gn:feature_class":"P",
    "gn:feature_code":"PPL",
    "gn:name":"Tidji",
    "gn:population":0,
    "gn:timezone":"Africa/Dakar",
    "iso:country":"SN",
    "wof:name":"Tidji",
    "wof:placetype":"locality"
},
  "geometry": {"coordinates":[-16.11833,16.10306],"type":"Point"}
}