{
  "type": "Feature",
  "properties": {
    "gn:admin1_code":"13.0",
    "gn:asciiname":"Kebe Ndeute",
    "gn:country_code":"SN",
    "gn:dem":39,
    "gn:feature_class":"P",
    "gn:feature_code":"PPL",
    "gn:name":"K\u00e9b\u00e9 Ndeute",
    "gn:population":0,
    "gn:timezone":"Africa/Dakar",
    "iso:country":"SN",
    "name:und_x_variant":[
        "K\u00e9b\u00e9",
        "K\u00e9b\u00e9 Ndeukt",
        "K\u00e9b\u00e9 Ndeute"
    ],
    "wof:name":"Kebe Ndeute",
    "wof:placetype":"locality"
},
  "geometry": {"coordinates":[-16.18333,15.68333],"type":"Point"}
}