{
  "type": "Feature",
  "properties": {
    "gn:admin1_code":"5.0",
    "gn:asciiname":"Marekounda",
    "gn:cc2":"SN",
    "gn:country_code":"SN",
    "gn:dem":21,
    "gn:feature_class":"P",
    "gn:feature_code":"PPL",
    "gn:name":"Mar\u00e9kounda",
    "gn:population":0,
    "gn:timezone":"Africa/Dakar",
    "iso:country":"SN",
    "name:und_x_variant":[
        "Mar\u00e9counda",
        "Mar\u00e9kounda"
    ],
    "wof:name":"Marekounda",
    "wof:placetype":"locality"
},
  "geometry": {"coordinates":[-14.03333,13.68333],"type":"Point"}
}