{
  "type": "Feature",
  "properties": {
    "gn:admin1_code":"12.0",
    "gn:asciiname":"Kailen",
    "gn:cc2":"SN",
    "gn:country_code":"SN",
    "gn:dem":14,
    "gn:feature_class":"P",
    "gn:feature_code":"PPL",
    "gn:name":"Ka\u00eflen",
    "gn:population":0,
    "gn:timezone":"Africa/Dakar",
    "iso:country":"SN",
    "name:und_x_variant":[
        "Ka\u00efl\u00e8ne",
        "Ka\u00eflen"
    ],
    "wof:lang_x_official":[
        "wol",
        "fra"
    ],
    "wof:lang_x_spoken":[
        "wol",
        "fra"
    ],
    "wof:name":"Kailen",
    "wof:placetype":"locality"
},
  "geometry": {"coordinates":[-16.33333,12.55],"type":"Point"}
}