{
  "type": "Feature",
  "properties": {
    "gn:admin1_code":"10.0",
    "gn:asciiname":"Diourbel",
    "gn:country_code":"SN",
    "gn:dem":10,
    "gn:feature_class":"P",
    "gn:feature_code":"PPL",
    "gn:name":"Diourbel",
    "gn:population":0,
    "gn:timezone":"Africa/Dakar",
    "iso:country":"SN",
    "name:bul_x_preferred":[
        "\u0414\u0438\u0443\u0440\u0431\u0435\u043b"
    ],
    "name:cat_x_preferred":[
        "Diourbel"
    ],
    "name:dan_x_preferred":[
        "Diourbel"
    ],
    "name:deu_x_preferred":[
        "Diourbel"
    ],
    "name:epo_x_preferred":[
        "Diourbel"
    ],
    "name:eus_x_preferred":[
        "Diourbel"
    ],
    "name:fra_x_preferred":[
        "Diourbel"
    ],
    "name:frr_x_preferred":[
        "Diourbel"
    ],
    "name:heb_x_preferred":[
        "\u05d3\u05d9\u05d5\u05e8\u05d1\u05dc"
    ],
    "name:ita_x_preferred":[
        "Diourbel"
    ],
    "name:jpn_x_preferred":[
        "\u30b8\u30e5\u30eb\u30d9\u30eb"
    ],
    "name:kor_x_preferred":[
        "\ub514\uc6b0\ub974\ubca8"
    ],
    "name:lit_x_preferred":[
        "Diurbelis"
    ],
    "name:nld_x_preferred":[
        "Diourbel"
    ],
    "name:pol_x_preferred":[
        "Diourbel"
    ],
    "name:ron_x_preferred":[
        "Diourbel"
    ],
    "name:rus_x_preferred":[
        "\u0414\u0438\u0443\u0440\u0431\u0435\u043b\u044c"
    ],
    "name:spa_x_preferred":[
        "Diourbel"
    ],
    "name:swe_x_preferred":[
        "Diourbel"
    ],
    "name:urd_x_preferred":[
        "\u062f\u06cc\u0648\u0631\u0628\u06cc\u0644"
    ],
    "name:wol_x_preferred":[
        "Jurbel"
    ],
    "name:zho_x_preferred":[
        "\u4e45\u723e\u8c9d\u52d2"
    ],
    "wof:lang_x_official":[
        "wol",
        "fra"
    ],
    "wof:lang_x_spoken":[
        "wol",
        "fra"
    ],
    "wof:name":"Diourbel",
    "wof:placetype":"locality"
},
  "geometry": {"coordinates":[-16.18333,14.23333],"type":"Point"}
}