{
  "type": "Feature",
  "properties": {
    "iso:country":"SN",
    "name:fas_x_preferred":[
        "\u0641\u0631\u0648\u062f\u06af\u0627\u0647 \u06a9\u067e \u0627\u0633\u06a9\u0631"
    ],
    "name:fra_x_preferred":[
        "A\u00e9roport de Cap Skirring"
    ],
    "name:ind_x_preferred":[
        "Bandar Udara Cap Skirring"
    ],
    "name:ita_x_preferred":[
        "Aeroporto di Cap Skirring"
    ],
    "name:pol_x_preferred":[
        "Port lotniczy Cap Skirring"
    ],
    "name:tgk_x_preferred":[
        "\u0424\u0443\u0440\u0443\u0434\u0433\u043e\u04b3\u0438 \u041a\u0435\u043f \u0421\u043a\u0438\u0440\u0438\u043d\u0433"
    ],
    "oa:elevation_ft":"52",
    "oa:type":"medium_airport",
    "wd:wordcount":108,
    "woe:hierarchy":{
        "country_id":23424943,
        "county_id":56055817,
        "planet_id":1,
        "state_id":2346997
    },
    "wof:name":"Cap Skiring Airport",
    "wof:placetype":"campus"
},
  "geometry": {"coordinates":[-16.746111111111,12.41],"type":"Point"}
}