{
  "type": "Feature",
  "properties": {
    "iso:country":"SN",
    "name:ceb_x_preferred":[
        "Cap Skirring Airport"
    ],
    "name:deu_x_preferred":[
        "Flughafen Cap Skirring"
    ],
    "name:eng_x_preferred":[
        "Cap Skirring Airport"
    ],
    "name:fas_x_preferred":[
        "\u0641\u0631\u0648\u062f\u06af\u0627\u0647 \u06a9\u067e \u0627\u0633\u06a9\u0631"
    ],
    "name:fra_x_preferred":[
        "A\u00e9roport de Cap Skirring"
    ],
    "name:ind_x_preferred":[
        "Bandar Udara Cap Skirring"
    ],
    "name:ita_x_preferred":[
        "Aeroporto di Cap Skirring"
    ],
    "name:jpn_x_preferred":[
        "\u30ad\u30e3\u30c3\u30d7\u30fb\u30b9\u30ad\u30ea\u30f3\u30b0\u7a7a\u6e2f"
    ],
    "name:msa_x_preferred":[
        "Lapangan Terbang Cap Skiring"
    ],
    "name:nld_x_preferred":[
        "Cap Skirring Airport"
    ],
    "name:pol_x_preferred":[
        "Port lotniczy Cap Skirring"
    ],
    "name:ron_x_preferred":[
        "Aeroportul Cap Skirring"
    ],
    "name:spa_x_preferred":[
        "Aeropuerto Cap Skirring"
    ],
    "name:tgk_x_preferred":[
        "\u0424\u0443\u0440\u0443\u0434\u0433\u043e\u04b3\u0438 \u041a\u0435\u043f \u0421\u043a\u0438\u0440\u0438\u043d\u0433"
    ],
    "name:tgk_x_variant":[
        "\u0424\u0443\u0440\u0443\u0434\u0433\u043e\u04b3\u0438 \u043a\u043f \u043e\u0441\u043a\u0440"
    ],
    "name:zho_x_preferred":[
        "Cap Skirring\u6a5f\u5834"
    ],
    "oa:elevation_ft":"52",
    "oa:type":"medium_airport",
    "wd:wordcount":108,
    "woe:hierarchy":{
        "country_id":23424943,
        "county_id":56055817,
        "planet_id":1,
        "state_id":2346997
    },
    "wof:name":"Cap Skiring Airport",
    "wof:placetype":"campus"
},
  "geometry": {"coordinates":[-16.746111111111,12.41],"type":"Point"}
}