{
  "type": "Feature",
  "properties": {
    "gn:admin1_code":"15.0",
    "gn:asciiname":"Beli Diallo",
    "gn:country_code":"SN",
    "gn:dem":17,
    "gn:feature_class":"P",
    "gn:feature_code":"PPL",
    "gn:name":"B\u00e9li Diallo",
    "gn:population":0,
    "gn:timezone":"Africa/Dakar",
    "iso:country":"SN",
    "wof:name":"Beli Diallo",
    "wof:placetype":"locality"
},
  "geometry": {"coordinates":[-13.23057,15.61282],"type":"Point"}
}