{
  "type": "Feature",
  "properties": {
    "gn:admin1_code":"14.0",
    "gn:asciiname":"Gassel",
    "gn:country_code":"SN",
    "gn:dem":58,
    "gn:feature_class":"P",
    "gn:feature_code":"PPL",
    "gn:name":"Gassel",
    "gn:population":0,
    "gn:timezone":"Africa/Dakar",
    "iso:country":"SN",
    "wof:name":"Gassel",
    "wof:placetype":"locality"
},
  "geometry": {"coordinates":[-14.5191,15.9936],"type":"Point"}
}