{
  "type": "Feature",
  "properties": {
    "gn:admin1_code":"13.0",
    "gn:asciiname":"Bainak",
    "gn:cc2":"SN",
    "gn:country_code":"SN",
    "gn:dem":41,
    "gn:feature_class":"P",
    "gn:feature_code":"PPL",
    "gn:name":"Ba\u00efnak",
    "gn:population":0,
    "gn:timezone":"Africa/Dakar",
    "iso:country":"SN",
    "name:und_x_variant":[
        "Ba\u00efnack",
        "Ba\u00efnak"
    ],
    "wof:lang_x_official":[
        "wol",
        "fra"
    ],
    "wof:lang_x_spoken":[
        "wol",
        "fra"
    ],
    "wof:name":"Bainak",
    "wof:placetype":"locality"
},
  "geometry": {"coordinates":[-16.25,15.71667],"type":"Point"}
}