{
  "type": "Feature",
  "properties": {
    "gn:admin1_code":"15.0",
    "gn:asciiname":"Boki Bagou",
    "gn:country_code":"SN",
    "gn:dem":54,
    "gn:feature_class":"P",
    "gn:feature_code":"PPL",
    "gn:name":"Boki Bagou",
    "gn:population":0,
    "gn:timezone":"Africa/Dakar",
    "iso:country":"SN",
    "wof:name":"Boki Bagou",
    "wof:placetype":"locality"
},
  "geometry": {"coordinates":[-13.88333,15.81667],"type":"Point"}
}