{
  "type": "Feature",
  "properties": {
    "gn:admin1_code":"5.0",
    "gn:asciiname":"Banfara",
    "gn:cc2":"SN",
    "gn:country_code":"SN",
    "gn:dem":46,
    "gn:feature_class":"P",
    "gn:feature_code":"PPL",
    "gn:name":"Banfara",
    "gn:population":0,
    "gn:timezone":"Africa/Dakar",
    "iso:country":"SN",
    "name:und_x_variant":[
        "Banfara I",
        "Banfara"
    ],
    "wof:name":"Banfara",
    "wof:placetype":"locality"
},
  "geometry": {"coordinates":[-13.43333,13.83333],"type":"Point"}
}