{
  "type": "Feature",
  "properties": {
    "gn:admin1_code":"12.0",
    "gn:asciiname":"Djilakoune",
    "gn:cc2":"SN",
    "gn:country_code":"SN",
    "gn:dem":8,
    "gn:feature_class":"P",
    "gn:feature_code":"PPL",
    "gn:name":"Djilakoune",
    "gn:population":0,
    "gn:timezone":"Africa/Dakar",
    "iso:country":"SN",
    "name:und_x_variant":[
        "Djilakoun",
        "Djilakoune"
    ],
    "wof:name":"Djilakoune",
    "wof:placetype":"locality"
},
  "geometry": {"coordinates":[-16.21361,12.65444],"type":"Point"}
}