{
  "type": "Feature",
  "properties": {
    "gn:admin1_code":"7.0",
    "gn:asciiname":"Ngueniene",
    "gn:cc2":"SN",
    "gn:country_code":"SN",
    "gn:dem":15,
    "gn:feature_class":"P",
    "gn:feature_code":"PPL",
    "gn:name":"Ngu\u00e9ni\u00e8ne",
    "gn:population":0,
    "gn:timezone":"Africa/Dakar",
    "iso:country":"SN",
    "name:und_x_variant":[
        "Ngu\u00e9niane",
        "Ngu\u00e9nian",
        "Nguniane",
        "Ngu\u00e9mian",
        "Ngu\u00e9ni\u00e8ne"
    ],
    "wof:name":"Ngueniene",
    "wof:placetype":"locality"
},
  "geometry": {"coordinates":[-16.75,14.28333],"type":"Point"}
}