{
  "type": "Feature",
  "properties": {
    "gn:admin1_code":"14.0",
    "gn:asciiname":"Lougou-Fourodi",
    "gn:country_code":"SN",
    "gn:dem":6,
    "gn:feature_class":"P",
    "gn:feature_code":"PPL",
    "gn:name":"Lougou-Fourodi",
    "gn:population":0,
    "gn:timezone":"Africa/Dakar",
    "iso:country":"SN",
    "wof:name":"Lougou-Fourodi",
    "wof:placetype":"locality"
},
  "geometry": {"coordinates":[-14.99816,16.51161],"type":"Point"}
}