{
  "type": "Feature",
  "properties": {
    "gn:admin1_code":"5.0",
    "gn:asciiname":"Diaweli",
    "gn:country_code":"SN",
    "gn:dem":64,
    "gn:feature_class":"P",
    "gn:feature_code":"PPL",
    "gn:name":"Diaw\u00e9li",
    "gn:population":0,
    "gn:timezone":"Africa/Dakar",
    "iso:country":"SN",
    "name:und_x_variant":[
        "Diaouel",
        "Dianvel",
        "Diaw\u00e9ll Sako",
        "Diaw\u00e9li Sako",
        "Diaw\u00e9li"
    ],
    "wof:lang_x_official":[
        "wol",
        "fra"
    ],
    "wof:lang_x_spoken":[
        "wol",
        "fra"
    ],
    "wof:name":"Diaweli",
    "wof:placetype":"locality"
},
  "geometry": {"coordinates":[-12.37476,14.34528],"type":"Point"}
}