{
  "type": "Feature",
  "properties": {
    "gn:admin1_code":"17.0",
    "gn:asciiname":"Hore Bova",
    "gn:country_code":"SN",
    "gn:dem":134,
    "gn:feature_class":"P",
    "gn:feature_code":"PPL",
    "gn:name":"Hor\u00e9 Bova",
    "gn:population":0,
    "gn:timezone":"Africa/Dakar",
    "iso:country":"SN",
    "name:und_x_variant":[
        "Hor\u00e9 Boval",
        "Hor\u00e9 Bova"
    ],
    "wof:lang_x_official":[
        "wol",
        "fra"
    ],
    "wof:lang_x_spoken":[
        "wol",
        "fra"
    ],
    "wof:name":"Hore Bova",
    "wof:placetype":"locality"
},
  "geometry": {"coordinates":[-12.45,12.45],"type":"Point"}
}