{
  "type": "Feature",
  "properties": {
    "gn:admin1_code":"18.0",
    "gn:asciiname":"Belan",
    "gn:country_code":"SN",
    "gn:dem":30,
    "gn:feature_class":"P",
    "gn:feature_code":"PPL",
    "gn:name":"B\u00e9lan",
    "gn:population":0,
    "gn:timezone":"Africa/Dakar",
    "iso:country":"SN",
    "name:ceb_x_preferred":[
        "Belan"
    ],
    "name:deu_x_preferred":[
        "Belan"
    ],
    "name:fra_x_preferred":[
        "Belan"
    ],
    "name:swe_x_preferred":[
        "Belan"
    ],
    "wof:lang_x_official":[
        "wol",
        "fra"
    ],
    "wof:lang_x_spoken":[
        "wol",
        "fra"
    ],
    "wof:name":"Belan",
    "wof:placetype":"locality"
},
  "geometry": {"coordinates":[-15.48167,12.56194],"type":"Point"}
}