{
  "type": "Feature",
  "properties": {
    "gn:admin1_code":"9.0",
    "gn:asciiname":"Aidra",
    "gn:cc2":"SN",
    "gn:country_code":"SN",
    "gn:dem":40,
    "gn:feature_class":"P",
    "gn:feature_code":"PPL",
    "gn:name":"A\u00efdra",
    "gn:population":0,
    "gn:timezone":"Africa/Dakar",
    "iso:country":"SN",
    "name:und_x_variant":[
        "A\u00efdara",
        "A\u00efdra"
    ],
    "wof:lang_x_official":[
        "wol",
        "fra"
    ],
    "wof:lang_x_spoken":[
        "wol",
        "fra"
    ],
    "wof:name":"Aidra",
    "wof:placetype":"locality"
},
  "geometry": {"coordinates":[-16.41667,13.68333],"type":"Point"}
}