{
  "type": "Feature",
  "properties": {
    "gn:admin1_code":"14.0",
    "gn:asciiname":"Goumel",
    "gn:country_code":"SN",
    "gn:dem":7,
    "gn:feature_class":"P",
    "gn:feature_code":"PPL",
    "gn:name":"Goumel",
    "gn:population":0,
    "gn:timezone":"Africa/Dakar",
    "iso:country":"SN",
    "wof:name":"Goumel",
    "wof:placetype":"locality"
},
  "geometry": {"coordinates":[-14.99547,16.61872],"type":"Point"}
}