{
  "type": "Feature",
  "properties": {
    "gn:admin1_code":"7.0",
    "gn:asciiname":"B'oungap",
    "gn:country_code":"SN",
    "gn:dem":31,
    "gn:feature_class":"P",
    "gn:feature_code":"PPL",
    "gn:name":"B\u2019oungap",
    "gn:population":0,
    "gn:timezone":"Africa/Dakar",
    "iso:country":"SN",
    "wof:name":"B'oungap",
    "wof:placetype":"locality"
},
  "geometry": {"coordinates":[-17.10438,14.614],"type":"Point"}
}