{
  "type": "Feature",
  "properties": {
    "gn:admin1_code":"5.0",
    "gn:asciiname":"Boulel",
    "gn:cc2":"SN",
    "gn:country_code":"SN",
    "gn:dem":44,
    "gn:feature_class":"P",
    "gn:feature_code":"PPL",
    "gn:name":"Boul\u00e9l",
    "gn:population":0,
    "gn:timezone":"Africa/Dakar",
    "iso:country":"SN",
    "name:und_x_variant":[
        "Boul\u00e9le",
        "Boubel",
        "Boul\u00e9l"
    ],
    "wof:name":"Boulel",
    "wof:placetype":"locality"
},
  "geometry": {"coordinates":[-13.91667,14.23333],"type":"Point"}
}