{
  "type": "Feature",
  "properties": {
    "gn:admin1_code":"5.0",
    "gn:asciiname":"Sintiou Baba",
    "gn:country_code":"SN",
    "gn:dem":60,
    "gn:feature_class":"P",
    "gn:feature_code":"PPL",
    "gn:name":"Sintiou Baba",
    "gn:population":0,
    "gn:timezone":"Africa/Dakar",
    "iso:country":"SN",
    "wof:name":"Sintiou Baba",
    "wof:placetype":"locality"
},
  "geometry": {"coordinates":[-12.79143,14.24702],"type":"Point"}
}