{
  "type": "Feature",
  "properties": {
    "gn:admin1_code":"13.0",
    "gn:asciiname":"Sintiou Ndiobene",
    "gn:cc2":"SN",
    "gn:country_code":"SN",
    "gn:dem":37,
    "gn:feature_class":"P",
    "gn:feature_code":"PPL",
    "gn:name":"Sintiou Ndiob\u00e8ne",
    "gn:population":0,
    "gn:timezone":"Africa/Dakar",
    "iso:country":"SN",
    "name:und_x_variant":[
        "Seignethiou Diob\u00e8ne",
        "Sintiou Ndiob\u00e8ne"
    ],
    "wof:name":"Sintiou Ndiobene",
    "wof:placetype":"locality"
},
  "geometry": {"coordinates":[-16.36667000000001,15.73333],"type":"Point"}
}