{
  "type": "Feature",
  "properties": {
    "gn:admin1_code":"12.0",
    "gn:asciiname":"Kolomba",
    "gn:cc2":"SN",
    "gn:country_code":"SN",
    "gn:dem":5,
    "gn:feature_class":"P",
    "gn:feature_code":"PPL",
    "gn:name":"Kolomba",
    "gn:population":0,
    "gn:timezone":"Africa/Dakar",
    "iso:country":"SN",
    "name:und_x_variant":[
        "Kolonba",
        "Kolomba"
    ],
    "wof:name":"Kolomba",
    "wof:placetype":"locality"
},
  "geometry": {"coordinates":[-16.67527999999999,12.99778],"type":"Point"}
}