{
  "type": "Feature",
  "properties": {
    "gn:admin1_code":"15.0",
    "gn:asciiname":"Galayabe Foulbe",
    "gn:country_code":"SN",
    "gn:dem":32,
    "gn:feature_class":"P",
    "gn:feature_code":"PPL",
    "gn:name":"Galayab\u00e9 Foulb\u00e9",
    "gn:population":0,
    "gn:timezone":"Africa/Dakar",
    "iso:country":"SN",
    "wof:name":"Galayabe Foulbe",
    "wof:placetype":"locality"
},
  "geometry": {"coordinates":[-13.34258,15.52124],"type":"Point"}
}