{
  "type": "Feature",
  "properties": {
    "gn:admin1_code":"5.0",
    "gn:asciiname":"Sintiou Amat Modi",
    "gn:cc2":"SN",
    "gn:country_code":"SN",
    "gn:dem":52,
    "gn:feature_class":"P",
    "gn:feature_code":"PPL",
    "gn:name":"Sintiou Amat Modi",
    "gn:population":0,
    "gn:timezone":"Africa/Dakar",
    "iso:country":"SN",
    "name:und_x_variant":[
        "Sinntiou Amat Modi",
        "Sintiou Amat Modi"
    ],
    "wof:name":"Sintiou Amat Modi",
    "wof:placetype":"locality"
},
  "geometry": {"coordinates":[-13.03333,14.38333],"type":"Point"}
}