{
  "type": "Feature",
  "properties": {
    "gn:admin1_code":"11.0",
    "gn:asciiname":"Sourel Moulaye",
    "gn:country_code":"SN",
    "gn:dem":51,
    "gn:feature_class":"P",
    "gn:feature_code":"PPL",
    "gn:name":"Sourel Moulaye",
    "gn:population":0,
    "gn:timezone":"Africa/Dakar",
    "iso:country":"SN",
    "wof:name":"Sourel Moulaye",
    "wof:placetype":"locality"
},
  "geometry": {"coordinates":[-14.26667,13.06667],"type":"Point"}
}