{
  "type": "Feature",
  "properties": {
    "gn:admin1_code":"17.0",
    "gn:asciiname":"Batimba",
    "gn:country_code":"SN",
    "gn:dem":93,
    "gn:feature_class":"P",
    "gn:feature_code":"PPL",
    "gn:name":"Batimba",
    "gn:population":0,
    "gn:timezone":"Africa/Dakar",
    "iso:country":"SN",
    "name:und_x_variant":[
        "Batinba",
        "Batimba"
    ],
    "wof:name":"Batimba",
    "wof:placetype":"locality"
},
  "geometry": {"coordinates":[-12.549,12.4825],"type":"Point"}
}