{
  "type": "Feature",
  "properties": {
    "gn:admin1_code":"13.0",
    "gn:asciiname":"Belil Nelbi",
    "gn:country_code":"SN",
    "gn:dem":48,
    "gn:feature_class":"P",
    "gn:feature_code":"PPL",
    "gn:name":"Belil Nelbi",
    "gn:population":0,
    "gn:timezone":"Africa/Dakar",
    "iso:country":"SN",
    "wof:name":"Belil Nelbi",
    "wof:placetype":"locality"
},
  "geometry": {"coordinates":[-15.1921,15.1741],"type":"Point"}
}