{
  "type": "Feature",
  "properties": {
    "gn:admin1_code":"5.0",
    "gn:asciiname":"Sintiou Kagnoube",
    "gn:cc2":"SN",
    "gn:country_code":"SN",
    "gn:dem":74,
    "gn:feature_class":"P",
    "gn:feature_code":"PPL",
    "gn:name":"Sintiou Kagnoub\u00e9",
    "gn:population":0,
    "gn:timezone":"Africa/Dakar",
    "iso:country":"SN",
    "name:und_x_variant":[
        "Sinntiou Kagnoub\u00e9",
        "Sinthiou Kagnoub\u00e9",
        "Sintiou Kagnoub\u00e9"
    ],
    "wof:lang_x_official":[
        "wol",
        "fra"
    ],
    "wof:lang_x_spoken":[
        "wol",
        "fra"
    ],
    "wof:name":"Sintiou Kagnoube",
    "wof:placetype":"locality"
},
  "geometry": {"coordinates":[-13.08333,13.16667],"type":"Point"}
}