{
  "type": "Feature",
  "properties": {
    "gn:admin1_code":"7.0",
    "gn:asciiname":"Koure",
    "gn:country_code":"SN",
    "gn:dem":35,
    "gn:feature_class":"P",
    "gn:feature_code":"PPL",
    "gn:name":"Kour\u00e9",
    "gn:population":0,
    "gn:timezone":"Africa/Dakar",
    "iso:country":"SN",
    "name:ceb_x_preferred":[
        "Kour\u00e9"
    ],
    "name:deu_x_preferred":[
        "Kour\u00e9"
    ],
    "name:swe_x_preferred":[
        "Kour\u00e9"
    ],
    "wof:name":"Koure",
    "wof:placetype":"locality"
},
  "geometry": {"coordinates":[-16.56667,15.08333],"type":"Point"}
}