{
  "type": "Feature",
  "properties": {
    "gn:admin1_code":"16.0",
    "gn:asciiname":"Maleme",
    "gn:country_code":"SN",
    "gn:dem":30,
    "gn:feature_class":"P",
    "gn:feature_code":"PPL",
    "gn:name":"Mal\u00e8me",
    "gn:population":0,
    "gn:timezone":"Africa/Dakar",
    "iso:country":"SN",
    "name:cat_x_preferred":[
        "M\u00e0leme"
    ],
    "name:deu_x_preferred":[
        "Maleme"
    ],
    "name:ell_x_preferred":[
        "\u039c\u03ac\u03bb\u03b5\u03bc\u03b5 \u03a7\u03b1\u03bd\u03af\u03c9\u03bd"
    ],
    "name:epo_x_preferred":[
        "Maleme"
    ],
    "name:fin_x_preferred":[
        "M\u00e1leme"
    ],
    "name:fra_x_preferred":[
        "Maleme"
    ],
    "name:ita_x_preferred":[
        "Mal\u00e9me"
    ],
    "name:pol_x_preferred":[
        "Maleme"
    ],
    "name:por_x_preferred":[
        "M\u00e1leme"
    ],
    "name:rus_x_preferred":[
        "\u041c\u0430\u043b\u0435\u043c\u0435"
    ],
    "name:spa_x_preferred":[
        "M\u00e1leme"
    ],
    "name:swe_x_preferred":[
        "Maleme"
    ],
    "name:ukr_x_preferred":[
        "\u041c\u0430\u043b\u0435\u043c\u0435"
    ],
    "name:und_x_variant":[
        "Mal\u00e8m",
        "Mal\u00e8me"
    ],
    "wof:name":"Maleme",
    "wof:placetype":"locality"
},
  "geometry": {"coordinates":[-15.23333,14.05],"type":"Point"}
}