{
  "type": "Feature",
  "properties": {
    "gn:admin1_code":"16.0",
    "gn:asciiname":"Maleme",
    "gn:country_code":"SN",
    "gn:dem":30,
    "gn:feature_class":"P",
    "gn:feature_code":"PPL",
    "gn:name":"Mal\u00e8me",
    "gn:population":0,
    "gn:timezone":"Africa/Dakar",
    "iso:country":"SN",
    "name:und_x_variant":[
        "Mal\u00e8m",
        "Mal\u00e8me"
    ],
    "wof:name":"Maleme",
    "wof:placetype":"locality"
},
  "geometry": {"coordinates":[-15.23333,14.05],"type":"Point"}
}