{
  "type": "Feature",
  "properties": {
    "gn:admin1_code":"13.0",
    "gn:asciiname":"Mbayene",
    "gn:country_code":"SN",
    "gn:dem":44,
    "gn:feature_class":"P",
    "gn:feature_code":"PPL",
    "gn:name":"Mbay\u00e8ne",
    "gn:population":0,
    "gn:timezone":"Africa/Dakar",
    "iso:country":"SN",
    "name:und_x_variant":[
        "N\u2019Bayene Tiasd\u00e9",
        "Mbavene Thiasde",
        "Mbayen",
        "Mbay\u00e8ne-Thiasd\u00e9",
        "Mbay\u00e8ne"
    ],
    "wof:name":"Mbayene",
    "wof:placetype":"locality"
},
  "geometry": {"coordinates":[-15.5643,15.5114],"type":"Point"}
}