{
  "type": "Feature",
  "properties": {
    "gn:admin1_code":"7.0",
    "gn:asciiname":"Balabougou",
    "gn:cc2":"SN",
    "gn:country_code":"SN",
    "gn:dem":12,
    "gn:feature_class":"P",
    "gn:feature_code":"PPL",
    "gn:name":"Balabougou",
    "gn:population":0,
    "gn:timezone":"Africa/Dakar",
    "iso:country":"SN",
    "name:und_x_variant":[
        "Balabou",
        "Balabougou"
    ],
    "wof:name":"Balabougou",
    "wof:placetype":"locality"
},
  "geometry": {"coordinates":[-16.81667,14.35],"type":"Point"}
}