{
  "type": "Feature",
  "properties": {
    "gn:admin1_code":"7.0",
    "gn:asciiname":"Til Sieno",
    "gn:country_code":"SN",
    "gn:dem":40,
    "gn:feature_class":"P",
    "gn:feature_code":"PPL",
    "gn:name":"Til Si\u00e9no",
    "gn:population":0,
    "gn:timezone":"Africa/Dakar",
    "iso:country":"SN",
    "wof:name":"Til Sieno",
    "wof:placetype":"locality"
},
  "geometry": {"coordinates":[-16.36667000000001,15.18333],"type":"Point"}
}