{
  "type": "Feature",
  "properties": {
    "gn:admin1_code":"5.0",
    "gn:asciiname":"Koudi",
    "gn:country_code":"SN",
    "gn:dem":45,
    "gn:feature_class":"P",
    "gn:feature_code":"PPL",
    "gn:name":"Koudi",
    "gn:population":0,
    "gn:timezone":"Africa/Dakar",
    "iso:country":"SN",
    "name:fra_x_preferred":[
        "Koudi"
    ],
    "name:slk_x_preferred":[
        "Koudi"
    ],
    "name:und_x_variant":[
        "Koudy",
        "Kondy",
        "Koudi"
    ],
    "wof:name":"Koudi",
    "wof:placetype":"locality"
},
  "geometry": {"coordinates":[-12.76891,14.03597],"type":"Point"}
}