{
  "type": "Feature",
  "properties": {
    "gn:admin1_code":"3.0",
    "gn:asciiname":"Keur Masser",
    "gn:cc2":"SN",
    "gn:country_code":"SN",
    "gn:dem":40,
    "gn:feature_class":"P",
    "gn:feature_code":"PPL",
    "gn:name":"Keur Masser",
    "gn:population":0,
    "gn:timezone":"Africa/Dakar",
    "iso:country":"SN",
    "name:und_x_variant":[
        "Keur Massere",
        "Keur Masser"
    ],
    "wof:lang_x_official":[
        "wol",
        "fra"
    ],
    "wof:lang_x_spoken":[
        "wol",
        "fra"
    ],
    "wof:name":"Keur Masser",
    "wof:placetype":"locality"
},
  "geometry": {"coordinates":[-16.31667,14.88333],"type":"Point"}
}