{
  "type": "Feature",
  "properties": {
    "gn:admin1_code":"15.0",
    "gn:asciiname":"Gourel Mama Demba",
    "gn:country_code":"SN",
    "gn:dem":56,
    "gn:feature_class":"P",
    "gn:feature_code":"PPL",
    "gn:name":"Gourel Mama Demba",
    "gn:population":0,
    "gn:timezone":"Africa/Dakar",
    "iso:country":"SN",
    "name:und_x_variant":[
        "Gangel Mama Dinba",
        "Gourel Mama Demba"
    ],
    "wof:name":"Gourel Mama Demba",
    "wof:placetype":"locality"
},
  "geometry": {"coordinates":[-12.70095,14.89431],"type":"Point"}
}