{
  "type": "Feature",
  "properties": {
    "gn:admin1_code":"13.0",
    "gn:asciiname":"Nelbi",
    "gn:country_code":"SN",
    "gn:dem":44,
    "gn:feature_class":"P",
    "gn:feature_code":"PPL",
    "gn:name":"Nelbi",
    "gn:population":0,
    "gn:timezone":"Africa/Dakar",
    "iso:country":"SN",
    "name:und_x_variant":[
        "Nelb\u00e8",
        "Nelbi"
    ],
    "wof:name":"Nelbi",
    "wof:placetype":"locality"
},
  "geometry": {"coordinates":[-15.5802,15.478],"type":"Point"}
}