{
  "type": "Feature",
  "properties": {
    "gn:admin1_code":"10.0",
    "gn:asciiname":"Samba Drame",
    "gn:country_code":"SN",
    "gn:dem":38,
    "gn:feature_class":"P",
    "gn:feature_code":"PPL",
    "gn:name":"Samba Dram\u00e9",
    "gn:population":0,
    "gn:timezone":"Africa/Dakar",
    "iso:country":"SN",
    "wof:name":"Samba Drame",
    "wof:placetype":"locality"
},
  "geometry": {"coordinates":[-16.03333,13.81667],"type":"Point"}
}