{
  "type": "Feature",
  "properties": {
    "gn:admin1_code":"12.0",
    "gn:asciiname":"Kabiline",
    "gn:country_code":"SN",
    "gn:dem":4,
    "gn:feature_class":"P",
    "gn:feature_code":"PPL",
    "gn:name":"Kabiline",
    "gn:population":0,
    "gn:timezone":"Africa/Dakar",
    "iso:country":"SN",
    "name:fra_x_preferred":[
        "Kabiline"
    ],
    "wof:name":"Kabiline",
    "wof:placetype":"locality"
},
  "geometry": {"coordinates":[-16.56194,12.95583],"type":"Point"}
}