{
  "type": "Feature",
  "properties": {
    "gn:admin1_code":"13.0",
    "gn:asciiname":"Loumbi Arabobe",
    "gn:country_code":"SN",
    "gn:dem":43,
    "gn:feature_class":"P",
    "gn:feature_code":"PPL",
    "gn:name":"Loumbi Arabob\u00e9",
    "gn:population":0,
    "gn:timezone":"Africa/Dakar",
    "iso:country":"SN",
    "wof:name":"Loumbi Arabobe",
    "wof:placetype":"locality"
},
  "geometry": {"coordinates":[-15.5014,15.8654],"type":"Point"}
}