{
  "type": "Feature",
  "properties": {
    "gn:admin1_code":"7.0",
    "gn:asciiname":"Tanguis",
    "gn:country_code":"SN",
    "gn:dem":31,
    "gn:feature_class":"P",
    "gn:feature_code":"PPL",
    "gn:name":"Tanguis",
    "gn:population":0,
    "gn:timezone":"Africa/Dakar",
    "iso:country":"SN",
    "wof:name":"Tanguis",
    "wof:placetype":"locality"
},
  "geometry": {"coordinates":[-17.13081,14.64076],"type":"Point"}
}