{
  "type": "Feature",
  "properties": {
    "gn:admin1_code":"17.0",
    "gn:asciiname":"Bagni-Bagni",
    "gn:country_code":"SN",
    "gn:dem":156,
    "gn:feature_class":"P",
    "gn:feature_code":"PPL",
    "gn:name":"Bagni-Bagni",
    "gn:population":0,
    "gn:timezone":"Africa/Dakar",
    "iso:country":"SN",
    "name:und_x_variant":[
        "Bagnou-Bagnou",
        "Bagny-Bagny",
        "Bagni-Bagni"
    ],
    "wof:lang_x_official":[
        "wol",
        "fra"
    ],
    "wof:lang_x_spoken":[
        "wol",
        "fra"
    ],
    "wof:name":"Bagni-Bagni",
    "wof:placetype":"locality"
},
  "geometry": {"coordinates":[-11.64605,12.93036],"type":"Point"}
}