{
  "type": "Feature",
  "properties": {
    "gn:admin1_code":"3.0",
    "gn:asciiname":"Tienngoul",
    "gn:cc2":"SN",
    "gn:country_code":"SN",
    "gn:dem":31,
    "gn:feature_class":"P",
    "gn:feature_code":"PPL",
    "gn:name":"Tienngoul",
    "gn:population":0,
    "gn:timezone":"Africa/Dakar",
    "iso:country":"SN",
    "name:und_x_variant":[
        "Ti\u00e8negou",
        "Tienngoul"
    ],
    "wof:name":"Tienngoul",
    "wof:placetype":"locality"
},
  "geometry": {"coordinates":[-15.81667,14.76667],"type":"Point"}
}