{
  "type": "Feature",
  "properties": {
    "gn:admin1_code":"9.0",
    "gn:asciiname":"Kahone",
    "gn:country_code":"SN",
    "gn:dem":0,
    "gn:feature_class":"P",
    "gn:feature_code":"PPL",
    "gn:name":"Kahone",
    "gn:population":0,
    "gn:timezone":"Africa/Dakar",
    "iso:country":"SN",
    "wof:name":"Kahone",
    "wof:placetype":"locality"
},
  "geometry": {"coordinates":[-16.03333,14.15],"type":"Point"}
}