{
  "type": "Feature",
  "properties": {
    "gn:admin1_code":"9.0",
    "gn:asciiname":"Kahone",
    "gn:country_code":"SN",
    "gn:dem":0,
    "gn:feature_class":"P",
    "gn:feature_code":"PPL",
    "gn:name":"Kahone",
    "gn:population":0,
    "gn:timezone":"Africa/Dakar",
    "iso:country":"SN",
    "name:ceb_x_preferred":[
        "Kahone"
    ],
    "name:deu_x_preferred":[
        "Kahone"
    ],
    "name:fin_x_preferred":[
        "Kahone"
    ],
    "name:fra_x_preferred":[
        "Kahone"
    ],
    "name:pol_x_preferred":[
        "Kahone"
    ],
    "name:swe_x_preferred":[
        "Kahone"
    ],
    "wof:lang_x_official":[
        "wol",
        "fra"
    ],
    "wof:lang_x_spoken":[
        "wol",
        "fra"
    ],
    "wof:name":"Kahone",
    "wof:placetype":"locality"
},
  "geometry": {"coordinates":[-16.03333,14.15],"type":"Point"}
}