{
  "type": "Feature",
  "properties": {
    "gn:admin1_code":"15.0",
    "gn:asciiname":"Madina Torobe",
    "gn:country_code":"SN",
    "gn:dem":70,
    "gn:feature_class":"P",
    "gn:feature_code":"PPL",
    "gn:name":"Madina Torob\u00e9",
    "gn:population":0,
    "gn:timezone":"Africa/Dakar",
    "iso:country":"SN",
    "wof:name":"Madina Torobe",
    "wof:placetype":"locality"
},
  "geometry": {"coordinates":[-12.90788,14.68183],"type":"Point"}
}