{
  "type": "Feature",
  "properties": {
    "gn:admin1_code":"14.0",
    "gn:asciiname":"Ross-Betio",
    "gn:country_code":"SN",
    "gn:dem":5,
    "gn:feature_class":"P",
    "gn:feature_code":"PPL",
    "gn:name":"Ross-B\u00e9tio",
    "gn:population":0,
    "gn:timezone":"Africa/Dakar",
    "iso:country":"SN",
    "name:und_x_variant":[
        "Ross",
        "Ross-B\u00e9tio",
        "Ross-B\u00e9thio"
    ],
    "wof:name":"Ross-Betio",
    "wof:placetype":"locality"
},
  "geometry": {"coordinates":[-16.13778,16.27333],"type":"Point"}
}