{
  "type": "Feature",
  "properties": {
    "gn:admin1_code":"5.0",
    "gn:asciiname":"Goudinseini",
    "gn:country_code":"SN",
    "gn:dem":63,
    "gn:feature_class":"P",
    "gn:feature_code":"PPL",
    "gn:name":"Goudinseini",
    "gn:population":0,
    "gn:timezone":"Africa/Dakar",
    "iso:country":"SN",
    "name:und_x_variant":[
        "Goud\u00e9saini",
        "Goudesemi",
        "Goudins\u00e9yni",
        "Goudinseini"
    ],
    "wof:name":"Goudinseini",
    "wof:placetype":"locality"
},
  "geometry": {"coordinates":[-12.99203,13.6244],"type":"Point"}
}