{
  "type": "Feature",
  "properties": {
    "gn:admin1_code":"5.0",
    "gn:asciiname":"Bakel",
    "gn:country_code":"SN",
    "gn:dem":28,
    "gn:feature_class":"P",
    "gn:feature_code":"PPL",
    "gn:name":"Bakel",
    "gn:population":0,
    "gn:timezone":"Africa/Dakar",
    "iso:country":"SN",
    "wof:name":"Bakel",
    "wof:placetype":"locality"
},
  "geometry": {"coordinates":[-12.45935,14.90238],"type":"Point"}
}