{
  "type": "Feature",
  "properties": {
    "gn:admin1_code":"5.0",
    "gn:asciiname":"Bakel",
    "gn:country_code":"SN",
    "gn:dem":28,
    "gn:feature_class":"P",
    "gn:feature_code":"PPL",
    "gn:name":"Bakel",
    "gn:population":0,
    "gn:timezone":"Africa/Dakar",
    "iso:country":"SN",
    "name:cat_x_preferred":[
        "Bakel"
    ],
    "name:deu_x_preferred":[
        "Bakel"
    ],
    "name:fin_x_preferred":[
        "Bakel"
    ],
    "name:fra_x_preferred":[
        "Bakel"
    ],
    "name:ita_x_preferred":[
        "Bakel"
    ],
    "name:pol_x_preferred":[
        "Bakel"
    ],
    "name:rus_x_preferred":[
        "\u0411\u0430\u043a\u0435\u043b\u044c"
    ],
    "name:swe_x_preferred":[
        "Bakel"
    ],
    "name:zho_x_preferred":[
        "\u5df4\u514b\u723e"
    ],
    "wof:name":"Bakel",
    "wof:placetype":"locality"
},
  "geometry": {"coordinates":[-12.45935,14.90238],"type":"Point"}
}