{
  "type": "Feature",
  "properties": {
    "gn:admin1_code":"18.0",
    "gn:asciiname":"Inor",
    "gn:country_code":"SN",
    "gn:dem":14,
    "gn:feature_class":"P",
    "gn:feature_code":"PPL",
    "gn:name":"Inor",
    "gn:population":0,
    "gn:timezone":"Africa/Dakar",
    "iso:country":"SN",
    "wof:name":"Inor",
    "wof:placetype":"locality"
},
  "geometry": {"coordinates":[-15.70806,12.99556],"type":"Point"}
}