{
  "type": "Feature",
  "properties": {
    "gn:admin1_code":"11.0",
    "gn:asciiname":"Sare Kolissale",
    "gn:country_code":"SN",
    "gn:dem":33,
    "gn:feature_class":"P",
    "gn:feature_code":"PPL",
    "gn:name":"Sar\u00e9 Kolissal\u00e9",
    "gn:population":0,
    "gn:timezone":"Africa/Dakar",
    "iso:country":"SN",
    "wof:name":"Sare Kolissale",
    "wof:placetype":"locality"
},
  "geometry": {"coordinates":[-14.06667,13.06667],"type":"Point"}
}