{
  "type": "Feature",
  "properties": {
    "gn:admin1_code":"7.0",
    "gn:asciiname":"Lalane",
    "gn:country_code":"SN",
    "gn:dem":63,
    "gn:feature_class":"P",
    "gn:feature_code":"PPL",
    "gn:name":"Lalane",
    "gn:population":0,
    "gn:timezone":"Africa/Dakar",
    "iso:country":"SN",
    "wof:name":"Lalane",
    "wof:placetype":"locality"
},
  "geometry": {"coordinates":[-16.88332999999999,14.85],"type":"Point"}
}