{
  "type": "Feature",
  "properties": {
    "gn:admin1_code":"11.0",
    "gn:asciiname":"Sare Diallo",
    "gn:country_code":"SN",
    "gn:dem":22,
    "gn:feature_class":"P",
    "gn:feature_code":"PPL",
    "gn:name":"Sar\u00e9 Diallo",
    "gn:population":0,
    "gn:timezone":"Africa/Dakar",
    "iso:country":"SN",
    "wof:name":"Sare Diallo",
    "wof:placetype":"locality"
},
  "geometry": {"coordinates":[-15.06667,12.71667],"type":"Point"}
}