{
  "type": "Feature",
  "properties": {
    "gn:admin1_code":"17.0",
    "gn:asciiname":"Sangola",
    "gn:country_code":"SN",
    "gn:dem":101,
    "gn:feature_class":"P",
    "gn:feature_code":"PPL",
    "gn:name":"Sangola",
    "gn:population":0,
    "gn:timezone":"Africa/Dakar",
    "iso:country":"SN",
    "wof:name":"Sangola",
    "wof:placetype":"locality"
},
  "geometry": {"coordinates":[-12.45,12.66667],"type":"Point"}
}