{
  "type": "Feature",
  "properties": {
    "gn:admin1_code":"5.0",
    "gn:asciiname":"Sintiou Dialo",
    "gn:cc2":"SN",
    "gn:country_code":"SN",
    "gn:dem":30,
    "gn:feature_class":"P",
    "gn:feature_code":"PPL",
    "gn:name":"Sintiou Dialo",
    "gn:population":0,
    "gn:timezone":"Africa/Dakar",
    "iso:country":"SN",
    "name:und_x_variant":[
        "Sinntiou Dialo",
        "Sintiou Dialo"
    ],
    "wof:lang_x_official":[
        "wol",
        "fra"
    ],
    "wof:lang_x_spoken":[
        "wol",
        "fra"
    ],
    "wof:name":"Sintiou Dialo",
    "wof:placetype":"locality"
},
  "geometry": {"coordinates":[-13.78333,13.75],"type":"Point"}
}