{
  "type": "Feature",
  "properties": {
    "gn:admin1_code":"5.0",
    "gn:asciiname":"Gangali",
    "gn:country_code":"SN",
    "gn:dem":66,
    "gn:feature_class":"P",
    "gn:feature_code":"PPL",
    "gn:name":"Gangali",
    "gn:population":0,
    "gn:timezone":"Africa/Dakar",
    "iso:country":"SN",
    "wof:name":"Gangali",
    "wof:placetype":"locality"
},
  "geometry": {"coordinates":[-12.73098,13.72829],"type":"Point"}
}