{
  "type": "Feature",
  "properties": {
    "gn:admin1_code":"3.0",
    "gn:asciiname":"Abdou",
    "gn:cc2":"SN",
    "gn:country_code":"SN",
    "gn:dem":39,
    "gn:feature_class":"P",
    "gn:feature_code":"PPL",
    "gn:name":"Abdou",
    "gn:population":0,
    "gn:timezone":"Africa/Dakar",
    "iso:country":"SN",
    "name:und_x_variant":[
        "Keur Abdou",
        "Abdou"
    ],
    "wof:name":"Abdou",
    "wof:placetype":"locality"
},
  "geometry": {"coordinates":[-16.33333,14.95],"type":"Point"}
}