{
  "type": "Feature",
  "properties": {
    "gn:admin1_code":"13.0",
    "gn:asciiname":"Tieurigne",
    "gn:cc2":"SN",
    "gn:country_code":"SN",
    "gn:dem":41,
    "gn:feature_class":"P",
    "gn:feature_code":"PPL",
    "gn:name":"Tieurigne",
    "gn:population":0,
    "gn:timezone":"Africa/Dakar",
    "iso:country":"SN",
    "name:und_x_variant":[
        "Ti\u00e9rigne",
        "Tieurigne"
    ],
    "wof:name":"Tieurigne",
    "wof:placetype":"locality"
},
  "geometry": {"coordinates":[-16.45,15.56667],"type":"Point"}
}