{
  "type": "Feature",
  "properties": {
    "gn:admin1_code":"18.0",
    "gn:asciiname":"Sandinier",
    "gn:country_code":"SN",
    "gn:dem":12,
    "gn:feature_class":"P",
    "gn:feature_code":"PPL",
    "gn:name":"Sandini\u00e8r",
    "gn:population":0,
    "gn:timezone":"Africa/Dakar",
    "iso:country":"SN",
    "name:und_x_variant":[
        "Sandini\u00e8re",
        "Sandini\u00e8r"
    ],
    "wof:name":"Sandinier",
    "wof:placetype":"locality"
},
  "geometry": {"coordinates":[-15.52972,12.73167],"type":"Point"}
}