{
  "type": "Feature",
  "properties": {
    "gn:admin1_code":"13.0",
    "gn:asciiname":"Kofie",
    "gn:country_code":"SN",
    "gn:dem":22,
    "gn:feature_class":"P",
    "gn:feature_code":"PPL",
    "gn:name":"Kofi\u00e8",
    "gn:population":0,
    "gn:timezone":"Africa/Dakar",
    "iso:country":"SN",
    "wof:name":"Kofie",
    "wof:placetype":"locality"
},
  "geometry": {"coordinates":[-15.9218,15.8586],"type":"Point"}
}