{
  "type": "Feature",
  "properties": {
    "gn:admin1_code":"13.0",
    "gn:asciiname":"Ndam Guinop",
    "gn:cc2":"SN",
    "gn:country_code":"SN",
    "gn:dem":43,
    "gn:feature_class":"P",
    "gn:feature_code":"PPL",
    "gn:name":"Ndam Guinop",
    "gn:population":0,
    "gn:timezone":"Africa/Dakar",
    "iso:country":"SN",
    "name:und_x_variant":[
        "N\u2019D\u00e2me",
        "Ndam Guinop"
    ],
    "wof:name":"Ndam Guinop",
    "wof:placetype":"locality"
},
  "geometry": {"coordinates":[-16.25,15.33333],"type":"Point"}
}