{
  "type": "Feature",
  "properties": {
    "gn:admin1_code":"13.0",
    "gn:asciiname":"Bounar",
    "gn:country_code":"SN",
    "gn:dem":42,
    "gn:feature_class":"P",
    "gn:feature_code":"PPL",
    "gn:name":"Bounar",
    "gn:population":0,
    "gn:timezone":"Africa/Dakar",
    "iso:country":"SN",
    "wof:name":"Bounar",
    "wof:placetype":"locality"
},
  "geometry": {"coordinates":[-16.11667000000001,15.33333],"type":"Point"}
}