{
  "type": "Feature",
  "properties": {
    "gn:admin1_code":"16.0",
    "gn:asciiname":"Kouyane",
    "gn:country_code":"SN",
    "gn:dem":50,
    "gn:feature_class":"P",
    "gn:feature_code":"PPL",
    "gn:name":"Kouyan\u00e9",
    "gn:population":0,
    "gn:timezone":"Africa/Dakar",
    "iso:country":"SN",
    "name:und_x_variant":[
        "Kouyan",
        "Kouyan\u00e9"
    ],
    "wof:name":"Kouyane",
    "wof:placetype":"locality"
},
  "geometry": {"coordinates":[-15.51667,14.41667],"type":"Point"}
}