{
  "type": "Feature",
  "properties": {
    "gn:admin1_code":"7.0",
    "gn:asciiname":"Killi",
    "gn:cc2":"SN",
    "gn:country_code":"SN",
    "gn:dem":36,
    "gn:feature_class":"P",
    "gn:feature_code":"PPL",
    "gn:name":"Killi",
    "gn:population":0,
    "gn:timezone":"Africa/Dakar",
    "iso:country":"SN",
    "name:und_x_variant":[
        "Killi Sat\u00e9",
        "Killi"
    ],
    "wof:name":"Killi",
    "wof:placetype":"locality"
},
  "geometry": {"coordinates":[-16.38332999999999,15.13333],"type":"Point"}
}