{
  "type": "Feature",
  "properties": {
    "gn:admin1_code":"11.0",
    "gn:asciiname":"Bakayoko",
    "gn:country_code":"SN",
    "gn:dem":65,
    "gn:feature_class":"P",
    "gn:feature_code":"PPL",
    "gn:name":"Bakayoko",
    "gn:population":0,
    "gn:timezone":"Africa/Dakar",
    "iso:country":"SN",
    "name:rus_x_preferred":[
        "\u0411\u0430\u043a\u0430\u0439\u043e\u043a\u043e"
    ],
    "wof:name":"Bakayoko",
    "wof:placetype":"locality"
},
  "geometry": {"coordinates":[-14.15,13.21667],"type":"Point"}
}