{
  "type": "Feature",
  "properties": {
    "gn:admin1_code":"9.0",
    "gn:asciiname":"Mbayene",
    "gn:country_code":"SN",
    "gn:dem":33,
    "gn:feature_class":"P",
    "gn:feature_code":"PPL",
    "gn:name":"Mbay\u00e8ne",
    "gn:population":0,
    "gn:timezone":"Africa/Dakar",
    "iso:country":"SN",
    "wof:name":"Mbayene",
    "wof:placetype":"locality"
},
  "geometry": {"coordinates":[-15.76667,14.58333],"type":"Point"}
}