{
  "type": "Feature",
  "properties": {
    "gn:admin1_code":"13.0",
    "gn:asciiname":"Cherif",
    "gn:cc2":"SN",
    "gn:country_code":"SN",
    "gn:dem":49,
    "gn:feature_class":"P",
    "gn:feature_code":"PPL",
    "gn:name":"Ch\u00e9rif",
    "gn:population":0,
    "gn:timezone":"Africa/Dakar",
    "iso:country":"SN",
    "name:deu_x_preferred":[
        "Cherif"
    ],
    "name:fra_x_preferred":[
        "Cherif"
    ],
    "name:und_x_variant":[
        "Serif",
        "Ch\u00e9rif"
    ],
    "wof:name":"Cherif",
    "wof:placetype":"locality"
},
  "geometry": {"coordinates":[-16.58333,15.28333],"type":"Point"}
}