{
  "type": "Feature",
  "properties": {
    "gn:admin1_code":"13.0",
    "gn:asciiname":"Ali Ndene",
    "gn:country_code":"SN",
    "gn:dem":49,
    "gn:feature_class":"P",
    "gn:feature_code":"PPL",
    "gn:name":"Ali Nd\u00e8n\u00e8",
    "gn:population":0,
    "gn:timezone":"Africa/Dakar",
    "iso:country":"SN",
    "wof:name":"Ali Ndene",
    "wof:placetype":"locality"
},
  "geometry": {"coordinates":[-15.7925,15.5075],"type":"Point"}
}