{
  "type": "Feature",
  "properties": {
    "gn:admin1_code":"3.0",
    "gn:asciiname":"Sokanou",
    "gn:country_code":"SN",
    "gn:dem":35,
    "gn:feature_class":"P",
    "gn:feature_code":"PPL",
    "gn:name":"Sokanou",
    "gn:population":0,
    "gn:timezone":"Africa/Dakar",
    "iso:country":"SN",
    "wof:name":"Sokanou",
    "wof:placetype":"locality"
},
  "geometry": {"coordinates":[-16.38332999999999,14.75],"type":"Point"}
}