{
  "type": "Feature",
  "properties": {
    "iso:country":"SN",
    "name:deu_x_preferred":[
        "Grand Dakar"
    ],
    "name:eng_x_preferred":[
        "Grand Dakar"
    ],
    "name:fra_x_preferred":[
        "Grand Dakar"
    ],
    "name:fra_x_variant":[
        "Grand Dakar Bope"
    ],
    "name:nld_x_preferred":[
        "Grand Dakar"
    ],
    "qs:gn_adm0_cc":"SN",
    "qs:gn_fcode":"PPL",
    "qs:gn_local":2253354,
    "qs:gn_nam_loc":"Dakar, Dakar, Dakar, SN",
    "qs:gn_namadm1":"01",
    "qs:gn_name":"Grand Dakar",
    "qs:local_max":378,
    "qs:local_sum":1759,
    "qs:localhoods":9,
    "qs:name":"Grand Dakar",
    "qs:name_adm0":"S\u00e9n\u00e9gal",
    "qs:name_adm1":"Dakar",
    "qs:name_adm2":"Dakar",
    "qs:name_local":"Dakar",
    "qs:photo_max":15,
    "qs:photo_sum":20,
    "qs:placetype":"Suburb",
    "qs:quad_count":5,
    "qs:woe_adm0":23424943,
    "qs:woe_adm1":2346988,
    "qs:woe_adm2":56055803,
    "qs:woe_lau":0,
    "qs:woe_local":1411986,
    "qs:woe_ver":"7.10.0",
    "wd:wordcount":31,
    "wof:name":"Grand Dakar",
    "wof:placetype":"neighbourhood"
},
  "geometry": {"coordinates":[-17.45343,14.714853],"type":"Point"}
}