{
  "type": "Feature",
  "properties": {
    "gn:country":"SN",
    "gn:fcode":"PPL",
    "gn:population":2352057,
    "iso:country":"SN",
    "name:deu_x_preferred":[
        "Grand Dakar"
    ],
    "name:eng_x_preferred":[
        "Grand Dakar"
    ],
    "name:fra_x_preferred":[
        "Grand Dakar"
    ],
    "name:fra_x_variant":[
        "Grand Dakar Bope"
    ],
    "name:nld_x_preferred":[
        "Grand Dakar"
    ],
    "qs:gn_adm0_cc":"SN",
    "qs:gn_fcode":"PPL",
    "qs:gn_local":2253354,
    "qs:gn_nam_loc":"Dakar, Dakar, Dakar, SN",
    "qs:gn_namadm1":"01",
    "qs:gn_name":"Grand Dakar",
    "qs:local_max":378,
    "qs:local_sum":1759,
    "qs:localhoods":9,
    "qs:name":"Grand Dakar",
    "qs:name_adm0":"S\u00e9n\u00e9gal",
    "qs:name_adm1":"Dakar",
    "qs:name_adm2":"Dakar",
    "qs:name_local":"Dakar",
    "qs:photo_max":15,
    "qs:photo_sum":20,
    "qs:placetype":"Suburb",
    "qs:quad_count":5,
    "qs:woe_adm0":23424943,
    "qs:woe_adm1":2346988,
    "qs:woe_adm2":56055803,
    "qs:woe_lau":0,
    "qs:woe_local":1411986,
    "qs:woe_ver":"7.10.0",
    "qs_pg:aaroncc":"SN",
    "qs_pg:gn_country":"SN",
    "qs_pg:gn_fcode":"PPL",
    "qs_pg:gn_pop":2352057,
    "qs_pg:name":"Grand Dakar",
    "qs_pg:name_adm0":"S\u00e9n\u00e9gal",
    "qs_pg:name_adm1":"Dakar",
    "qs_pg:photos":26,
    "qs_pg:photos_1k":5,
    "qs_pg:photos_9k":1,
    "qs_pg:photos_9r":2,
    "qs_pg:photos_all":26,
    "qs_pg:photos_sr":2,
    "qs_pg:pop_sr":12,
    "qs_pg:qs_pg_placetype":"neighbourhood",
    "qs_pg:qs_pg_placetype_gp":"Suburb",
    "qs_pg:woe_adm0":23424943,
    "wd:wordcount":31,
    "woe:adm0_id":23424943,
    "woe:name_adm0":"S\u00e9n\u00e9gal",
    "woe:name_adm1":"Dakar",
    "woe:placetype":"Suburb",
    "wof:lang":[
        "fre"
    ],
    "wof:name":"Grand Dakar",
    "wof:placetype":"neighbourhood",
    "wof:population":2352057
},
  "geometry": {"coordinates":[-17.45343,14.714853],"type":"Point"}
}