{
  "type": "Feature",
  "properties": {
    "gn:admin1_code":"14.0",
    "gn:asciiname":"Nguent Nawar",
    "gn:country_code":"SN",
    "gn:dem":20,
    "gn:feature_class":"P",
    "gn:feature_code":"PPL",
    "gn:name":"Ngu\u00e8nt Nawar",
    "gn:population":0,
    "gn:timezone":"Africa/Dakar",
    "iso:country":"SN",
    "wof:name":"Nguent Nawar",
    "wof:placetype":"locality"
},
  "geometry": {"coordinates":[-16.27222,16.16082999999999],"type":"Point"}
}