{
  "type": "Feature",
  "properties": {
    "gn:admin1_code":"7.0",
    "gn:asciiname":"Keur Pate Deye",
    "gn:country_code":"SN",
    "gn:dem":24,
    "gn:feature_class":"P",
    "gn:feature_code":"PPL",
    "gn:name":"Keur Pat\u00e9 D\u00e9ye",
    "gn:population":0,
    "gn:timezone":"Africa/Dakar",
    "iso:country":"SN",
    "wof:name":"Keur Pate Deye",
    "wof:placetype":"locality"
},
  "geometry": {"coordinates":[-16.78333,15.26667],"type":"Point"}
}