{
  "type": "Feature",
  "properties": {
    "gn:admin1_code":"12.0",
    "gn:asciiname":"Kafountine",
    "gn:cc2":"SN",
    "gn:country_code":"SN",
    "gn:dem":11,
    "gn:feature_class":"P",
    "gn:feature_code":"PPL",
    "gn:name":"Kafountine",
    "gn:population":0,
    "gn:timezone":"Africa/Dakar",
    "iso:country":"SN",
    "name:und_x_variant":[
        "Cafountine",
        "Kafoutin",
        "Cafoutine",
        "Kafountine"
    ],
    "wof:name":"Kafountine",
    "wof:placetype":"locality"
},
  "geometry": {"coordinates":[-16.73889,12.92528],"type":"Point"}
}