{
  "type": "Feature",
  "properties": {
    "gn:admin1_code":"5.0",
    "gn:asciiname":"Koliya",
    "gn:country_code":"SN",
    "gn:dem":102,
    "gn:feature_class":"P",
    "gn:feature_code":"PPL",
    "gn:name":"Koliya",
    "gn:population":0,
    "gn:timezone":"Africa/Dakar",
    "iso:country":"SN",
    "name:hin_x_preferred":[
        "\u0915\u094b\u0932\u0940\u092f"
    ],
    "name:hun_x_preferred":[
        "K\u00f3lij\u00e1k"
    ],
    "name:tam_x_preferred":[
        "\u0b95\u0bcb\u0bb2\u0bbf\u0baf\u0bb0\u0bcd"
    ],
    "name:und_x_variant":[
        "Kolia"
    ],
    "name:vie_x_preferred":[
        "Koliya"
    ],
    "wof:lang_x_official":[
        "wol",
        "fra"
    ],
    "wof:lang_x_spoken":[
        "wol",
        "fra"
    ],
    "wof:name":"Koliya",
    "wof:placetype":"locality"
},
  "geometry": {"coordinates":[-11.41363,12.97844],"type":"Point"}
}