{
  "type": "Feature",
  "properties": {
    "gn:admin1_code":"13.0",
    "gn:asciiname":"Diaene Parba",
    "gn:country_code":"SN",
    "gn:dem":32,
    "gn:feature_class":"P",
    "gn:feature_code":"PPL",
    "gn:name":"Dia\u00e8ne Parba",
    "gn:population":0,
    "gn:timezone":"Africa/Dakar",
    "iso:country":"SN",
    "name:und_x_variant":[
        "Dia\u00e8na Parba",
        "Dia\u00e8ne Parba"
    ],
    "wof:name":"Diaene Parba",
    "wof:placetype":"locality"
},
  "geometry": {"coordinates":[-15.2206,15.3932],"type":"Point"}
}