{
  "type": "Feature",
  "properties": {
    "gn:admin1_code":"15.0",
    "gn:asciiname":"Sintiou Marse",
    "gn:country_code":"SN",
    "gn:dem":46,
    "gn:feature_class":"P",
    "gn:feature_code":"PPL",
    "gn:name":"Sintiou Mars\u00e9",
    "gn:population":0,
    "gn:timezone":"Africa/Dakar",
    "iso:country":"SN",
    "name:und_x_variant":[
        "Sinntiou Mars\u00e9",
        "Sintiou Mars\u00e9"
    ],
    "wof:lang_x_official":[
        "wol",
        "fra"
    ],
    "wof:lang_x_spoken":[
        "wol",
        "fra"
    ],
    "wof:name":"Sintiou Marse",
    "wof:placetype":"locality"
},
  "geometry": {"coordinates":[-13.27151,15.45953],"type":"Point"}
}