{
  "type": "Feature",
  "properties": {
    "gn:admin1_code":"5.0",
    "gn:asciiname":"Sinntiou Omar Lile",
    "gn:country_code":"SN",
    "gn:dem":60,
    "gn:feature_class":"P",
    "gn:feature_code":"PPL",
    "gn:name":"Sinntiou Omar Lil\u00e9",
    "gn:population":0,
    "gn:timezone":"Africa/Dakar",
    "iso:country":"SN",
    "name:und_x_variant":[
        "Sintiou Omar Lil\u00e9",
        "Sinntiou Omar Lil\u00e9"
    ],
    "wof:name":"Sinntiou Omar Lile",
    "wof:placetype":"locality"
},
  "geometry": {"coordinates":[-12.77358,14.20545],"type":"Point"}
}