{
  "type": "Feature",
  "properties": {
    "gn:admin1_code":"11.0",
    "gn:asciiname":"Dioulagueul Banta",
    "gn:cc2":"SN",
    "gn:country_code":"SN",
    "gn:dem":54,
    "gn:feature_class":"P",
    "gn:feature_code":"PPL",
    "gn:name":"Dioulagueul Banta",
    "gn:population":0,
    "gn:timezone":"Africa/Dakar",
    "iso:country":"SN",
    "name:und_x_variant":[
        "Dioulagueu Banta",
        "Dioulagueul Banta"
    ],
    "wof:name":"Dioulagueul Banta",
    "wof:placetype":"locality"
},
  "geometry": {"coordinates":[-14.43333,13.21667],"type":"Point"}
}