{
  "type": "Feature",
  "properties": {
    "gn:admin1_code":"7.0",
    "gn:asciiname":"Fas Boye",
    "gn:country_code":"SN",
    "gn:dem":8,
    "gn:feature_class":"P",
    "gn:feature_code":"PPL",
    "gn:name":"Fas Boye",
    "gn:population":0,
    "gn:timezone":"Africa/Dakar",
    "iso:country":"SN",
    "name:und_x_variant":[
        "Fas Bou\u00e9",
        "Fas Boye"
    ],
    "wof:name":"Fas Boye",
    "wof:placetype":"locality"
},
  "geometry": {"coordinates":[-16.8379,15.2701],"type":"Point"}
}