{
  "type": "Feature",
  "properties": {
    "gn:admin1_code":"9.0",
    "gn:asciiname":"Doni Taif",
    "gn:country_code":"SN",
    "gn:dem":57,
    "gn:feature_class":"P",
    "gn:feature_code":"PPL",
    "gn:name":"Doni Ta\u00eff",
    "gn:population":0,
    "gn:timezone":"Africa/Dakar",
    "iso:country":"SN",
    "wof:name":"Doni Taif",
    "wof:placetype":"locality"
},
  "geometry": {"coordinates":[-15.63333,14.86667],"type":"Point"}
}