{
  "type": "Feature",
  "properties": {
    "gn:admin1_code":"5.0",
    "gn:asciiname":"Goundiour",
    "gn:cc2":"SN",
    "gn:country_code":"SN",
    "gn:dem":30,
    "gn:feature_class":"P",
    "gn:feature_code":"PPL",
    "gn:name":"Goundiour",
    "gn:population":0,
    "gn:timezone":"Africa/Dakar",
    "iso:country":"SN",
    "name:und_x_variant":[
        "Goundiou",
        "Goundiour"
    ],
    "wof:name":"Goundiour",
    "wof:placetype":"locality"
},
  "geometry": {"coordinates":[-14.43333,13.98333],"type":"Point"}
}