{
  "type": "Feature",
  "properties": {
    "gn:admin1_code":"10.0",
    "gn:asciiname":"Koutango",
    "gn:cc2":"SN",
    "gn:country_code":"SN",
    "gn:dem":21,
    "gn:feature_class":"P",
    "gn:feature_code":"PPL",
    "gn:name":"Koutango",
    "gn:population":0,
    "gn:timezone":"Africa/Dakar",
    "iso:country":"SN",
    "name:und_x_variant":[
        "Koutang",
        "Kutang",
        "Koutango"
    ],
    "wof:name":"Koutango",
    "wof:placetype":"locality"
},
  "geometry": {"coordinates":[-16.08333,13.66667],"type":"Point"}
}