{
  "type": "Feature",
  "properties": {
    "gn:admin1_code":"18.0",
    "gn:asciiname":"Boussinki",
    "gn:country_code":"SN",
    "gn:dem":45,
    "gn:feature_class":"P",
    "gn:feature_code":"PPL",
    "gn:name":"Boussinki",
    "gn:population":0,
    "gn:timezone":"Africa/Dakar",
    "iso:country":"SN",
    "name:und_x_variant":[
        "Bousanki",
        "Boussanki",
        "Boussinki"
    ],
    "wof:name":"Boussinki",
    "wof:placetype":"locality"
},
  "geometry": {"coordinates":[-15.58333,13.08333],"type":"Point"}
}