{
  "type": "Feature",
  "properties": {
    "gn:admin1_code":"5.0",
    "gn:asciiname":"Gouidi",
    "gn:cc2":"SN",
    "gn:country_code":"SN",
    "gn:dem":32,
    "gn:feature_class":"P",
    "gn:feature_code":"PPL",
    "gn:name":"Gouidi",
    "gn:population":0,
    "gn:timezone":"Africa/Dakar",
    "iso:country":"SN",
    "name:und_x_variant":[
        "Gouidy",
        "Gouili",
        "Gouidi"
    ],
    "wof:name":"Gouidi",
    "wof:placetype":"locality"
},
  "geometry": {"coordinates":[-13.93333,14.05],"type":"Point"}
}