{
  "type": "Feature",
  "properties": {
    "gn:admin1_code":"5.0",
    "gn:asciiname":"Yoro Sankoule",
    "gn:country_code":"SN",
    "gn:dem":32,
    "gn:feature_class":"P",
    "gn:feature_code":"PPL",
    "gn:name":"Yoro Sankoul\u00e9",
    "gn:population":0,
    "gn:timezone":"Africa/Dakar",
    "iso:country":"SN",
    "wof:name":"Yoro Sankoule",
    "wof:placetype":"locality"
},
  "geometry": {"coordinates":[-13.71667,13.86667],"type":"Point"}
}