{
  "type": "Feature",
  "properties": {
    "gn:admin1_code":"9.0",
    "gn:asciiname":"Samba Dia",
    "gn:cc2":"SN",
    "gn:country_code":"SN",
    "gn:dem":9,
    "gn:feature_class":"P",
    "gn:feature_code":"PPL",
    "gn:name":"Samba Dia",
    "gn:population":0,
    "gn:timezone":"Africa/Dakar",
    "iso:country":"SN",
    "name:und_x_variant":[
        "Keur Samba Dia"
    ],
    "wof:name":"Samba Dia",
    "wof:placetype":"locality"
},
  "geometry": {"coordinates":[-16.72782,14.13083],"type":"Point"}
}