{
  "type": "Feature",
  "properties": {
    "gn:country":"SN",
    "gn:fcode":"PPL",
    "gn:population":27741,
    "iso:country":"SN",
    "qs_pg:aaroncc":"SN",
    "qs_pg:gn_country":"SN",
    "qs_pg:gn_fcode":"PPL",
    "qs_pg:gn_pop":27741,
    "qs_pg:name":"Ndib\u00e8ne Dahra",
    "qs_pg:photos_9r":0,
    "qs_pg:photos_sr":0,
    "qs_pg:pop_sr":7,
    "qs_pg:qs_pg_placetype":"locality",
    "wof:lang_x_official":[
        "wol",
        "fra"
    ],
    "wof:lang_x_spoken":[
        "wol",
        "fra"
    ],
    "wof:name":"Ndib\u00e8ne Dahra",
    "wof:placetype":"locality",
    "wof:population":27741
},
  "geometry": {"coordinates":[-15.4766,15.3338],"type":"Point"}
}