{
  "type": "Feature",
  "properties": {
    "gn:admin1_code":"5.0",
    "gn:asciiname":"Paniat",
    "gn:country_code":"SN",
    "gn:dem":44,
    "gn:feature_class":"P",
    "gn:feature_code":"PPL",
    "gn:name":"Paniat",
    "gn:population":0,
    "gn:timezone":"Africa/Dakar",
    "iso:country":"SN",
    "wof:name":"Paniat",
    "wof:placetype":"locality"
},
  "geometry": {"coordinates":[-14.18333,14.01667],"type":"Point"}
}