{
  "type": "Feature",
  "properties": {
    "gn:admin1_code":"3.0",
    "gn:asciiname":"Ndiayene",
    "gn:cc2":"SN",
    "gn:country_code":"SN",
    "gn:dem":34,
    "gn:feature_class":"P",
    "gn:feature_code":"PPL",
    "gn:name":"Ndiay\u00e8ne",
    "gn:population":0,
    "gn:timezone":"Africa/Dakar",
    "iso:country":"SN",
    "name:und_x_variant":[
        "Ndi\u00e8ne",
        "Ndiay\u00e8ne"
    ],
    "wof:lang_x_official":[
        "wol",
        "fra"
    ],
    "wof:lang_x_spoken":[
        "wol",
        "fra"
    ],
    "wof:name":"Ndiayene",
    "wof:placetype":"locality"
},
  "geometry": {"coordinates":[-16.45,14.81667],"type":"Point"}
}