{
  "type": "Feature",
  "properties": {
    "gn:admin1_code":"12.0",
    "gn:asciiname":"Baraf",
    "gn:cc2":"SN",
    "gn:country_code":"SN",
    "gn:dem":23,
    "gn:feature_class":"P",
    "gn:feature_code":"PPL",
    "gn:name":"Baraf",
    "gn:population":0,
    "gn:timezone":"Africa/Dakar",
    "iso:country":"SN",
    "name:ceb_x_preferred":[
        "Baraf"
    ],
    "name:fra_x_preferred":[
        "Baraf"
    ],
    "name:und_x_variant":[
        "Barafe",
        "Baraf"
    ],
    "wof:name":"Baraf",
    "wof:placetype":"locality"
},
  "geometry": {"coordinates":[-16.30861,12.52056],"type":"Point"}
}