{
  "type": "Feature",
  "properties": {
    "gn:admin1_code":"17.0",
    "gn:asciiname":"Malinda",
    "gn:country_code":"SN",
    "gn:dem":185,
    "gn:feature_class":"P",
    "gn:feature_code":"PPL",
    "gn:name":"Malinda",
    "gn:population":0,
    "gn:timezone":"Africa/Dakar",
    "iso:country":"SN",
    "wof:name":"Malinda",
    "wof:placetype":"locality"
},
  "geometry": {"coordinates":[-11.95694,12.47624],"type":"Point"}
}