{
  "type": "Feature",
  "properties": {
    "gn:admin1_code":"12.0",
    "gn:asciiname":"Djioundji",
    "gn:country_code":"SN",
    "gn:dem":35,
    "gn:feature_class":"P",
    "gn:feature_code":"PPL",
    "gn:name":"Djioundji",
    "gn:population":0,
    "gn:timezone":"Africa/Dakar",
    "iso:country":"SN",
    "wof:name":"Djioundji",
    "wof:placetype":"locality"
},
  "geometry": {"coordinates":[-16.21667,13.08333],"type":"Point"}
}