{
  "type": "Feature",
  "properties": {
    "gn:admin1_code":"13.0",
    "gn:asciiname":"Kadiar Peul",
    "gn:cc2":"SN",
    "gn:country_code":"SN",
    "gn:dem":26,
    "gn:feature_class":"P",
    "gn:feature_code":"PPL",
    "gn:name":"Kadiar Peul",
    "gn:population":0,
    "gn:timezone":"Africa/Dakar",
    "iso:country":"SN",
    "name:und_x_variant":[
        "Kadiar Peulh",
        "Kadlar Peul",
        "Kadiar Peul"
    ],
    "wof:name":"Kadiar Peul",
    "wof:placetype":"locality"
},
  "geometry": {"coordinates":[-16.29778,15.80278],"type":"Point"}
}