{
  "type": "Feature",
  "properties": {
    "gn:admin1_code":"11.0",
    "gn:asciiname":"Tamassanssan",
    "gn:country_code":"SN",
    "gn:dem":30,
    "gn:feature_class":"P",
    "gn:feature_code":"PPL",
    "gn:name":"Tamassanssan",
    "gn:population":0,
    "gn:timezone":"Africa/Dakar",
    "iso:country":"SN",
    "wof:name":"Tamassanssan",
    "wof:placetype":"locality"
},
  "geometry": {"coordinates":[-14.18333,12.73333],"type":"Point"}
}