{
  "type": "Feature",
  "properties": {
    "gn:admin1_code":"13.0",
    "gn:asciiname":"Karatchel-Ouolof",
    "gn:country_code":"SN",
    "gn:dem":50,
    "gn:feature_class":"P",
    "gn:feature_code":"PPL",
    "gn:name":"Karatchel-Ouolof",
    "gn:population":0,
    "gn:timezone":"Africa/Dakar",
    "iso:country":"SN",
    "wof:name":"Karatchel-Ouolof",
    "wof:placetype":"locality"
},
  "geometry": {"coordinates":[-15.9557,15.1394],"type":"Point"}
}