{
  "type": "Feature",
  "properties": {
    "gn:admin1_code":"13.0",
    "gn:asciiname":"Ngomene",
    "gn:cc2":"SN",
    "gn:country_code":"SN",
    "gn:dem":20,
    "gn:feature_class":"P",
    "gn:feature_code":"PPL",
    "gn:name":"Ngom\u00e8ne",
    "gn:population":0,
    "gn:timezone":"Africa/Dakar",
    "iso:country":"SN",
    "name:und_x_variant":[
        "Mboyo Gom\u00e8ne",
        "Ngom\u00e8ne"
    ],
    "wof:name":"Ngomene",
    "wof:placetype":"locality"
},
  "geometry": {"coordinates":[-16.32722,15.81361],"type":"Point"}
}