{
  "type": "Feature",
  "properties": {
    "gn:admin1_code":"7.0",
    "gn:asciiname":"Ndjiw",
    "gn:country_code":"SN",
    "gn:dem":27,
    "gn:feature_class":"P",
    "gn:feature_code":"PPL",
    "gn:name":"Ndjiw",
    "gn:population":0,
    "gn:timezone":"Africa/Dakar",
    "iso:country":"SN",
    "wof:name":"Ndjiw",
    "wof:placetype":"locality"
},
  "geometry": {"coordinates":[-17.06661,14.5569],"type":"Point"}
}