{
  "type": "Feature",
  "properties": {
    "gn:admin1_code":"11.0",
    "gn:asciiname":"Sare Pate Bouya",
    "gn:cc2":"SN",
    "gn:country_code":"SN",
    "gn:dem":58,
    "gn:feature_class":"P",
    "gn:feature_code":"PPL",
    "gn:name":"Sar\u00e9 Pat\u00e9 Bouya",
    "gn:population":0,
    "gn:timezone":"Africa/Dakar",
    "iso:country":"SN",
    "name:und_x_variant":[
        "Sar\u00e9-Pat\u00e9-Bouia",
        "Sar\u00e9 Pat\u00e9 Bouya"
    ],
    "wof:name":"Sare Pate Bouya",
    "wof:placetype":"locality"
},
  "geometry": {"coordinates":[-14.36667,12.95],"type":"Point"}
}