{
  "type": "Feature",
  "properties": {
    "gn:admin1_code":"17.0",
    "gn:asciiname":"Oussounkala",
    "gn:country_code":"SN",
    "gn:dem":113,
    "gn:feature_class":"P",
    "gn:feature_code":"PPL",
    "gn:name":"Oussounkala",
    "gn:population":0,
    "gn:timezone":"Africa/Dakar",
    "iso:country":"SN",
    "wof:name":"Oussounkala",
    "wof:placetype":"locality"
},
  "geometry": {"coordinates":[-12.4639,12.7038],"type":"Point"}
}