{
  "type": "Feature",
  "properties": {
    "gn:admin1_code":"3.0",
    "gn:asciiname":"Darou Mbeye",
    "gn:country_code":"SN",
    "gn:dem":28,
    "gn:feature_class":"P",
    "gn:feature_code":"PPL",
    "gn:name":"Darou Mb\u00e8ye",
    "gn:population":0,
    "gn:timezone":"Africa/Dakar",
    "iso:country":"SN",
    "wof:name":"Darou Mbeye",
    "wof:placetype":"locality"
},
  "geometry": {"coordinates":[-16.33333,14.81667],"type":"Point"}
}