{
  "type": "Feature",
  "properties": {
    "gn:admin1_code":"15.0",
    "gn:asciiname":"Fadiara",
    "gn:country_code":"SN",
    "gn:dem":29,
    "gn:feature_class":"P",
    "gn:feature_code":"PPL",
    "gn:name":"Fadiara",
    "gn:population":0,
    "gn:timezone":"Africa/Dakar",
    "iso:country":"SN",
    "name:und_x_variant":[
        "Fadaria",
        "Fadiara"
    ],
    "wof:name":"Fadiara",
    "wof:placetype":"locality"
},
  "geometry": {"coordinates":[-12.8074,15.07923],"type":"Point"}
}