{
  "type": "Feature",
  "properties": {
    "gn:admin1_code":"13.0",
    "gn:asciiname":"Debolate",
    "gn:country_code":"SN",
    "gn:dem":51,
    "gn:feature_class":"P",
    "gn:feature_code":"PPL",
    "gn:name":"D\u00e8bolat\u00e9",
    "gn:population":0,
    "gn:timezone":"Africa/Dakar",
    "iso:country":"SN",
    "wof:name":"Debolate",
    "wof:placetype":"locality"
},
  "geometry": {"coordinates":[-15.9458,15.4769],"type":"Point"}
}