{
  "type": "Feature",
  "properties": {
    "gn:admin1_code":"10.0",
    "gn:asciiname":"Ndiba",
    "gn:country_code":"SN",
    "gn:dem":21,
    "gn:feature_class":"P",
    "gn:feature_code":"PPL",
    "gn:name":"Ndiba",
    "gn:population":0,
    "gn:timezone":"Africa/Dakar",
    "iso:country":"SN",
    "wof:name":"Ndiba",
    "wof:placetype":"locality"
},
  "geometry": {"coordinates":[-15.55,13.76667],"type":"Point"}
}