{
  "type": "Feature",
  "properties": {
    "gn:admin1_code":"16.0",
    "gn:asciiname":"Koumbidia",
    "gn:country_code":"SN",
    "gn:dem":14,
    "gn:feature_class":"P",
    "gn:feature_code":"PPL",
    "gn:name":"Koumbidia",
    "gn:population":0,
    "gn:timezone":"Africa/Dakar",
    "iso:country":"SN",
    "name:und_x_variant":[
        "Coumbidia",
        "Koumbidia"
    ],
    "wof:name":"Koumbidia",
    "wof:placetype":"locality"
},
  "geometry": {"coordinates":[-14.86667,13.91667],"type":"Point"}
}