{
  "type": "Feature",
  "properties": {
    "gn:admin1_code":"3.0",
    "gn:asciiname":"Pouniar",
    "gn:cc2":"SN",
    "gn:country_code":"SN",
    "gn:dem":40,
    "gn:feature_class":"P",
    "gn:feature_code":"PPL",
    "gn:name":"Pouniar",
    "gn:population":0,
    "gn:timezone":"Africa/Dakar",
    "iso:country":"SN",
    "name:und_x_variant":[
        "Pougnar",
        "Pouniar"
    ],
    "wof:name":"Pouniar",
    "wof:placetype":"locality"
},
  "geometry": {"coordinates":[-16.55,14.83333],"type":"Point"}
}