{
  "type": "Feature",
  "properties": {
    "gn:admin1_code":"9.0",
    "gn:asciiname":"Keur Bangou",
    "gn:country_code":"SN",
    "gn:dem":19,
    "gn:feature_class":"P",
    "gn:feature_code":"PPL",
    "gn:name":"Keur Bangou",
    "gn:population":0,
    "gn:timezone":"Africa/Dakar",
    "iso:country":"SN",
    "wof:name":"Keur Bangou",
    "wof:placetype":"locality"
},
  "geometry": {"coordinates":[-16.26667,13.88333],"type":"Point"}
}