{
  "type": "Feature",
  "properties": {
    "gn:admin1_code":"14.0",
    "gn:asciiname":"Demet",
    "gn:country_code":"SN",
    "gn:dem":13,
    "gn:feature_class":"P",
    "gn:feature_code":"PPL",
    "gn:name":"D\u00e9m\u00e8t",
    "gn:population":0,
    "gn:timezone":"Africa/Dakar",
    "iso:country":"SN",
    "name:cat_x_preferred":[
        "Demet"
    ],
    "name:deu_x_preferred":[
        "Demet"
    ],
    "name:tur_x_preferred":[
        "Demet"
    ],
    "name:und_x_variant":[
        "Diem\u00e8t Ti\u00e9nel",
        "Diem\u00e8l Ti\u00e9nel",
        "D\u00e9m\u00e8t"
    ],
    "wof:name":"Demet",
    "wof:placetype":"locality"
},
  "geometry": {"coordinates":[-14.28065,16.56442],"type":"Point"}
}