{
  "type": "Feature",
  "properties": {
    "gn:admin1_code":"9.0",
    "gn:asciiname":"Soudiane Loul",
    "gn:country_code":"SN",
    "gn:dem":6,
    "gn:feature_class":"P",
    "gn:feature_code":"PPL",
    "gn:name":"Soudiane Loul",
    "gn:population":0,
    "gn:timezone":"Africa/Dakar",
    "iso:country":"SN",
    "wof:name":"Soudiane Loul",
    "wof:placetype":"locality"
},
  "geometry": {"coordinates":[-16.68333,14.23333],"type":"Point"}
}