{
  "type": "Feature",
  "properties": {
    "gn:admin1_code":"5.0",
    "gn:asciiname":"Gourel Seliki",
    "gn:country_code":"SN",
    "gn:dem":62,
    "gn:feature_class":"P",
    "gn:feature_code":"PPL",
    "gn:name":"Gourel Seliki",
    "gn:population":0,
    "gn:timezone":"Africa/Dakar",
    "iso:country":"SN",
    "wof:name":"Gourel Seliki",
    "wof:placetype":"locality"
},
  "geometry": {"coordinates":[-12.5778,14.76462],"type":"Point"}
}