{
  "type": "Feature",
  "properties": {
    "gn:admin1_code":"5.0",
    "gn:asciiname":"Ndia",
    "gn:country_code":"SN",
    "gn:dem":81,
    "gn:feature_class":"P",
    "gn:feature_code":"PPL",
    "gn:name":"Ndia",
    "gn:population":0,
    "gn:timezone":"Africa/Dakar",
    "iso:country":"SN",
    "name:ceb_x_preferred":[
        "Ndia"
    ],
    "name:swe_x_preferred":[
        "Ndia"
    ],
    "wof:lang_x_official":[
        "wol",
        "fra"
    ],
    "wof:lang_x_spoken":[
        "wol",
        "fra"
    ],
    "wof:name":"Ndia",
    "wof:placetype":"locality"
},
  "geometry": {"coordinates":[-12.74976,14.55574],"type":"Point"}
}