{
  "type": "Feature",
  "properties": {
    "gn:admin1_code":"13.0",
    "gn:asciiname":"Keur Meissa",
    "gn:cc2":"SN",
    "gn:country_code":"SN",
    "gn:dem":32,
    "gn:feature_class":"P",
    "gn:feature_code":"PPL",
    "gn:name":"Keur M\u00e8\u00efssa",
    "gn:population":0,
    "gn:timezone":"Africa/Dakar",
    "iso:country":"SN",
    "name:und_x_variant":[
        "Keur Ma\u00efssa Bou",
        "Keur M\u00e8\u00efssa"
    ],
    "wof:name":"Keur Meissa",
    "wof:placetype":"locality"
},
  "geometry": {"coordinates":[-16.18333,15.75],"type":"Point"}
}