{
  "type": "Feature",
  "properties": {
    "gn:admin1_code":"15.0",
    "gn:asciiname":"Bloug",
    "gn:country_code":"SN",
    "gn:dem":17,
    "gn:feature_class":"P",
    "gn:feature_code":"PPL",
    "gn:name":"Bloug",
    "gn:population":0,
    "gn:timezone":"Africa/Dakar",
    "iso:country":"SN",
    "name:und_x_variant":[
        "Bloug Pour\u00e9",
        "Bloug"
    ],
    "wof:name":"Bloug",
    "wof:placetype":"locality"
},
  "geometry": {"coordinates":[-13.02208,15.43085],"type":"Point"}
}