{
  "type": "Feature",
  "properties": {
    "gn:admin1_code":"16.0",
    "gn:asciiname":"Diagle",
    "gn:country_code":"SN",
    "gn:dem":8,
    "gn:feature_class":"P",
    "gn:feature_code":"PPL",
    "gn:name":"Diagl\u00e9",
    "gn:population":0,
    "gn:timezone":"Africa/Dakar",
    "iso:country":"SN",
    "name:und_x_variant":[
        "Diackl\u00e9",
        "Diagl\u00e9"
    ],
    "wof:name":"Diagle",
    "wof:placetype":"locality"
},
  "geometry": {"coordinates":[-15.46667,14.18333],"type":"Point"}
}