{
  "type": "Feature",
  "properties": {
    "gn:admin1_code":"13.0",
    "gn:asciiname":"Thioyene",
    "gn:country_code":"SN",
    "gn:dem":49,
    "gn:feature_class":"P",
    "gn:feature_code":"PPL",
    "gn:name":"Thioy\u00e8ne",
    "gn:population":0,
    "gn:timezone":"Africa/Dakar",
    "iso:country":"SN",
    "name:und_x_variant":[
        "Tioy\u00e8ne",
        "Thioy\u00e8ne"
    ],
    "wof:name":"Thioyene",
    "wof:placetype":"locality"
},
  "geometry": {"coordinates":[-15.5209,15.1961],"type":"Point"}
}