{
  "type": "Feature",
  "properties": {
    "gn:admin1_code":"11.0",
    "gn:asciiname":"Balingor",
    "gn:cc2":"SN",
    "gn:country_code":"SN",
    "gn:dem":20,
    "gn:feature_class":"P",
    "gn:feature_code":"PPL",
    "gn:name":"Balingor",
    "gn:population":0,
    "gn:timezone":"Africa/Dakar",
    "iso:country":"SN",
    "name:ceb_x_preferred":[
        "Balingor"
    ],
    "name:fra_x_preferred":[
        "Balingore"
    ],
    "name:und_x_variant":[
        "Tobor Balingor",
        "Balingor"
    ],
    "wof:name":"Balingor",
    "wof:placetype":"locality"
},
  "geometry": {"coordinates":[-16.25,12.66667],"type":"Point"}
}