{
  "type": "Feature",
  "properties": {
    "gn:admin1_code":"13.0",
    "gn:asciiname":"Tiekha Gaye",
    "gn:cc2":"SN",
    "gn:country_code":"SN",
    "gn:dem":50,
    "gn:feature_class":"P",
    "gn:feature_code":"PPL",
    "gn:name":"Tiekha Gaye",
    "gn:population":0,
    "gn:timezone":"Africa/Dakar",
    "iso:country":"SN",
    "name:und_x_variant":[
        "Tia Khaou",
        "Tiekha Gaye"
    ],
    "wof:name":"Tiekha Gaye",
    "wof:placetype":"locality"
},
  "geometry": {"coordinates":[-16.55,15.33333],"type":"Point"}
}