{
  "type": "Feature",
  "properties": {
    "gn:admin1_code":"5.0",
    "gn:asciiname":"Talibadji",
    "gn:country_code":"SN",
    "gn:dem":67,
    "gn:feature_class":"P",
    "gn:feature_code":"PPL",
    "gn:name":"Talibadji",
    "gn:population":0,
    "gn:timezone":"Africa/Dakar",
    "iso:country":"SN",
    "wof:name":"Talibadji",
    "wof:placetype":"locality"
},
  "geometry": {"coordinates":[-12.62271,13.97243],"type":"Point"}
}