{
  "type": "Feature",
  "properties": {
    "gn:admin1_code":"12.0",
    "gn:asciiname":"Mossor",
    "gn:cc2":"SN",
    "gn:country_code":"SN",
    "gn:dem":1,
    "gn:feature_class":"P",
    "gn:feature_code":"PPL",
    "gn:name":"Mossor",
    "gn:population":0,
    "gn:timezone":"Africa/Dakar",
    "iso:country":"SN",
    "name:und_x_variant":[
        "Cabros",
        "Massor",
        "Mossor"
    ],
    "wof:name":"Mossor",
    "wof:placetype":"locality"
},
  "geometry": {"coordinates":[-16.73333,12.36667],"type":"Point"}
}