{
  "type": "Feature",
  "properties": {
    "gn:admin1_code":"13.0",
    "gn:asciiname":"Belene Boulbi",
    "gn:country_code":"SN",
    "gn:dem":41,
    "gn:feature_class":"P",
    "gn:feature_code":"PPL",
    "gn:name":"B\u00e9l\u00e8ne Boulbi",
    "gn:population":0,
    "gn:timezone":"Africa/Dakar",
    "iso:country":"SN",
    "name:und_x_variant":[
        "B\u00e9lenn Boulbi",
        "B\u00e9l\u00e8ne Boulbi"
    ],
    "wof:name":"Belene Boulbi",
    "wof:placetype":"locality"
},
  "geometry": {"coordinates":[-15.4285,15.734],"type":"Point"}
}