{
  "type": "Feature",
  "properties": {
    "gn:admin1_code":"5.0",
    "gn:asciiname":"Ouro Singa",
    "gn:country_code":"SN",
    "gn:dem":61,
    "gn:feature_class":"P",
    "gn:feature_code":"PPL",
    "gn:name":"Ouro Singa",
    "gn:population":0,
    "gn:timezone":"Africa/Dakar",
    "iso:country":"SN",
    "name:und_x_variant":[
        "Ouro Sinnga",
        "Ouro Singa"
    ],
    "wof:name":"Ouro Singa",
    "wof:placetype":"locality"
},
  "geometry": {"coordinates":[-12.98701,14.38075],"type":"Point"}
}