{
  "type": "Feature",
  "properties": {
    "gn:admin1_code":"5.0",
    "gn:asciiname":"Sintiou Idi",
    "gn:country_code":"SN",
    "gn:dem":60,
    "gn:feature_class":"P",
    "gn:feature_code":"PPL",
    "gn:name":"Sintiou Idi",
    "gn:population":0,
    "gn:timezone":"Africa/Dakar",
    "iso:country":"SN",
    "name:und_x_variant":[
        "Sinntiou Idi",
        "Sintiou Idi"
    ],
    "wof:name":"Sintiou Idi",
    "wof:placetype":"locality"
},
  "geometry": {"coordinates":[-12.80553,14.25489],"type":"Point"}
}