{
  "type": "Feature",
  "properties": {
    "gn:admin1_code":"3.0",
    "gn:asciiname":"Tiandiagne",
    "gn:cc2":"SN",
    "gn:country_code":"SN",
    "gn:dem":25,
    "gn:feature_class":"P",
    "gn:feature_code":"PPL",
    "gn:name":"Tiandiagne",
    "gn:population":0,
    "gn:timezone":"Africa/Dakar",
    "iso:country":"SN",
    "name:und_x_variant":[
        "Tiandiane",
        "Tiandiagne"
    ],
    "wof:name":"Tiandiagne",
    "wof:placetype":"locality"
},
  "geometry": {"coordinates":[-16.13332999999999,14.65],"type":"Point"}
}