{
  "type": "Feature",
  "properties": {
    "gn:admin1_code":"10.0",
    "gn:asciiname":"Keur Ndari",
    "gn:cc2":"SN",
    "gn:country_code":"SN",
    "gn:dem":39,
    "gn:feature_class":"P",
    "gn:feature_code":"PPL",
    "gn:name":"Keur Ndari",
    "gn:population":0,
    "gn:timezone":"Africa/Dakar",
    "iso:country":"SN",
    "name:und_x_variant":[
        "Keur N\u2019D\u00e9ri",
        "Keur Ndari"
    ],
    "wof:name":"Keur Ndari",
    "wof:placetype":"locality"
},
  "geometry": {"coordinates":[-16.08333,13.73333],"type":"Point"}
}