{
  "type": "Feature",
  "properties": {
    "gn:admin1_code":"13.0",
    "gn:asciiname":"Keur Ibrahima Mbaye",
    "gn:country_code":"SN",
    "gn:dem":46,
    "gn:feature_class":"P",
    "gn:feature_code":"PPL",
    "gn:name":"Keur Ibrah\u00efma Mbaye",
    "gn:population":0,
    "gn:timezone":"Africa/Dakar",
    "iso:country":"SN",
    "name:und_x_variant":[
        "Keur Ibra\u00efma Mbaye",
        "Keur Ibrah\u00efma Mbaye"
    ],
    "wof:name":"Keur Ibrahima Mbaye",
    "wof:placetype":"locality"
},
  "geometry": {"coordinates":[-15.9659,15.0042],"type":"Point"}
}