{
  "type": "Feature",
  "properties": {
    "gn:admin1_code":"7.0",
    "gn:asciiname":"Ndiobene",
    "gn:country_code":"SN",
    "gn:dem":67,
    "gn:feature_class":"P",
    "gn:feature_code":"PPL",
    "gn:name":"Ndiob\u00e8ne",
    "gn:population":0,
    "gn:timezone":"Africa/Dakar",
    "iso:country":"SN",
    "wof:name":"Ndiobene",
    "wof:placetype":"locality"
},
  "geometry": {"coordinates":[-16.88332999999999,14.86667],"type":"Point"}
}