{
  "type": "Feature",
  "properties": {
    "gn:admin1_code":"17.0",
    "gn:asciiname":"Gaegui",
    "gn:country_code":"SN",
    "gn:dem":173,
    "gn:feature_class":"P",
    "gn:feature_code":"PPL",
    "gn:name":"Ga\u00e9gui",
    "gn:population":0,
    "gn:timezone":"Africa/Dakar",
    "iso:country":"SN",
    "wof:name":"Gaegui",
    "wof:placetype":"locality"
},
  "geometry": {"coordinates":[-12.8381,12.6286],"type":"Point"}
}