{
  "type": "Feature",
  "properties": {
    "gn:admin1_code":"13.0",
    "gn:asciiname":"Keur Souleye",
    "gn:cc2":"SN",
    "gn:country_code":"SN",
    "gn:dem":42,
    "gn:feature_class":"P",
    "gn:feature_code":"PPL",
    "gn:name":"Keur Soul\u00e8ye",
    "gn:population":0,
    "gn:timezone":"Africa/Dakar",
    "iso:country":"SN",
    "name:und_x_variant":[
        "Keur Souleil",
        "Keur Soul\u00e8ye"
    ],
    "wof:name":"Keur Souleye",
    "wof:placetype":"locality"
},
  "geometry": {"coordinates":[-16.13332999999999,15.55],"type":"Point"}
}