{
  "type": "Feature",
  "properties": {
    "gn:admin1_code":"7.0",
    "gn:asciiname":"Tiokhmat",
    "gn:cc2":"SN",
    "gn:country_code":"SN",
    "gn:dem":12,
    "gn:feature_class":"P",
    "gn:feature_code":"PPL",
    "gn:name":"Tiokhmat",
    "gn:population":0,
    "gn:timezone":"Africa/Dakar",
    "iso:country":"SN",
    "name:und_x_variant":[
        "Tiormad",
        "Tiokhmat"
    ],
    "wof:name":"Tiokhmat",
    "wof:placetype":"locality"
},
  "geometry": {"coordinates":[-16.75,15.41667],"type":"Point"}
}