{
  "type": "Feature",
  "properties": {
    "gn:admin1_code":"13.0",
    "gn:asciiname":"Ndiabani",
    "gn:country_code":"SN",
    "gn:dem":53,
    "gn:feature_class":"P",
    "gn:feature_code":"PPL",
    "gn:name":"Ndiabani",
    "gn:population":0,
    "gn:timezone":"Africa/Dakar",
    "iso:country":"SN",
    "name:und_x_variant":[
        "Dabani",
        "Ndiabani"
    ],
    "wof:name":"Ndiabani",
    "wof:placetype":"locality"
},
  "geometry": {"coordinates":[-15.768,15.3263],"type":"Point"}
}