{
  "type": "Feature",
  "properties": {
    "gn:admin1_code":"5.0",
    "gn:asciiname":"Pada",
    "gn:country_code":"SN",
    "gn:dem":17,
    "gn:feature_class":"P",
    "gn:feature_code":"PPL",
    "gn:name":"Pada",
    "gn:population":0,
    "gn:timezone":"Africa/Dakar",
    "iso:country":"SN",
    "name:cat_x_preferred":[
        "Pada"
    ],
    "name:ceb_x_preferred":[
        "Pada"
    ],
    "name:nor_x_preferred":[
        "Pada"
    ],
    "name:swe_x_preferred":[
        "Pada"
    ],
    "wof:lang_x_official":[
        "wol",
        "fra"
    ],
    "wof:lang_x_spoken":[
        "wol",
        "fra"
    ],
    "wof:name":"Pada",
    "wof:placetype":"locality"
},
  "geometry": {"coordinates":[-13.85,13.81667],"type":"Point"}
}