{
  "type": "Feature",
  "properties": {
    "gn:admin1_code":"15.0",
    "gn:asciiname":"Louggue Tiekodie",
    "gn:country_code":"SN",
    "gn:dem":39,
    "gn:feature_class":"P",
    "gn:feature_code":"PPL",
    "gn:name":"Louggu\u00e9 Ti\u00e9kodi\u00e9",
    "gn:population":0,
    "gn:timezone":"Africa/Dakar",
    "iso:country":"SN",
    "name:und_x_variant":[
        "Lougu\u00e9 T\u00e9kodi\u00e9",
        "Lougu\u00e9 Ti\u00e9kodi\u00e9",
        "Louggu\u00e9 Ti\u00e9kodi\u00e9"
    ],
    "wof:lang_x_official":[
        "wol",
        "fra"
    ],
    "wof:lang_x_spoken":[
        "wol",
        "fra"
    ],
    "wof:name":"Louggue Tiekodie",
    "wof:placetype":"locality"
},
  "geometry": {"coordinates":[-13.98333,14.66667],"type":"Point"}
}