{
  "type": "Feature",
  "properties": {
    "gn:admin1_code":"7.0",
    "gn:asciiname":"Sindia Kafngoun",
    "gn:country_code":"SN",
    "gn:dem":17,
    "gn:feature_class":"P",
    "gn:feature_code":"PPL",
    "gn:name":"Sindia Kafngoun",
    "gn:population":0,
    "gn:timezone":"Africa/Dakar",
    "iso:country":"SN",
    "wof:name":"Sindia Kafngoun",
    "wof:placetype":"locality"
},
  "geometry": {"coordinates":[-17.03112999999999,14.56559],"type":"Point"}
}