{
  "type": "Feature",
  "properties": {
    "gn:admin1_code":"13.0",
    "gn:asciiname":"Leti Kobra",
    "gn:country_code":"SN",
    "gn:dem":42,
    "gn:feature_class":"P",
    "gn:feature_code":"PPL",
    "gn:name":"L\u00e9ti Kobra",
    "gn:population":0,
    "gn:timezone":"Africa/Dakar",
    "iso:country":"SN",
    "wof:name":"Leti Kobra",
    "wof:placetype":"locality"
},
  "geometry": {"coordinates":[-15.4414,15.376],"type":"Point"}
}