{
  "type": "Feature",
  "properties": {
    "gn:admin1_code":"16.0",
    "gn:asciiname":"Barone",
    "gn:country_code":"SN",
    "gn:dem":44,
    "gn:feature_class":"P",
    "gn:feature_code":"PPL",
    "gn:name":"Barone",
    "gn:population":0,
    "gn:timezone":"Africa/Dakar",
    "iso:country":"SN",
    "name:ceb_x_preferred":[
        "Barone"
    ],
    "name:deu_x_preferred":[
        "Barone"
    ],
    "name:fra_x_preferred":[
        "Barone"
    ],
    "name:ita_x_preferred":[
        "Barone"
    ],
    "name:rus_x_preferred":[
        "\u0411\u0430\u0440\u043e\u043d\u0435"
    ],
    "name:slv_x_preferred":[
        "Barone"
    ],
    "name:spa_x_preferred":[
        "Barone"
    ],
    "name:srp_x_preferred":[
        "Barone"
    ],
    "name:swe_x_preferred":[
        "Barone"
    ],
    "wof:name":"Barone",
    "wof:placetype":"locality"
},
  "geometry": {"coordinates":[-15.46667,14.05],"type":"Point"}
}