{
  "type": "Feature",
  "properties": {
    "gn:admin1_code":"14.0",
    "gn:asciiname":"Mbaye Mbaye",
    "gn:country_code":"SN",
    "gn:dem":24,
    "gn:feature_class":"P",
    "gn:feature_code":"PPL",
    "gn:name":"Mbaye Mbaye",
    "gn:population":0,
    "gn:timezone":"Africa/Dakar",
    "iso:country":"SN",
    "name:und_x_variant":[
        "Baye",
        "Mbaye Mbaye"
    ],
    "wof:lang_x_official":[
        "wol",
        "fra"
    ],
    "wof:lang_x_spoken":[
        "wol",
        "fra"
    ],
    "wof:name":"Mbaye Mbaye",
    "wof:placetype":"locality"
},
  "geometry": {"coordinates":[-16.8927,15.1312],"type":"Point"}
}