{
  "type": "Feature",
  "properties": {
    "gn:admin1_code":"14.0",
    "gn:asciiname":"Takhmbeut Peul",
    "gn:country_code":"SN",
    "gn:dem":12,
    "gn:feature_class":"P",
    "gn:feature_code":"PPL",
    "gn:name":"Takhmbeut Peul",
    "gn:population":0,
    "gn:timezone":"Africa/Dakar",
    "iso:country":"SN",
    "wof:name":"Takhmbeut Peul",
    "wof:placetype":"locality"
},
  "geometry": {"coordinates":[-16.27806,16.03],"type":"Point"}
}