{
  "type": "Feature",
  "properties": {
    "gn:admin1_code":"7.0",
    "gn:asciiname":"Keur Ibra Gueye",
    "gn:cc2":"SN",
    "gn:country_code":"SN",
    "gn:dem":24,
    "gn:feature_class":"P",
    "gn:feature_code":"PPL",
    "gn:name":"Keur Ibra Gueye",
    "gn:population":0,
    "gn:timezone":"Africa/Dakar",
    "iso:country":"SN",
    "name:und_x_variant":[
        "Keur Ibra Gaye",
        "Kibra-Gaye",
        "Keur Ibra Gueye"
    ],
    "wof:name":"Keur Ibra Gueye",
    "wof:placetype":"locality"
},
  "geometry": {"coordinates":[-16.73333,14.86667],"type":"Point"}
}