{
  "type": "Feature",
  "properties": {
    "gn:admin1_code":"10.0",
    "gn:asciiname":"Ngayene",
    "gn:country_code":"SN",
    "gn:dem":36,
    "gn:feature_class":"P",
    "gn:feature_code":"PPL",
    "gn:name":"Ngay\u00e8ne",
    "gn:population":0,
    "gn:timezone":"Africa/Dakar",
    "iso:country":"SN",
    "wof:name":"Ngayene",
    "wof:placetype":"locality"
},
  "geometry": {"coordinates":[-15.95,13.63333],"type":"Point"}
}