{
  "type": "Feature",
  "properties": {
    "gn:admin1_code":"5.0",
    "gn:asciiname":"Nianakounda",
    "gn:country_code":"SN",
    "gn:dem":54,
    "gn:feature_class":"P",
    "gn:feature_code":"PPL",
    "gn:name":"Nianakounda",
    "gn:population":0,
    "gn:timezone":"Africa/Dakar",
    "iso:country":"SN",
    "wof:name":"Nianakounda",
    "wof:placetype":"locality"
},
  "geometry": {"coordinates":[-13.65,13.66667],"type":"Point"}
}