{
  "type": "Feature",
  "properties": {
    "gn:admin1_code":"11.0",
    "gn:asciiname":"Kerevane",
    "gn:cc2":"SN",
    "gn:country_code":"SN",
    "gn:dem":38,
    "gn:feature_class":"P",
    "gn:feature_code":"PPL",
    "gn:name":"K\u00e9r\u00e9vane",
    "gn:population":0,
    "gn:timezone":"Africa/Dakar",
    "iso:country":"SN",
    "name:und_x_variant":[
        "K\u00e9r\u00e9van",
        "K\u00e9r\u00e9ouan\u00e9",
        "K\u00e9r\u00e9vane"
    ],
    "wof:name":"Kerevane",
    "wof:placetype":"locality"
},
  "geometry": {"coordinates":[-14.16667,13.11667],"type":"Point"}
}