{
  "type": "Feature",
  "properties": {
    "gn:admin1_code":"16.0",
    "gn:asciiname":"Keur Abdou Mbaye",
    "gn:country_code":"SN",
    "gn:dem":22,
    "gn:feature_class":"P",
    "gn:feature_code":"PPL",
    "gn:name":"Keur Abdou Mbaye",
    "gn:population":0,
    "gn:timezone":"Africa/Dakar",
    "iso:country":"SN",
    "wof:name":"Keur Abdou Mbaye",
    "wof:placetype":"locality"
},
  "geometry": {"coordinates":[-15.13333,13.85],"type":"Point"}
}