{
  "type": "Feature",
  "properties": {
    "gn:admin1_code":"14.0",
    "gn:asciiname":"Bowde Doudal",
    "gn:country_code":"SN",
    "gn:dem":28,
    "gn:feature_class":"P",
    "gn:feature_code":"PPL",
    "gn:name":"Bowd\u00e9 Doudal",
    "gn:population":0,
    "gn:timezone":"Africa/Dakar",
    "iso:country":"SN",
    "name:und_x_variant":[
        "Mbar Toubab",
        "Bowd\u00e9 Doudal"
    ],
    "wof:name":"Bowde Doudal",
    "wof:placetype":"locality"
},
  "geometry": {"coordinates":[-15.67861,16.00972],"type":"Point"}
}