{
  "type": "Feature",
  "properties": {
    "gn:admin1_code":"17.0",
    "gn:asciiname":"Bandemba",
    "gn:country_code":"SN",
    "gn:dem":356,
    "gn:feature_class":"P",
    "gn:feature_code":"PPL",
    "gn:name":"Band\u00e9mba",
    "gn:population":0,
    "gn:timezone":"Africa/Dakar",
    "iso:country":"SN",
    "name:und_x_variant":[
        "Bandanba",
        "Band\u00e9mba"
    ],
    "wof:name":"Bandemba",
    "wof:placetype":"locality"
},
  "geometry": {"coordinates":[-12.3804,12.525],"type":"Point"}
}