{
  "type": "Feature",
  "properties": {
    "gn:admin1_code":"13.0",
    "gn:asciiname":"Kelel Diop",
    "gn:country_code":"SN",
    "gn:dem":47,
    "gn:feature_class":"P",
    "gn:feature_code":"PPL",
    "gn:name":"K\u00e9lel Diop",
    "gn:population":0,
    "gn:timezone":"Africa/Dakar",
    "iso:country":"SN",
    "wof:name":"Kelel Diop",
    "wof:placetype":"locality"
},
  "geometry": {"coordinates":[-15.888,15.0122],"type":"Point"}
}