{
  "type": "Feature",
  "properties": {
    "gn:admin1_code":"17.0",
    "gn:asciiname":"Sillakounda Diakha",
    "gn:country_code":"SN",
    "gn:dem":110,
    "gn:feature_class":"P",
    "gn:feature_code":"PPL",
    "gn:name":"Sillakounda Diakha",
    "gn:population":0,
    "gn:timezone":"Africa/Dakar",
    "iso:country":"SN",
    "name:und_x_variant":[
        "Silacounda",
        "Silakounda",
        "Sillakounda Diakha"
    ],
    "wof:lang_x_official":[
        "wol",
        "fra"
    ],
    "wof:lang_x_spoken":[
        "wol",
        "fra"
    ],
    "wof:name":"Sillakounda Diakha",
    "wof:placetype":"locality"
},
  "geometry": {"coordinates":[-12.1235,12.6441],"type":"Point"}
}