{
  "type": "Feature",
  "properties": {
    "gn:admin1_code":"5.0",
    "gn:asciiname":"Ouro Baidi Dienaba",
    "gn:country_code":"SN",
    "gn:dem":50,
    "gn:feature_class":"P",
    "gn:feature_code":"PPL",
    "gn:name":"Ouro Ba\u00efdi Di\u00e9naba",
    "gn:population":0,
    "gn:timezone":"Africa/Dakar",
    "iso:country":"SN",
    "name:und_x_variant":[
        "Ouro Ba\u00e9di Di\u00e9naba",
        "Ouro Ba\u00efdi Di\u00e9naba"
    ],
    "wof:lang_x_official":[
        "wol",
        "fra"
    ],
    "wof:lang_x_spoken":[
        "wol",
        "fra"
    ],
    "wof:name":"Ouro Baidi Dienaba",
    "wof:placetype":"locality"
},
  "geometry": {"coordinates":[-12.73436,14.14359],"type":"Point"}
}