{
  "type": "Feature",
  "properties": {
    "gn:admin1_code":"5.0",
    "gn:asciiname":"Sitaoule Boure Kamara",
    "gn:country_code":"SN",
    "gn:dem":53,
    "gn:feature_class":"P",
    "gn:feature_code":"PPL",
    "gn:name":"Sitaoul\u00e9 Bour\u00e9 Kamara",
    "gn:population":0,
    "gn:timezone":"Africa/Dakar",
    "iso:country":"SN",
    "wof:name":"Sitaoule Boure Kamara",
    "wof:placetype":"locality"
},
  "geometry": {"coordinates":[-13.71667,13.63333],"type":"Point"}
}