{
  "type": "Feature",
  "properties": {
    "gn:admin1_code":"5.0",
    "gn:asciiname":"Niedebel",
    "gn:country_code":"SN",
    "gn:dem":53,
    "gn:feature_class":"P",
    "gn:feature_code":"PPL",
    "gn:name":"Ni\u00e9d\u00e9bel",
    "gn:population":0,
    "gn:timezone":"Africa/Dakar",
    "iso:country":"SN",
    "wof:name":"Niedebel",
    "wof:placetype":"locality"
},
  "geometry": {"coordinates":[-12.28274,14.53219],"type":"Point"}
}