{
  "type": "Feature",
  "properties": {
    "gn:admin1_code":"7.0",
    "gn:asciiname":"Khoubit",
    "gn:country_code":"SN",
    "gn:dem":44,
    "gn:feature_class":"P",
    "gn:feature_code":"PPL",
    "gn:name":"Khoubit",
    "gn:population":0,
    "gn:timezone":"Africa/Dakar",
    "iso:country":"SN",
    "name:und_x_variant":[
        "Ndiass Rhobite",
        "Ndias",
        "Khoubit"
    ],
    "wof:name":"Khoubit",
    "wof:placetype":"locality"
},
  "geometry": {"coordinates":[-17.09193,14.62947],"type":"Point"}
}