{
  "type": "Feature",
  "properties": {
    "gn:admin1_code":"16.0",
    "gn:asciiname":"Medina Sintiou Amat Maram",
    "gn:country_code":"SN",
    "gn:dem":43,
    "gn:feature_class":"P",
    "gn:feature_code":"PPL",
    "gn:name":"M\u00e9dina Sintiou Amat Maram",
    "gn:population":0,
    "gn:timezone":"Africa/Dakar",
    "iso:country":"SN",
    "wof:name":"Medina Sintiou Amat Maram",
    "wof:placetype":"locality"
},
  "geometry": {"coordinates":[-15.46667,13.81667],"type":"Point"}
}