{
  "type": "Feature",
  "properties": {
    "gn:country":"SN",
    "gn:fcode":"PPL",
    "gn:population":900,
    "iso:country":"SN",
    "name:und_x_variant":[
        "Baboucar Toumbou"
    ],
    "qs:name":"Keur Babakar Toumbou",
    "qs:photos_9r":0,
    "qs:photos_sr":0,
    "qs:pop_sr":"2",
    "wof:lang_x_official":[
        "wol",
        "fra"
    ],
    "wof:lang_x_spoken":[
        "wol",
        "fra"
    ],
    "wof:name":"Keur Babakar Toumbou",
    "wof:placetype":"locality",
    "wof:population":900
},
  "geometry": {"coordinates":[-16.719,14.10877],"type":"Point"}
}