{
  "type": "Feature",
  "properties": {
    "gn:admin1_code":"1.0",
    "gn:asciiname":"Tounde Ndargou",
    "gn:country_code":"SN",
    "gn:dem":21,
    "gn:feature_class":"P",
    "gn:feature_code":"PPLL",
    "gn:name":"Tounde Ndargou",
    "gn:population":0,
    "gn:timezone":"Africa/Dakar",
    "iso:country":"SN",
    "wof:name":"Tounde Ndargou",
    "wof:placetype":"locality"
},
  "geometry": {"coordinates":[-17.42517,14.75951],"type":"Point"}
}