{
  "type": "Feature",
  "properties": {
    "gn:admin1_code":"13.0",
    "gn:asciiname":"Keur Abdou Siri",
    "gn:country_code":"SN",
    "gn:dem":53,
    "gn:feature_class":"P",
    "gn:feature_code":"PPL",
    "gn:name":"Keur Abdou Siri",
    "gn:population":0,
    "gn:timezone":"Africa/Dakar",
    "iso:country":"SN",
    "wof:name":"Keur Abdou Siri",
    "wof:placetype":"locality"
},
  "geometry": {"coordinates":[-15.8535,15.0552],"type":"Point"}
}