{
  "type": "Feature",
  "properties": {
    "gn:admin1_code":"7.0",
    "gn:asciiname":"Keur Tiem Savare",
    "gn:country_code":"SN",
    "gn:dem":85,
    "gn:feature_class":"P",
    "gn:feature_code":"PPL",
    "gn:name":"Keur Tiem Savar\u00e9",
    "gn:population":0,
    "gn:timezone":"Africa/Dakar",
    "iso:country":"SN",
    "wof:name":"Keur Tiem Savare",
    "wof:placetype":"locality"
},
  "geometry": {"coordinates":[-16.93333,14.73333],"type":"Point"}
}