{
  "type": "Feature",
  "properties": {
    "gn:admin1_code":"7.0",
    "gn:asciiname":"Risso",
    "gn:country_code":"SN",
    "gn:dem":38,
    "gn:feature_class":"P",
    "gn:feature_code":"PPL",
    "gn:name":"Risso",
    "gn:population":0,
    "gn:timezone":"Africa/Dakar",
    "iso:country":"SN",
    "name:rus_x_preferred":[
        "\u0420\u0438\u0441\u0441\u043e"
    ],
    "wof:name":"Risso",
    "wof:placetype":"locality"
},
  "geometry": {"coordinates":[-16.63332999999999,15.08333],"type":"Point"}
}