{
  "type": "Feature",
  "properties": {
    "gn:admin1_code":"13.0",
    "gn:asciiname":"Keri Ibromane",
    "gn:cc2":"SN",
    "gn:country_code":"SN",
    "gn:dem":49,
    "gn:feature_class":"P",
    "gn:feature_code":"PPL",
    "gn:name":"K\u00e9ri Ibromane",
    "gn:population":0,
    "gn:timezone":"Africa/Dakar",
    "iso:country":"SN",
    "name:und_x_variant":[
        "Keur Ibra Mane",
        "K\u00e9ri Ibromane"
    ],
    "wof:name":"Keri Ibromane",
    "wof:placetype":"locality"
},
  "geometry": {"coordinates":[-16.13332999999999,15.21667],"type":"Point"}
}