{
  "type": "Feature",
  "properties": {
    "gn:admin1_code":"15.0",
    "gn:asciiname":"Alana",
    "gn:country_code":"SN",
    "gn:dem":49,
    "gn:feature_class":"P",
    "gn:feature_code":"PPL",
    "gn:name":"Alana",
    "gn:population":0,
    "gn:timezone":"Africa/Dakar",
    "iso:country":"SN",
    "wof:name":"Alana",
    "wof:placetype":"locality"
},
  "geometry": {"coordinates":[-12.61591,14.91747],"type":"Point"}
}