{
  "type": "Feature",
  "properties": {
    "gn:admin1_code":"15.0",
    "gn:asciiname":"Gasse Diabe",
    "gn:country_code":"SN",
    "gn:dem":26,
    "gn:feature_class":"P",
    "gn:feature_code":"PPL",
    "gn:name":"Gass\u00e9 Diab\u00e9",
    "gn:population":0,
    "gn:timezone":"Africa/Dakar",
    "iso:country":"SN",
    "wof:lang_x_official":[
        "wol",
        "fra"
    ],
    "wof:lang_x_spoken":[
        "wol",
        "fra"
    ],
    "wof:name":"Gasse Diabe",
    "wof:placetype":"locality"
},
  "geometry": {"coordinates":[-14.3548,15.2636],"type":"Point"}
}