{
  "type": "Feature",
  "properties": {
    "gn:admin1_code":"9.0",
    "gn:asciiname":"Bikol",
    "gn:cc2":"SN",
    "gn:country_code":"SN",
    "gn:dem":9,
    "gn:feature_class":"P",
    "gn:feature_code":"PPL",
    "gn:name":"Bikol",
    "gn:population":0,
    "gn:timezone":"Africa/Dakar",
    "iso:country":"SN",
    "name:und_x_variant":[
        "Bukol",
        "Bikol"
    ],
    "wof:name":"Bikol",
    "wof:placetype":"locality"
},
  "geometry": {"coordinates":[-16.45,14.41667],"type":"Point"}
}