{
  "type": "Feature",
  "properties": {
    "gn:admin1_code":"5.0",
    "gn:asciiname":"Eremokono",
    "gn:country_code":"SN",
    "gn:dem":90,
    "gn:feature_class":"P",
    "gn:feature_code":"PPL",
    "gn:name":"Er\u00e9mokono",
    "gn:population":0,
    "gn:timezone":"Africa/Dakar",
    "iso:country":"SN",
    "name:und_x_variant":[
        "H\u00e8r\u00e8makono",
        "Er\u00e9mokono"
    ],
    "wof:lang_x_official":[
        "wol",
        "fra"
    ],
    "wof:lang_x_spoken":[
        "wol",
        "fra"
    ],
    "wof:name":"Eremokono",
    "wof:placetype":"locality"
},
  "geometry": {"coordinates":[-12.0022,13.43294],"type":"Point"}
}