{
  "type": "Feature",
  "properties": {
    "gn:admin1_code":"5.0",
    "gn:asciiname":"Dindoudi Doka",
    "gn:country_code":"SN",
    "gn:dem":82,
    "gn:feature_class":"P",
    "gn:feature_code":"PPL",
    "gn:name":"Dindoudi Doka",
    "gn:population":0,
    "gn:timezone":"Africa/Dakar",
    "iso:country":"SN",
    "wof:name":"Dindoudi Doka",
    "wof:placetype":"locality"
},
  "geometry": {"coordinates":[-12.60769,14.27773],"type":"Point"}
}