{
  "type": "Feature",
  "properties": {
    "gn:admin1_code":"9.0",
    "gn:asciiname":"Mbelane",
    "gn:country_code":"SN",
    "gn:dem":7,
    "gn:feature_class":"P",
    "gn:feature_code":"PPL",
    "gn:name":"Mbelane",
    "gn:population":0,
    "gn:timezone":"Africa/Dakar",
    "iso:country":"SN",
    "wof:name":"Mbelane",
    "wof:placetype":"locality"
},
  "geometry": {"coordinates":[-16.45,14.05],"type":"Point"}
}