{
  "type": "Feature",
  "properties": {
    "gn:admin1_code":"14.0",
    "gn:asciiname":"Saninte",
    "gn:country_code":"SN",
    "gn:dem":21,
    "gn:feature_class":"P",
    "gn:feature_code":"PPL",
    "gn:name":"Saninte",
    "gn:population":0,
    "gn:timezone":"Africa/Dakar",
    "iso:country":"SN",
    "wof:name":"Saninte",
    "wof:placetype":"locality"
},
  "geometry": {"coordinates":[-15.70417,16.2025],"type":"Point"}
}