{
  "type": "Feature",
  "properties": {
    "gn:admin1_code":"7.0",
    "gn:asciiname":"Nguik Fal",
    "gn:country_code":"SN",
    "gn:dem":18,
    "gn:feature_class":"P",
    "gn:feature_code":"PPL",
    "gn:name":"Nguik Fal",
    "gn:population":0,
    "gn:timezone":"Africa/Dakar",
    "iso:country":"SN",
    "name:und_x_variant":[
        "Nguick",
        "Nquik",
        "Nguik",
        "Nguik Fal"
    ],
    "wof:name":"Nguik Fal",
    "wof:placetype":"locality"
},
  "geometry": {"coordinates":[-17.02132000000001,14.92967],"type":"Point"}
}