{
  "type": "Feature",
  "properties": {
    "gn:admin1_code":"14.0",
    "gn:asciiname":"Ndiaye Nguent",
    "gn:country_code":"SN",
    "gn:dem":6,
    "gn:feature_class":"P",
    "gn:feature_code":"PPL",
    "gn:name":"Ndiaye Ngu\u00e8nt",
    "gn:population":0,
    "gn:timezone":"Africa/Dakar",
    "iso:country":"SN",
    "wof:name":"Ndiaye Nguent",
    "wof:placetype":"locality"
},
  "geometry": {"coordinates":[-16.26472,16.19833],"type":"Point"}
}