{
  "type": "Feature",
  "properties": {
    "gn:admin1_code":"9.0",
    "gn:asciiname":"Badiane Nem",
    "gn:country_code":"SN",
    "gn:dem":27,
    "gn:feature_class":"P",
    "gn:feature_code":"PPL",
    "gn:name":"Badiane N\u00e8m",
    "gn:population":0,
    "gn:timezone":"Africa/Dakar",
    "iso:country":"SN",
    "wof:name":"Badiane Nem",
    "wof:placetype":"locality"
},
  "geometry": {"coordinates":[-15.75,14.61667],"type":"Point"}
}