{
  "type": "Feature",
  "properties": {
    "gn:admin1_code":"14.0",
    "gn:asciiname":"Bogguel",
    "gn:country_code":"SN",
    "gn:dem":27,
    "gn:feature_class":"P",
    "gn:feature_code":"PPL",
    "gn:name":"Bogguel",
    "gn:population":0,
    "gn:timezone":"Africa/Dakar",
    "iso:country":"SN",
    "name:und_x_variant":[
        "Boguel",
        "Bogguel"
    ],
    "wof:name":"Bogguel",
    "wof:placetype":"locality"
},
  "geometry": {"coordinates":[-13.84063,16.01487],"type":"Point"}
}