{
  "type": "Feature",
  "properties": {
    "gn:admin1_code":"14.0",
    "gn:asciiname":"Figo",
    "gn:country_code":"SN",
    "gn:dem":6,
    "gn:feature_class":"P",
    "gn:feature_code":"PPL",
    "gn:name":"Figo",
    "gn:population":0,
    "gn:timezone":"Africa/Dakar",
    "iso:country":"SN",
    "name:deu_x_preferred":[
        "Figo"
    ],
    "name:fas_x_preferred":[
        "\u0641\u06cc\u06af\u0648"
    ],
    "name:fra_x_preferred":[
        "Figo"
    ],
    "name:glg_x_preferred":[
        "Figo"
    ],
    "name:ita_x_preferred":[
        "Figo"
    ],
    "name:jpn_x_preferred":[
        "\u30d5\u30a3\u30fc\u30b4"
    ],
    "name:kor_x_preferred":[
        "\ud53c\uad6c"
    ],
    "name:nld_x_preferred":[
        "Figo"
    ],
    "name:pol_x_preferred":[
        "Figo"
    ],
    "wof:name":"Figo",
    "wof:placetype":"locality"
},
  "geometry": {"coordinates":[-15.01667,16.51667],"type":"Point"}
}