{
  "type": "Feature",
  "properties": {
    "gn:admin1_code":"11.0",
    "gn:asciiname":"Badion",
    "gn:country_code":"SN",
    "gn:dem":54,
    "gn:feature_class":"P",
    "gn:feature_code":"PPL",
    "gn:name":"Badion",
    "gn:population":0,
    "gn:timezone":"Africa/Dakar",
    "iso:country":"SN",
    "wof:name":"Badion",
    "wof:placetype":"locality"
},
  "geometry": {"coordinates":[-14.35,13.08333],"type":"Point"}
}