{
  "type": "Feature",
  "properties": {
    "gn:admin1_code":"15.0",
    "gn:asciiname":"Sintiou Mogo",
    "gn:country_code":"SN",
    "gn:dem":21,
    "gn:feature_class":"P",
    "gn:feature_code":"PPL",
    "gn:name":"Sintiou Mogo",
    "gn:population":0,
    "gn:timezone":"Africa/Dakar",
    "iso:country":"SN",
    "name:und_x_variant":[
        "Sinthiou-Mogo",
        "Sinntiou Mogo",
        "Sintiou Mogo"
    ],
    "wof:name":"Sintiou Mogo",
    "wof:placetype":"locality"
},
  "geometry": {"coordinates":[-13.3742,15.68609],"type":"Point"}
}