{
  "type": "Feature",
  "properties": {
    "gn:admin1_code":"7.0",
    "gn:asciiname":"Ndiorokh Mbot",
    "gn:country_code":"SN",
    "gn:dem":17,
    "gn:feature_class":"P",
    "gn:feature_code":"PPL",
    "gn:name":"Ndiorokh Mbot",
    "gn:population":0,
    "gn:timezone":"Africa/Dakar",
    "iso:country":"SN",
    "name:und_x_variant":[
        "Ndiorhorh",
        "Ndiorokh Mbot"
    ],
    "wof:lang_x_official":[
        "wol",
        "fra"
    ],
    "wof:lang_x_spoken":[
        "wol",
        "fra"
    ],
    "wof:name":"Ndiorokh Mbot",
    "wof:placetype":"locality"
},
  "geometry": {"coordinates":[-17.03047999999999,14.47133],"type":"Point"}
}