{
  "type": "Feature",
  "properties": {
    "gn:admin1_code":"7.0",
    "gn:asciiname":"Keur Sadarou Fam",
    "gn:cc2":"SN",
    "gn:country_code":"SN",
    "gn:dem":57,
    "gn:feature_class":"P",
    "gn:feature_code":"PPL",
    "gn:name":"Keur Sadarou Fam",
    "gn:population":0,
    "gn:timezone":"Africa/Dakar",
    "iso:country":"SN",
    "name:und_x_variant":[
        "Keur Sadaro",
        "Keur Sadarou Fam"
    ],
    "wof:name":"Keur Sadarou Fam",
    "wof:placetype":"locality"
},
  "geometry": {"coordinates":[-16.88332999999999,14.73333],"type":"Point"}
}