{
  "type": "Feature",
  "properties": {
    "gn:admin1_code":"14.0",
    "gn:asciiname":"Dieri Douga",
    "gn:country_code":"SN",
    "gn:dem":19,
    "gn:feature_class":"P",
    "gn:feature_code":"PPL",
    "gn:name":"Di\u00e9ri Douga",
    "gn:population":0,
    "gn:timezone":"Africa/Dakar",
    "iso:country":"SN",
    "wof:name":"Dieri Douga",
    "wof:placetype":"locality"
},
  "geometry": {"coordinates":[-14.42599,16.43187],"type":"Point"}
}