{
  "type": "Feature",
  "properties": {
    "gn:admin1_code":"1.0",
    "gn:asciiname":"Yene Kaw",
    "gn:country_code":"SN",
    "gn:dem":20,
    "gn:feature_class":"P",
    "gn:feature_code":"PPL",
    "gn:name":"Y\u00e8ne Kaw",
    "gn:population":0,
    "gn:timezone":"Africa/Dakar",
    "iso:country":"SN",
    "name:und_x_variant":[
        "Yen",
        "Yenne-sur-Mer",
        "Y\u00e8ne",
        "Y\u00e8ne Kaw"
    ],
    "wof:name":"Yene Kaw",
    "wof:placetype":"locality"
},
  "geometry": {"coordinates":[-17.15694,14.63332],"type":"Point"}
}