{
  "type": "Feature",
  "properties": {
    "gn:admin1_code":"12.0",
    "gn:asciiname":"Diarone",
    "gn:country_code":"SN",
    "gn:dem":20,
    "gn:feature_class":"P",
    "gn:feature_code":"PPL",
    "gn:name":"Diarone",
    "gn:population":0,
    "gn:timezone":"Africa/Dakar",
    "iso:country":"SN",
    "wof:name":"Diarone",
    "wof:placetype":"locality"
},
  "geometry": {"coordinates":[-16.17389,12.8275],"type":"Point"}
}