{
  "type": "Feature",
  "properties": {
    "gn:admin1_code":"3.0",
    "gn:asciiname":"Keur Ndiak",
    "gn:cc2":"SN",
    "gn:country_code":"SN",
    "gn:dem":40,
    "gn:feature_class":"P",
    "gn:feature_code":"PPL",
    "gn:name":"Keur Ndiak",
    "gn:population":0,
    "gn:timezone":"Africa/Dakar",
    "iso:country":"SN",
    "name:und_x_variant":[
        "Keur Diak",
        "Keur Ndiak"
    ],
    "wof:name":"Keur Ndiak",
    "wof:placetype":"locality"
},
  "geometry": {"coordinates":[-16.51667,14.86667],"type":"Point"}
}