{
  "type": "Feature",
  "properties": {
    "gn:admin1_code":"9.0",
    "gn:asciiname":"Diomegueul",
    "gn:country_code":"SN",
    "gn:dem":9,
    "gn:feature_class":"P",
    "gn:feature_code":"PPL",
    "gn:name":"Diomegueul",
    "gn:population":0,
    "gn:timezone":"Africa/Dakar",
    "iso:country":"SN",
    "wof:name":"Diomegueul",
    "wof:placetype":"locality"
},
  "geometry": {"coordinates":[-16.63332999999999,14.33333],"type":"Point"}
}