{
  "type": "Feature",
  "properties": {
    "gn:admin1_code":"13.0",
    "gn:asciiname":"Loumbel Djibi",
    "gn:country_code":"SN",
    "gn:dem":57,
    "gn:feature_class":"P",
    "gn:feature_code":"PPL",
    "gn:name":"Loumbel Djibi",
    "gn:population":0,
    "gn:timezone":"Africa/Dakar",
    "iso:country":"SN",
    "wof:name":"Loumbel Djibi",
    "wof:placetype":"locality"
},
  "geometry": {"coordinates":[-14.6567,15.8435],"type":"Point"}
}