{
  "type": "Feature",
  "properties": {
    "gn:admin1_code":"17.0",
    "gn:asciiname":"Lougueniani",
    "gn:country_code":"SN",
    "gn:dem":103,
    "gn:feature_class":"P",
    "gn:feature_code":"PPL",
    "gn:name":"Lougu\u00e9niani",
    "gn:population":0,
    "gn:timezone":"Africa/Dakar",
    "iso:country":"SN",
    "wof:name":"Lougueniani",
    "wof:placetype":"locality"
},
  "geometry": {"coordinates":[-12.5572,12.4604],"type":"Point"}
}