{
  "type": "Feature",
  "properties": {
    "gn:admin1_code":"5.0",
    "gn:asciiname":"Dougue",
    "gn:country_code":"SN",
    "gn:dem":56,
    "gn:feature_class":"P",
    "gn:feature_code":"PPL",
    "gn:name":"Dougu\u00e9",
    "gn:population":0,
    "gn:timezone":"Africa/Dakar",
    "iso:country":"SN",
    "wof:name":"Dougue",
    "wof:placetype":"locality"
},
  "geometry": {"coordinates":[-12.66835,13.98794],"type":"Point"}
}