{
  "type": "Feature",
  "properties": {
    "gn:admin1_code":"7.0",
    "gn:asciiname":"Tok Lou Serer",
    "gn:country_code":"SN",
    "gn:dem":42,
    "gn:feature_class":"P",
    "gn:feature_code":"PPL",
    "gn:name":"Tok Lou S\u00e9r\u00e8r",
    "gn:population":0,
    "gn:timezone":"Africa/Dakar",
    "iso:country":"SN",
    "name:und_x_variant":[
        "Toglou",
        "Tok Lou S\u00e9r\u00e8re",
        "Tok Lou S\u00e9r\u00e8r",
        "Tok Lou"
    ],
    "wof:name":"Tok Lou Serer",
    "wof:placetype":"locality"
},
  "geometry": {"coordinates":[-17.12164,14.69927],"type":"Point"}
}