{
  "type": "Feature",
  "properties": {
    "gn:admin1_code":"18.0",
    "gn:asciiname":"Niakounda",
    "gn:country_code":"SN",
    "gn:dem":5,
    "gn:feature_class":"P",
    "gn:feature_code":"PPL",
    "gn:name":"Niakounda",
    "gn:population":0,
    "gn:timezone":"Africa/Dakar",
    "iso:country":"SN",
    "wof:name":"Niakounda",
    "wof:placetype":"locality"
},
  "geometry": {"coordinates":[-15.61667,12.53333],"type":"Point"}
}