{
  "type": "Feature",
  "properties": {
    "gn:admin1_code":"14.0",
    "gn:asciiname":"Touba Guene",
    "gn:cc2":"SN",
    "gn:country_code":"SN",
    "gn:dem":16,
    "gn:feature_class":"P",
    "gn:feature_code":"PPL",
    "gn:name":"Touba Gu\u00e8ne",
    "gn:population":0,
    "gn:timezone":"Africa/Dakar",
    "iso:country":"SN",
    "name:und_x_variant":[
        "Touba Gueye",
        "Touba",
        "Touba Gu\u00e8ne"
    ],
    "wof:name":"Touba Guene",
    "wof:placetype":"locality"
},
  "geometry": {"coordinates":[-16.39417000000001,15.86389],"type":"Point"}
}