{
  "type": "Feature",
  "properties": {
    "gn:admin1_code":"15.0",
    "gn:asciiname":"Tiankone Modi Maka",
    "gn:country_code":"SN",
    "gn:dem":37,
    "gn:feature_class":"P",
    "gn:feature_code":"PPL",
    "gn:name":"Tiankone Modi Maka",
    "gn:population":0,
    "gn:timezone":"Africa/Dakar",
    "iso:country":"SN",
    "wof:name":"Tiankone Modi Maka",
    "wof:placetype":"locality"
},
  "geometry": {"coordinates":[-13.38727,15.58493],"type":"Point"}
}