{
  "type": "Feature",
  "properties": {
    "gn:admin1_code":"7.0",
    "gn:asciiname":"Dingler",
    "gn:cc2":"SN",
    "gn:country_code":"SN",
    "gn:dem":20,
    "gn:feature_class":"P",
    "gn:feature_code":"PPL",
    "gn:name":"Dingler",
    "gn:population":0,
    "gn:timezone":"Africa/Dakar",
    "iso:country":"SN",
    "name:deu_x_preferred":[
        "Dingler"
    ],
    "name:fra_x_preferred":[
        "Dingler"
    ],
    "name:und_x_variant":[
        "Dingu\u00e9l\u00e8re",
        "Dingler"
    ],
    "wof:name":"Dingler",
    "wof:placetype":"locality"
},
  "geometry": {"coordinates":[-16.66667,14.73333],"type":"Point"}
}