{
  "type": "Feature",
  "properties": {
    "gn:admin1_code":"15.0",
    "gn:asciiname":"Sare Take",
    "gn:country_code":"SN",
    "gn:dem":30,
    "gn:feature_class":"P",
    "gn:feature_code":"PPL",
    "gn:name":"Sar\u00e9 Tak\u00e9",
    "gn:population":0,
    "gn:timezone":"Africa/Dakar",
    "iso:country":"SN",
    "wof:name":"Sare Take",
    "wof:placetype":"locality"
},
  "geometry": {"coordinates":[-14.0756,15.2763],"type":"Point"}
}