{
  "type": "Feature",
  "properties": {
    "gn:admin1_code":"9.0",
    "gn:asciiname":"Diofandor",
    "gn:country_code":"SN",
    "gn:dem":5,
    "gn:feature_class":"P",
    "gn:feature_code":"PPL",
    "gn:name":"Diofandor",
    "gn:population":0,
    "gn:timezone":"Africa/Dakar",
    "iso:country":"SN",
    "wof:name":"Diofandor",
    "wof:placetype":"locality"
},
  "geometry": {"coordinates":[-16.61667000000001,13.81667],"type":"Point"}
}