{
  "type": "Feature",
  "properties": {
    "gn:admin1_code":"5.0",
    "gn:asciiname":"Diokdou",
    "gn:country_code":"SN",
    "gn:dem":82,
    "gn:feature_class":"P",
    "gn:feature_code":"PPL",
    "gn:name":"Diokdou",
    "gn:population":0,
    "gn:timezone":"Africa/Dakar",
    "iso:country":"SN",
    "wof:name":"Diokdou",
    "wof:placetype":"locality"
},
  "geometry": {"coordinates":[-12.53337,14.68411],"type":"Point"}
}