{
  "type": "Feature",
  "properties": {
    "gn:admin1_code":"15.0",
    "gn:asciiname":"Mbelone",
    "gn:country_code":"SN",
    "gn:dem":64,
    "gn:feature_class":"P",
    "gn:feature_code":"PPL",
    "gn:name":"Mb\u00e9lone",
    "gn:population":0,
    "gn:timezone":"Africa/Dakar",
    "iso:country":"SN",
    "wof:name":"Mbelone",
    "wof:placetype":"locality"
},
  "geometry": {"coordinates":[-13.4508,15.54877],"type":"Point"}
}