{
  "type": "Feature",
  "properties": {
    "gn:admin1_code":"17.0",
    "gn:asciiname":"Dinkokono",
    "gn:country_code":"SN",
    "gn:dem":152,
    "gn:feature_class":"P",
    "gn:feature_code":"PPL",
    "gn:name":"Dinkokono",
    "gn:population":0,
    "gn:timezone":"Africa/Dakar",
    "iso:country":"SN",
    "wof:name":"Dinkokono",
    "wof:placetype":"locality"
},
  "geometry": {"coordinates":[-11.46877,12.79665],"type":"Point"}
}