{
  "type": "Feature",
  "properties": {
    "gn:admin1_code":"7.0",
    "gn:asciiname":"Mbirdiam",
    "gn:country_code":"SN",
    "gn:dem":51,
    "gn:feature_class":"P",
    "gn:feature_code":"PPL",
    "gn:name":"Mbirdiam",
    "gn:population":0,
    "gn:timezone":"Africa/Dakar",
    "iso:country":"SN",
    "name:und_x_variant":[
        "B\u00e9ridiam",
        "Mbirdiamm",
        "Mbirdiam"
    ],
    "wof:name":"Mbirdiam",
    "wof:placetype":"locality"
},
  "geometry": {"coordinates":[-17.10806,14.76297],"type":"Point"}
}