{
  "type": "Feature",
  "properties": {
    "gn:admin1_code":"14.0",
    "gn:asciiname":"Loumbal",
    "gn:country_code":"SN",
    "gn:dem":38,
    "gn:feature_class":"P",
    "gn:feature_code":"PPL",
    "gn:name":"Loumbal",
    "gn:population":0,
    "gn:timezone":"Africa/Dakar",
    "iso:country":"SN",
    "name:und_x_variant":[
        "Loumbol",
        "Loumbal"
    ],
    "wof:name":"Loumbal",
    "wof:placetype":"locality"
},
  "geometry": {"coordinates":[-13.82615,16.01009],"type":"Point"}
}