{
  "type": "Feature",
  "properties": {
    "gn:admin1_code":"18.0",
    "gn:asciiname":"Boudhie Samine",
    "gn:country_code":"SN",
    "gn:dem":16,
    "gn:feature_class":"P",
    "gn:feature_code":"PPL",
    "gn:name":"Boudhi\u00e9 Samine",
    "gn:population":0,
    "gn:timezone":"Africa/Dakar",
    "iso:country":"SN",
    "wof:name":"Boudhie Samine",
    "wof:placetype":"locality"
},
  "geometry": {"coordinates":[-15.69028,12.65389],"type":"Point"}
}