{
  "type": "Feature",
  "properties": {
    "gn:admin1_code":"18.0",
    "gn:asciiname":"Anpountoum",
    "gn:country_code":"SN",
    "gn:dem":18,
    "gn:feature_class":"P",
    "gn:feature_code":"PPL",
    "gn:name":"Anpountoum",
    "gn:population":0,
    "gn:timezone":"Africa/Dakar",
    "iso:country":"SN",
    "wof:name":"Anpountoum",
    "wof:placetype":"locality"
},
  "geometry": {"coordinates":[-15.805,12.92583],"type":"Point"}
}