{
  "type": "Feature",
  "properties": {
    "gn:admin1_code":"12.0",
    "gn:asciiname":"Tilel",
    "gn:cc2":"SN",
    "gn:country_code":"SN",
    "gn:dem":23,
    "gn:feature_class":"P",
    "gn:feature_code":"PPL",
    "gn:name":"Tilel",
    "gn:population":0,
    "gn:timezone":"Africa/Dakar",
    "iso:country":"SN",
    "name:und_x_variant":[
        "Tid\u00e8le",
        "Tilel"
    ],
    "wof:name":"Tilel",
    "wof:placetype":"locality"
},
  "geometry": {"coordinates":[-16.26667,12.56667],"type":"Point"}
}