{
  "type": "Feature",
  "properties": {
    "gn:admin1_code":"10.0",
    "gn:asciiname":"Mbelbouk",
    "gn:cc2":"SN",
    "gn:country_code":"SN",
    "gn:dem":19,
    "gn:feature_class":"P",
    "gn:feature_code":"PPL",
    "gn:name":"Mbelbouk",
    "gn:population":0,
    "gn:timezone":"Africa/Dakar",
    "iso:country":"SN",
    "name:und_x_variant":[
        "Belbouk",
        "Mbelbouk"
    ],
    "wof:name":"Mbelbouk",
    "wof:placetype":"locality"
},
  "geometry": {"coordinates":[-16.25,14.26667],"type":"Point"}
}