{
  "type": "Feature",
  "properties": {
    "gn:admin1_code":"5.0",
    "gn:asciiname":"Gourel Tiama",
    "gn:country_code":"SN",
    "gn:dem":72,
    "gn:feature_class":"P",
    "gn:feature_code":"PPL",
    "gn:name":"Gourel Tiama",
    "gn:population":0,
    "gn:timezone":"Africa/Dakar",
    "iso:country":"SN",
    "wof:lang_x_official":[
        "wol",
        "fra"
    ],
    "wof:lang_x_spoken":[
        "wol",
        "fra"
    ],
    "wof:name":"Gourel Tiama",
    "wof:placetype":"locality"
},
  "geometry": {"coordinates":[-12.73879,14.53486],"type":"Point"}
}