{
  "type": "Feature",
  "properties": {
    "gn:admin1_code":"11.0",
    "gn:asciiname":"Moulessi",
    "gn:cc2":"SN",
    "gn:country_code":"SN",
    "gn:dem":32,
    "gn:feature_class":"P",
    "gn:feature_code":"PPL",
    "gn:name":"Moulessi",
    "gn:population":0,
    "gn:timezone":"Africa/Dakar",
    "iso:country":"SN",
    "name:und_x_variant":[
        "Sabi",
        "Moul\u00e8s-Essy",
        "Moulessi"
    ],
    "wof:name":"Moulessi",
    "wof:placetype":"locality"
},
  "geometry": {"coordinates":[-13.65,13.58333],"type":"Point"}
}