{
  "type": "Feature",
  "properties": {
    "gn:admin1_code":"13.0",
    "gn:asciiname":"Tillem",
    "gn:cc2":"SN",
    "gn:country_code":"SN",
    "gn:dem":39,
    "gn:feature_class":"P",
    "gn:feature_code":"PPL",
    "gn:name":"Till\u00e8m",
    "gn:population":0,
    "gn:timezone":"Africa/Dakar",
    "iso:country":"SN",
    "name:und_x_variant":[
        "Thill\u00e8ne",
        "Till\u00e8m"
    ],
    "wof:name":"Tillem",
    "wof:placetype":"locality"
},
  "geometry": {"coordinates":[-16.21667,15.66667],"type":"Point"}
}