{
  "type": "Feature",
  "properties": {
    "gn:admin1_code":"18.0",
    "gn:asciiname":"Hamdalaye",
    "gn:country_code":"SN",
    "gn:dem":10,
    "gn:feature_class":"P",
    "gn:feature_code":"PPL",
    "gn:name":"Hamdalaye",
    "gn:population":0,
    "gn:timezone":"Africa/Dakar",
    "iso:country":"SN",
    "name:und_x_variant":[
        "Hamdalaye Num\u00e9ro 1",
        "Hamdalaye"
    ],
    "wof:name":"Hamdalaye",
    "wof:placetype":"locality"
},
  "geometry": {"coordinates":[-15.67333,12.54722],"type":"Point"}
}