{
  "type": "Feature",
  "properties": {
    "gn:admin1_code":"12.0",
    "gn:asciiname":"Kounatouba",
    "gn:country_code":"SN",
    "gn:dem":29,
    "gn:feature_class":"P",
    "gn:feature_code":"PPL",
    "gn:name":"Kounatouba",
    "gn:population":0,
    "gn:timezone":"Africa/Dakar",
    "iso:country":"SN",
    "wof:name":"Kounatouba",
    "wof:placetype":"locality"
},
  "geometry": {"coordinates":[-16.26139,12.95861],"type":"Point"}
}