{
  "type": "Feature",
  "properties": {
    "gn:admin1_code":"18.0",
    "gn:asciiname":"Batan Gnima",
    "gn:country_code":"SN",
    "gn:dem":4,
    "gn:feature_class":"P",
    "gn:feature_code":"PPL",
    "gn:name":"Batan Gnima",
    "gn:population":0,
    "gn:timezone":"Africa/Dakar",
    "iso:country":"SN",
    "wof:name":"Batan Gnima",
    "wof:placetype":"locality"
},
  "geometry": {"coordinates":[-15.84778,12.70667],"type":"Point"}
}