{
  "type": "Feature",
  "properties": {
    "gn:admin1_code":"7.0",
    "gn:asciiname":"Sali Niakhniakhal",
    "gn:country_code":"SN",
    "gn:dem":8,
    "gn:feature_class":"P",
    "gn:feature_code":"PPL",
    "gn:name":"Sali Niakhniakhal",
    "gn:population":0,
    "gn:timezone":"Africa/Dakar",
    "iso:country":"SN",
    "name:und_x_variant":[
        "Sali Nianiaral",
        "Sali Niagnaral",
        "Sali Niakhniakhal"
    ],
    "wof:lang_x_official":[
        "wol",
        "fra"
    ],
    "wof:lang_x_spoken":[
        "wol",
        "fra"
    ],
    "wof:name":"Sali Niakhniakhal",
    "wof:placetype":"locality"
},
  "geometry": {"coordinates":[-17.00062999999999,14.43498],"type":"Point"}
}