{
  "type": "Feature",
  "properties": {
    "gn:admin1_code":"13.0",
    "gn:asciiname":"Touba Merina",
    "gn:country_code":"SN",
    "gn:dem":52,
    "gn:feature_class":"P",
    "gn:feature_code":"PPL",
    "gn:name":"Touba M\u00e9rina",
    "gn:population":0,
    "gn:timezone":"Africa/Dakar",
    "iso:country":"SN",
    "wof:name":"Touba Merina",
    "wof:placetype":"locality"
},
  "geometry": {"coordinates":[-16.014,15.2524],"type":"Point"}
}