{
  "type": "Feature",
  "properties": {
    "gn:admin1_code":"14.0",
    "gn:asciiname":"Tielao",
    "gn:country_code":"SN",
    "gn:dem":13,
    "gn:feature_class":"P",
    "gn:feature_code":"PPL",
    "gn:name":"Ti\u00e9lao",
    "gn:population":0,
    "gn:timezone":"Africa/Dakar",
    "iso:country":"SN",
    "name:und_x_variant":[
        "Thi\u00e9lao",
        "Ti\u00e9lao"
    ],
    "wof:name":"Tielao",
    "wof:placetype":"locality"
},
  "geometry": {"coordinates":[-14.56026,16.57688],"type":"Point"}
}