{
  "type": "Feature",
  "properties": {
    "gn:admin1_code":"13.0",
    "gn:asciiname":"Diama",
    "gn:cc2":"SN",
    "gn:country_code":"SN",
    "gn:dem":30,
    "gn:feature_class":"P",
    "gn:feature_code":"PPL",
    "gn:name":"Diama",
    "gn:population":0,
    "gn:timezone":"Africa/Dakar",
    "iso:country":"SN",
    "name:und_x_variant":[
        "Diamagu\u00e8ne",
        "Diama Gui\u00e8ne",
        "Diama"
    ],
    "wof:lang_x_official":[
        "wol",
        "fra"
    ],
    "wof:lang_x_spoken":[
        "wol",
        "fra"
    ],
    "wof:name":"Diama",
    "wof:placetype":"locality"
},
  "geometry": {"coordinates":[-16.35556,15.78917],"type":"Point"}
}