{
  "type": "Feature",
  "properties": {
    "gn:admin1_code":"13.0",
    "gn:asciiname":"Keur Braham Fall",
    "gn:country_code":"SN",
    "gn:dem":43,
    "gn:feature_class":"P",
    "gn:feature_code":"PPL",
    "gn:name":"Keur Braham Fall",
    "gn:population":0,
    "gn:timezone":"Africa/Dakar",
    "iso:country":"SN",
    "name:und_x_variant":[
        "Keur Brahame Fal",
        "Keur Braham Fall"
    ],
    "wof:name":"Keur Braham Fall",
    "wof:placetype":"locality"
},
  "geometry": {"coordinates":[-15.9697,15.6298],"type":"Point"}
}