{
  "type": "Feature",
  "properties": {
    "gn:admin1_code":"5.0",
    "gn:asciiname":"Oumbare",
    "gn:country_code":"SN",
    "gn:dem":117,
    "gn:feature_class":"P",
    "gn:feature_code":"PPL",
    "gn:name":"Oumbar\u00e9",
    "gn:population":0,
    "gn:timezone":"Africa/Dakar",
    "iso:country":"SN",
    "wof:name":"Oumbare",
    "wof:placetype":"locality"
},
  "geometry": {"coordinates":[-12.41026,13.71946],"type":"Point"}
}