{
  "type": "Feature",
  "properties": {
    "gn:admin1_code":"13.0",
    "gn:asciiname":"Nayde",
    "gn:country_code":"SN",
    "gn:dem":39,
    "gn:feature_class":"P",
    "gn:feature_code":"PPL",
    "gn:name":"Nayd\u00e9",
    "gn:population":0,
    "gn:timezone":"Africa/Dakar",
    "iso:country":"SN",
    "wof:name":"Nayde",
    "wof:placetype":"locality"
},
  "geometry": {"coordinates":[-15.9413,15.7287],"type":"Point"}
}