{
  "type": "Feature",
  "properties": {
    "gn:admin1_code":"7.0",
    "gn:asciiname":"Ber Tialane",
    "gn:country_code":"SN",
    "gn:dem":16,
    "gn:feature_class":"P",
    "gn:feature_code":"PPL",
    "gn:name":"B\u00e9r Tialane",
    "gn:population":0,
    "gn:timezone":"Africa/Dakar",
    "iso:country":"SN",
    "name:und_x_variant":[
        "Berr Tialane",
        "Berr Kalane",
        "B\u00e9r Tialane"
    ],
    "wof:name":"Ber Tialane",
    "wof:placetype":"locality"
},
  "geometry": {"coordinates":[-17.13907,14.85863],"type":"Point"}
}