{
  "type": "Feature",
  "properties": {
    "gn:admin1_code":"13.0",
    "gn:asciiname":"Keur Mbarik",
    "gn:cc2":"SN",
    "gn:country_code":"SN",
    "gn:dem":37,
    "gn:feature_class":"P",
    "gn:feature_code":"PPL",
    "gn:name":"Keur Mbarik",
    "gn:population":0,
    "gn:timezone":"Africa/Dakar",
    "iso:country":"SN",
    "name:und_x_variant":[
        "Keur MBarick",
        "Keur Mbarik"
    ],
    "wof:lang_x_official":[
        "wol",
        "fra"
    ],
    "wof:lang_x_spoken":[
        "wol",
        "fra"
    ],
    "wof:name":"Keur Mbarik",
    "wof:placetype":"locality"
},
  "geometry": {"coordinates":[-16.28333,15.65],"type":"Point"}
}