{
  "type": "Feature",
  "properties": {
    "gn:admin1_code":"14.0",
    "gn:asciiname":"Mbaye Mbaye",
    "gn:cc2":"SN",
    "gn:country_code":"SN",
    "gn:dem":17,
    "gn:feature_class":"P",
    "gn:feature_code":"PPL",
    "gn:name":"Mbaye Mbaye",
    "gn:population":0,
    "gn:timezone":"Africa/Dakar",
    "iso:country":"SN",
    "name:und_x_variant":[
        "Mbaye Baye Sar",
        "Mbaye Mbaye"
    ],
    "wof:name":"Mbaye Mbaye",
    "wof:placetype":"locality"
},
  "geometry": {"coordinates":[-16.28833,15.89889],"type":"Point"}
}