{
  "type": "Feature",
  "properties": {
    "gn:admin1_code":"7.0",
    "gn:asciiname":"Ngop",
    "gn:cc2":"SN",
    "gn:country_code":"SN",
    "gn:dem":35,
    "gn:feature_class":"P",
    "gn:feature_code":"PPL",
    "gn:name":"Ngop",
    "gn:population":0,
    "gn:timezone":"Africa/Dakar",
    "iso:country":"SN",
    "name:und_x_variant":[
        "N\u2019Gopp\u00e9",
        "Ngop"
    ],
    "wof:name":"Ngop",
    "wof:placetype":"locality"
},
  "geometry": {"coordinates":[-16.35,15.15],"type":"Point"}
}