{
  "type": "Feature",
  "properties": {
    "gn:admin1_code":"13.0",
    "gn:asciiname":"Ouassoumassal",
    "gn:cc2":"SN",
    "gn:country_code":"SN",
    "gn:dem":32,
    "gn:feature_class":"P",
    "gn:feature_code":"PPL",
    "gn:name":"Ouassoumassal",
    "gn:population":0,
    "gn:timezone":"Africa/Dakar",
    "iso:country":"SN",
    "name:und_x_variant":[
        "Quassoumassal",
        "Oua Sommassal",
        "Ouassoumassal"
    ],
    "wof:name":"Ouassoumassal",
    "wof:placetype":"locality"
},
  "geometry": {"coordinates":[-16.58333,15.68333],"type":"Point"}
}