{
  "type": "Feature",
  "properties": {
    "gn:admin1_code":"13.0",
    "gn:asciiname":"Velingara",
    "gn:country_code":"SN",
    "gn:dem":39,
    "gn:feature_class":"P",
    "gn:feature_code":"PPL",
    "gn:name":"V\u00e9lingara",
    "gn:population":0,
    "gn:timezone":"Africa/Dakar",
    "iso:country":"SN",
    "name:und_x_variant":[
        "Ouilingara",
        "V\u00e9linngara",
        "V\u00e9lingara"
    ],
    "wof:name":"Velingara",
    "wof:placetype":"locality"
},
  "geometry": {"coordinates":[-16.2585,15.5839],"type":"Point"}
}