{
  "type": "Feature",
  "properties": {
    "gn:admin1_code":"11.0",
    "gn:asciiname":"Sintiou Bamba",
    "gn:cc2":"SN",
    "gn:country_code":"SN",
    "gn:dem":44,
    "gn:feature_class":"P",
    "gn:feature_code":"PPL",
    "gn:name":"Sintiou Bamba",
    "gn:population":0,
    "gn:timezone":"Africa/Dakar",
    "iso:country":"SN",
    "name:und_x_variant":[
        "Sinntiou Bamba",
        "Sinthiou Bamba",
        "Sintiou Bamba"
    ],
    "wof:name":"Sintiou Bamba",
    "wof:placetype":"locality"
},
  "geometry": {"coordinates":[-15.15,13.11667],"type":"Point"}
}