{
  "type": "Feature",
  "properties": {
    "gn:admin1_code":"5.0",
    "gn:asciiname":"Niakabana",
    "gn:country_code":"SN",
    "gn:dem":86,
    "gn:feature_class":"P",
    "gn:feature_code":"PPL",
    "gn:name":"Niakabana",
    "gn:population":0,
    "gn:timezone":"Africa/Dakar",
    "iso:country":"SN",
    "wof:name":"Niakabana",
    "wof:placetype":"locality"
},
  "geometry": {"coordinates":[-11.67522,13.38438],"type":"Point"}
}