{
  "type": "Feature",
  "properties": {
    "gn:admin1_code":"13.0",
    "gn:asciiname":"Boulal",
    "gn:country_code":"SN",
    "gn:dem":53,
    "gn:feature_class":"P",
    "gn:feature_code":"PPL",
    "gn:name":"Boulal",
    "gn:population":0,
    "gn:timezone":"Africa/Dakar",
    "iso:country":"SN",
    "name:und_x_variant":[
        "Boulel",
        "Boulal"
    ],
    "wof:name":"Boulal",
    "wof:placetype":"locality"
},
  "geometry": {"coordinates":[-15.6619,15.3978],"type":"Point"}
}