{
  "type": "Feature",
  "properties": {
    "gn:admin1_code":"1.0",
    "gn:asciiname":"Mbeut",
    "gn:country_code":"SN",
    "gn:dem":46,
    "gn:feature_class":"P",
    "gn:feature_code":"PPL",
    "gn:name":"Mbeut",
    "gn:population":0,
    "gn:timezone":"Africa/Dakar",
    "iso:country":"SN",
    "name:und_x_variant":[
        "Mbeut Ndangu\u00e8ne",
        "Mbout",
        "Mbeute",
        "Mbeut"
    ],
    "wof:name":"Mbeut",
    "wof:placetype":"locality"
},
  "geometry": {"coordinates":[-17.16628,14.78938],"type":"Point"}
}