{
  "type": "Feature",
  "properties": {
    "gn:admin1_code":"13.0",
    "gn:asciiname":"Loumbol",
    "gn:cc2":"SN",
    "gn:country_code":"SN",
    "gn:dem":25,
    "gn:feature_class":"P",
    "gn:feature_code":"PPL",
    "gn:name":"Loumbol",
    "gn:population":0,
    "gn:timezone":"Africa/Dakar",
    "iso:country":"SN",
    "name:und_x_variant":[
        "Loumboul D\u00e2di",
        "Loumbol"
    ],
    "wof:name":"Loumbol",
    "wof:placetype":"locality"
},
  "geometry": {"coordinates":[-16.01667,15.88333],"type":"Point"}
}