{
  "type": "Feature",
  "properties": {
    "gn:admin1_code":"11.0",
    "gn:asciiname":"Lenguedie",
    "gn:cc2":"SN",
    "gn:country_code":"SN",
    "gn:dem":56,
    "gn:feature_class":"P",
    "gn:feature_code":"PPL",
    "gn:name":"Lengu\u00e9di\u00e9",
    "gn:population":0,
    "gn:timezone":"Africa/Dakar",
    "iso:country":"SN",
    "name:und_x_variant":[
        "Lingu\u00e9di\u00e9",
        "Lengu\u00e9di\u00e9"
    ],
    "wof:name":"Lenguedie",
    "wof:placetype":"locality"
},
  "geometry": {"coordinates":[-14.36667,13.18333],"type":"Point"}
}