{
  "type": "Feature",
  "properties": {
    "gn:admin1_code":"11.0",
    "gn:asciiname":"Gambissara",
    "gn:cc2":"SN",
    "gn:country_code":"SN",
    "gn:dem":25,
    "gn:feature_class":"P",
    "gn:feature_code":"PPL",
    "gn:name":"Gambissara",
    "gn:population":0,
    "gn:timezone":"Africa/Dakar",
    "iso:country":"SN",
    "name:und_x_variant":[
        "Cambissar",
        "Gambissar I",
        "Gambissar",
        "Gambissara"
    ],
    "wof:name":"Gambissara",
    "wof:placetype":"locality"
},
  "geometry": {"coordinates":[-13.95,13.31667],"type":"Point"}
}