{
  "type": "Feature",
  "properties": {
    "gn:admin1_code":"7.0",
    "gn:asciiname":"Ndiakhate Sar",
    "gn:cc2":"SN",
    "gn:country_code":"SN",
    "gn:dem":30,
    "gn:feature_class":"P",
    "gn:feature_code":"PPL",
    "gn:name":"Ndiakhat\u00e9 Sar",
    "gn:population":0,
    "gn:timezone":"Africa/Dakar",
    "iso:country":"SN",
    "name:und_x_variant":[
        "Diakhat\u00e9",
        "Ndiakhat\u00e9 Sar"
    ],
    "wof:lang_x_official":[
        "wol",
        "fra"
    ],
    "wof:lang_x_spoken":[
        "wol",
        "fra"
    ],
    "wof:name":"Ndiakhate Sar",
    "wof:placetype":"locality"
},
  "geometry": {"coordinates":[-16.56667,15.05],"type":"Point"}
}