{
  "type": "Feature",
  "properties": {
    "gn:admin1_code":"18.0",
    "gn:asciiname":"Dioufana",
    "gn:country_code":"SN",
    "gn:dem":23,
    "gn:feature_class":"P",
    "gn:feature_code":"PPL",
    "gn:name":"Dioufana",
    "gn:population":0,
    "gn:timezone":"Africa/Dakar",
    "iso:country":"SN",
    "wof:name":"Dioufana",
    "wof:placetype":"locality"
},
  "geometry": {"coordinates":[-15.24917,12.92306],"type":"Point"}
}