{
  "type": "Feature",
  "properties": {
    "gn:admin1_code":"17.0",
    "gn:asciiname":"Lebare Tiannieto",
    "gn:country_code":"SN",
    "gn:dem":165,
    "gn:feature_class":"P",
    "gn:feature_code":"PPL",
    "gn:name":"L\u00e9bar\u00e9 Tianni\u00e9to",
    "gn:population":0,
    "gn:timezone":"Africa/Dakar",
    "iso:country":"SN",
    "wof:name":"Lebare Tiannieto",
    "wof:placetype":"locality"
},
  "geometry": {"coordinates":[-12.8561,12.685],"type":"Point"}
}