{
  "type": "Feature",
  "properties": {
    "gn:admin1_code":"18.0",
    "gn:asciiname":"Tabali",
    "gn:country_code":"SN",
    "gn:dem":15,
    "gn:feature_class":"P",
    "gn:feature_code":"PPL",
    "gn:name":"Tabali",
    "gn:population":0,
    "gn:timezone":"Africa/Dakar",
    "iso:country":"SN",
    "wof:name":"Tabali",
    "wof:placetype":"locality"
},
  "geometry": {"coordinates":[-15.90472,12.88556],"type":"Point"}
}