{
  "type": "Feature",
  "properties": {
    "gn:admin1_code":"10.0",
    "gn:asciiname":"Tialane",
    "gn:country_code":"SN",
    "gn:dem":21,
    "gn:feature_class":"P",
    "gn:feature_code":"PPL",
    "gn:name":"Tialane",
    "gn:population":0,
    "gn:timezone":"Africa/Dakar",
    "iso:country":"SN",
    "wof:name":"Tialane",
    "wof:placetype":"locality"
},
  "geometry": {"coordinates":[-15.88333,14.06667],"type":"Point"}
}