{
  "type": "Feature",
  "properties": {
    "gn:admin1_code":"11.0",
    "gn:asciiname":"Sare Ndiobo",
    "gn:country_code":"SN",
    "gn:dem":45,
    "gn:feature_class":"P",
    "gn:feature_code":"PPL",
    "gn:name":"Sar\u00e9 Ndiobo",
    "gn:population":0,
    "gn:timezone":"Africa/Dakar",
    "iso:country":"SN",
    "wof:name":"Sare Ndiobo",
    "wof:placetype":"locality"
},
  "geometry": {"coordinates":[-14.45,13.26667],"type":"Point"}
}