{
  "type": "Feature",
  "properties": {
    "gn:admin1_code":"17.0",
    "gn:asciiname":"Margou",
    "gn:country_code":"SN",
    "gn:dem":87,
    "gn:feature_class":"P",
    "gn:feature_code":"PPL",
    "gn:name":"Margou",
    "gn:population":0,
    "gn:timezone":"Africa/Dakar",
    "iso:country":"SN",
    "wof:name":"Margou",
    "wof:placetype":"locality"
},
  "geometry": {"coordinates":[-11.81402,13.25048],"type":"Point"}
}