{
  "type": "Feature",
  "properties": {
    "gn:admin1_code":"3.0",
    "gn:asciiname":"Darou Rahmane",
    "gn:cc2":"SN",
    "gn:country_code":"SN",
    "gn:dem":42,
    "gn:feature_class":"P",
    "gn:feature_code":"PPL",
    "gn:name":"Darou Rahmane",
    "gn:population":0,
    "gn:timezone":"Africa/Dakar",
    "iso:country":"SN",
    "name:und_x_variant":[
        "Darou Rhamane",
        "Darou Rahmane"
    ],
    "wof:name":"Darou Rahmane",
    "wof:placetype":"locality"
},
  "geometry": {"coordinates":[-16.01667,14.95],"type":"Point"}
}