{
  "type": "Feature",
  "properties": {
    "gn:admin1_code":"7.0",
    "gn:asciiname":"Ndayane",
    "gn:country_code":"SN",
    "gn:dem":7,
    "gn:feature_class":"P",
    "gn:feature_code":"PPL",
    "gn:name":"Ndayane",
    "gn:population":0,
    "gn:timezone":"Africa/Dakar",
    "iso:country":"SN",
    "name:und_x_variant":[
        "Nd\u00e9yane",
        "Ndayane"
    ],
    "wof:name":"Ndayane",
    "wof:placetype":"locality"
},
  "geometry": {"coordinates":[-17.12457,14.56494],"type":"Point"}
}