{
  "type": "Feature",
  "properties": {
    "gn:admin1_code":"13.0",
    "gn:asciiname":"Sintiou Tiarigne",
    "gn:cc2":"SN",
    "gn:country_code":"SN",
    "gn:dem":42,
    "gn:feature_class":"P",
    "gn:feature_code":"PPL",
    "gn:name":"Sintiou Tiarigne",
    "gn:population":0,
    "gn:timezone":"Africa/Dakar",
    "iso:country":"SN",
    "name:und_x_variant":[
        "Seignethiou Ti\u00e9rigne",
        "Sinntiou Tiarigne",
        "Sintiou Tiarigne"
    ],
    "wof:lang_x_official":[
        "wol",
        "fra"
    ],
    "wof:lang_x_spoken":[
        "wol",
        "fra"
    ],
    "wof:name":"Sintiou Tiarigne",
    "wof:placetype":"locality"
},
  "geometry": {"coordinates":[-16.41667,15.58333],"type":"Point"}
}