{
  "type": "Feature",
  "properties": {
    "gn:admin1_code":"13.0",
    "gn:asciiname":"Galene Ndjououndjou",
    "gn:country_code":"SN",
    "gn:dem":53,
    "gn:feature_class":"P",
    "gn:feature_code":"PPL",
    "gn:name":"Gal\u00e8ne Ndjououndjou",
    "gn:population":0,
    "gn:timezone":"Africa/Dakar",
    "iso:country":"SN",
    "name:und_x_variant":[
        "Galenn Ndiououndiou",
        "Galenn Ndiououndjou",
        "Gal\u00e8ne Ndjououndjou"
    ],
    "wof:name":"Galene Ndjououndjou",
    "wof:placetype":"locality"
},
  "geometry": {"coordinates":[-15.8396,15.3092],"type":"Point"}
}