{
  "type": "Feature",
  "properties": {
    "gn:admin1_code":"16.0",
    "gn:asciiname":"Keur Goumbo Gueye",
    "gn:country_code":"SN",
    "gn:dem":27,
    "gn:feature_class":"P",
    "gn:feature_code":"PPL",
    "gn:name":"Keur Goumbo Gu\u00e9ye",
    "gn:population":0,
    "gn:timezone":"Africa/Dakar",
    "iso:country":"SN",
    "wof:name":"Keur Goumbo Gueye",
    "wof:placetype":"locality"
},
  "geometry": {"coordinates":[-15.73333,14.03333],"type":"Point"}
}