{
  "type": "Feature",
  "properties": {
    "gn:admin1_code":"11.0",
    "gn:asciiname":"Katonfara",
    "gn:cc2":"SN",
    "gn:country_code":"SN",
    "gn:dem":29,
    "gn:feature_class":"P",
    "gn:feature_code":"PPL",
    "gn:name":"Katonfara",
    "gn:population":0,
    "gn:timezone":"Africa/Dakar",
    "iso:country":"SN",
    "name:und_x_variant":[
        "Takonfara",
        "Tankonfara",
        "Katonfara"
    ],
    "wof:name":"Katonfara",
    "wof:placetype":"locality"
},
  "geometry": {"coordinates":[-14.96667,13.25],"type":"Point"}
}