{
  "type": "Feature",
  "properties": {
    "gn:admin1_code":"17.0",
    "gn:asciiname":"Wondio",
    "gn:country_code":"SN",
    "gn:dem":163,
    "gn:feature_class":"P",
    "gn:feature_code":"PPL",
    "gn:name":"Wondio",
    "gn:population":0,
    "gn:timezone":"Africa/Dakar",
    "iso:country":"SN",
    "name:und_x_variant":[
        "Wenndia",
        "Wondio"
    ],
    "wof:name":"Wondio",
    "wof:placetype":"locality"
},
  "geometry": {"coordinates":[-12.0925,12.5362],"type":"Point"}
}