{
  "type": "Feature",
  "properties": {
    "iso:country":"SN",
    "name:ara_x_preferred":[
        "\u0646\u063a\u0648\u0631"
    ],
    "name:deu_x_preferred":[
        "Ngor"
    ],
    "name:eng_x_preferred":[
        "Ngor"
    ],
    "name:fra_x_preferred":[
        "Ngor"
    ],
    "name:nld_x_preferred":[
        "Ngor"
    ],
    "qs:gn_country":"SN",
    "qs:gn_fcode":"PPL",
    "qs:gn_pop":0,
    "qs:name":"Ngor",
    "qs:name_adm0":"S\u00e9n\u00e9gal",
    "qs:name_adm1":"Dakar",
    "qs:photos":264,
    "qs:photos_1k":53,
    "qs:photos_9k":1,
    "qs:photos_9r":4,
    "qs:photos_all":264,
    "qs:photos_sr":5,
    "qs:placetype":"Town",
    "qs:pop_sr":"0",
    "qs:woe_adm0":23424943,
    "wd:wordcount":49,
    "wof:lang_x_official":[
        "wol",
        "fra"
    ],
    "wof:lang_x_spoken":[
        "wol",
        "fra"
    ],
    "wof:name":"Ngor",
    "wof:placetype":"locality"
},
  "geometry": {"coordinates":[-17.51515,14.74935],"type":"Point"}
}