{
  "type": "Feature",
  "properties": {
    "gn:admin1_code":"13.0",
    "gn:asciiname":"Kourou",
    "gn:country_code":"SN",
    "gn:dem":44,
    "gn:feature_class":"P",
    "gn:feature_code":"PPL",
    "gn:name":"Kourou",
    "gn:population":0,
    "gn:timezone":"Africa/Dakar",
    "iso:country":"SN",
    "name:afr_x_preferred":[
        "Kourou"
    ],
    "name:ara_x_preferred":[
        "\u0643\u0648\u0631\u0648\u0627"
    ],
    "name:ast_x_preferred":[
        "Kourou"
    ],
    "name:bre_x_preferred":[
        "Kourou"
    ],
    "name:bul_x_preferred":[
        "\u041a\u0443\u0440\u0443"
    ],
    "name:cat_x_preferred":[
        "Kourou"
    ],
    "name:ceb_x_preferred":[
        "Kourou"
    ],
    "name:ces_x_preferred":[
        "Kourou"
    ],
    "name:deu_x_preferred":[
        "Kourou"
    ],
    "name:ell_x_preferred":[
        "\u039a\u03bf\u03c5\u03c1\u03bf\u03cd"
    ],
    "name:epo_x_preferred":[
        "Kourou"
    ],
    "name:est_x_preferred":[
        "Kourou"
    ],
    "name:fas_x_preferred":[
        "\u06a9\u0648\u0631\u0648"
    ],
    "name:fin_x_preferred":[
        "Kourou"
    ],
    "name:fra_x_preferred":[
        "Kourou"
    ],
    "name:ile_x_preferred":[
        "Kourou"
    ],
    "name:ind_x_preferred":[
        "Kourou"
    ],
    "name:ita_x_preferred":[
        "Kourou"
    ],
    "name:jpn_x_preferred":[
        "\u30af\u30fc\u30eb\u30fc"
    ],
    "name:kor_x_preferred":[
        "\ucfe0\ub8e8"
    ],
    "name:lat_x_preferred":[
        "Kourou"
    ],
    "name:ltz_x_preferred":[
        "Kourou"
    ],
    "name:msa_x_preferred":[
        "Kourou"
    ],
    "name:mzn_x_preferred":[
        "\u06a9\u0648\u0631\u0648"
    ],
    "name:nld_x_preferred":[
        "Kourou"
    ],
    "name:nno_x_preferred":[
        "Kourou"
    ],
    "name:nor_x_preferred":[
        "Kourou"
    ],
    "name:oci_x_preferred":[
        "Kourou"
    ],
    "name:pms_x_preferred":[
        "Kourou"
    ],
    "name:pol_x_preferred":[
        "Kourou"
    ],
    "name:por_x_preferred":[
        "Kourou"
    ],
    "name:rus_x_preferred":[
        "\u041a\u0443\u0440\u0443"
    ],
    "name:slk_x_preferred":[
        "Kourou"
    ],
    "name:spa_x_preferred":[
        "Kourou"
    ],
    "name:srp_x_preferred":[
        "\u041a\u0443\u0440\u0443"
    ],
    "name:swa_x_preferred":[
        "Kourou"
    ],
    "name:swe_x_preferred":[
        "Kourou"
    ],
    "name:tur_x_preferred":[
        "Kourou"
    ],
    "name:ukr_x_preferred":[
        "\u041a\u0443\u0440\u0443"
    ],
    "name:vie_x_preferred":[
        "Kourou"
    ],
    "name:war_x_preferred":[
        "Kourou"
    ],
    "wof:name":"Kourou",
    "wof:placetype":"locality"
},
  "geometry": {"coordinates":[-16.33333,15.51667],"type":"Point"}
}