{
  "type": "Feature",
  "properties": {
    "gn:admin1_code":"5.0",
    "gn:asciiname":"Hamdallai Tessan",
    "gn:cc2":"SN",
    "gn:country_code":"SN",
    "gn:dem":36,
    "gn:feature_class":"P",
    "gn:feature_code":"PPL",
    "gn:name":"Hamdalla\u00ef Tessan",
    "gn:population":0,
    "gn:timezone":"Africa/Dakar",
    "iso:country":"SN",
    "name:und_x_variant":[
        "Tessan",
        "Hamdaye Tessan",
        "Hamdalaye Tessan",
        "Hamdalla\u00ef Tessan"
    ],
    "wof:name":"Hamdallai Tessan",
    "wof:placetype":"locality"
},
  "geometry": {"coordinates":[-13.51667,13.61667],"type":"Point"}
}