{
  "type": "Feature",
  "properties": {
    "gn:admin1_code":"16.0",
    "gn:asciiname":"Taiba Ndioufene",
    "gn:country_code":"SN",
    "gn:dem":45,
    "gn:feature_class":"P",
    "gn:feature_code":"PPL",
    "gn:name":"Ta\u00efba Ndiouf\u00e8ne",
    "gn:population":0,
    "gn:timezone":"Africa/Dakar",
    "iso:country":"SN",
    "wof:name":"Taiba Ndioufene",
    "wof:placetype":"locality"
},
  "geometry": {"coordinates":[-14.98333,14.11667],"type":"Point"}
}