{
  "type": "Feature",
  "properties": {
    "gn:admin1_code":"18.0",
    "gn:asciiname":"Dator",
    "gn:country_code":"SN",
    "gn:dem":34,
    "gn:feature_class":"P",
    "gn:feature_code":"PPL",
    "gn:name":"Dator",
    "gn:population":0,
    "gn:timezone":"Africa/Dakar",
    "iso:country":"SN",
    "wof:name":"Dator",
    "wof:placetype":"locality"
},
  "geometry": {"coordinates":[-15.68333,13.31667],"type":"Point"}
}