{
  "type": "Feature",
  "properties": {
    "gn:admin1_code":"12.0",
    "gn:asciiname":"Tabi",
    "gn:country_code":"SN",
    "gn:dem":28,
    "gn:feature_class":"P",
    "gn:feature_code":"PPL",
    "gn:name":"Tabi",
    "gn:population":0,
    "gn:timezone":"Africa/Dakar",
    "iso:country":"SN",
    "name:afr_x_preferred":[
        "Tabi"
    ],
    "name:ara_x_preferred":[
        "\u062a\u0627\u0628\u064a"
    ],
    "name:aze_x_preferred":[
        "Tabi"
    ],
    "name:cat_x_preferred":[
        "Tabi"
    ],
    "name:ces_x_preferred":[
        "Tabi"
    ],
    "name:deu_x_preferred":[
        "Tabi"
    ],
    "name:epo_x_preferred":[
        "Tabioj"
    ],
    "name:fin_x_preferred":[
        "Tabi"
    ],
    "name:fra_x_preferred":[
        "Tabi"
    ],
    "name:heb_x_preferred":[
        "\u05d8\u05d0\u05d1\u05d9"
    ],
    "name:hye_x_preferred":[
        "\u054f\u0561\u0562\u056b"
    ],
    "name:ita_x_preferred":[
        "Tabi"
    ],
    "name:kor_x_preferred":[
        "\ub2e4\ube44"
    ],
    "name:nld_x_preferred":[
        "Tabi"
    ],
    "name:nno_x_preferred":[
        "Tabi"
    ],
    "name:pan_x_preferred":[
        "\u0a24\u0a3e\u0a2c\u0a40"
    ],
    "name:pol_x_preferred":[
        "Tabi"
    ],
    "name:por_x_preferred":[
        "Tabi"
    ],
    "name:ron_x_preferred":[
        "Tabi"
    ],
    "name:rus_x_preferred":[
        "\u0422\u0430\u0431\u0438"
    ],
    "name:spa_x_preferred":[
        "Tabi"
    ],
    "name:swe_x_preferred":[
        "Tabi"
    ],
    "name:tur_x_preferred":[
        "Tabi"
    ],
    "name:ukr_x_preferred":[
        "\u0422\u0430\u0431\u0456"
    ],
    "name:zho_x_preferred":[
        "\u5206\u8dbe\u978b\u896a"
    ],
    "wof:name":"Tabi",
    "wof:placetype":"locality"
},
  "geometry": {"coordinates":[-16.23361,12.72694],"type":"Point"}
}