{
  "type": "Feature",
  "properties": {
    "gn:admin1_code":"12.0",
    "gn:asciiname":"Tabi",
    "gn:country_code":"SN",
    "gn:dem":28,
    "gn:feature_class":"P",
    "gn:feature_code":"PPL",
    "gn:name":"Tabi",
    "gn:population":0,
    "gn:timezone":"Africa/Dakar",
    "iso:country":"SN",
    "wof:name":"Tabi",
    "wof:placetype":"locality"
},
  "geometry": {"coordinates":[-16.23361,12.72694],"type":"Point"}
}