{
  "type": "Feature",
  "properties": {
    "gn:admin1_code":"10.0",
    "gn:asciiname":"Ndiobiene",
    "gn:cc2":"SN",
    "gn:country_code":"SN",
    "gn:dem":19,
    "gn:feature_class":"P",
    "gn:feature_code":"PPL",
    "gn:name":"Ndiobi\u00e8ne",
    "gn:population":0,
    "gn:timezone":"Africa/Dakar",
    "iso:country":"SN",
    "name:und_x_variant":[
        "Ndob\u00e8ne",
        "Ndiobi\u00e8ne"
    ],
    "wof:name":"Ndiobiene",
    "wof:placetype":"locality"
},
  "geometry": {"coordinates":[-15.88333,13.98333],"type":"Point"}
}