{
  "type": "Feature",
  "properties": {
    "gn:admin1_code":"14.0",
    "gn:asciiname":"Lour Gaode",
    "gn:country_code":"SN",
    "gn:dem":53,
    "gn:feature_class":"P",
    "gn:feature_code":"PPL",
    "gn:name":"Lour Gaod\u00e9",
    "gn:population":0,
    "gn:timezone":"Africa/Dakar",
    "iso:country":"SN",
    "wof:name":"Lour Gaode",
    "wof:placetype":"locality"
},
  "geometry": {"coordinates":[-14.0534,15.8938],"type":"Point"}
}