{
  "type": "Feature",
  "properties": {
    "iso:country":"SN",
    "name:und_x_variant":[
        "Pobinguem"
    ],
    "qs:gn_country":"SN",
    "qs:gn_fcode":"PPL",
    "qs:gn_pop":0,
    "qs:name":"Popenguine",
    "qs:name_adm0":"S\u00e9n\u00e9gal",
    "qs:name_adm1":"Thi\u00e8s",
    "qs:photos":169,
    "qs:photos_1k":34,
    "qs:photos_9k":1,
    "qs:photos_9r":4,
    "qs:photos_all":169,
    "qs:photos_sr":4,
    "qs:placetype":"Town",
    "qs:pop_sr":"0",
    "qs:woe_adm0":23424943,
    "wof:name":"Popenguine",
    "wof:placetype":"locality"
},
  "geometry": {"coordinates":[-17.11396,14.55735],"type":"Point"}
}