{
  "type": "Feature",
  "properties": {
    "gn:admin1_code":"17.0",
    "gn:asciiname":"Goumbambere",
    "gn:country_code":"SN",
    "gn:dem":124,
    "gn:feature_class":"P",
    "gn:feature_code":"PPL",
    "gn:name":"Goumbamb\u00e9r\u00e9",
    "gn:population":0,
    "gn:timezone":"Africa/Dakar",
    "iso:country":"SN",
    "name:und_x_variant":[
        "Gounbab\u00e9r\u00e9",
        "Goumbamb\u00e9r\u00e9"
    ],
    "wof:lang_x_official":[
        "wol",
        "fra"
    ],
    "wof:lang_x_spoken":[
        "wol",
        "fra"
    ],
    "wof:name":"Goumbambere",
    "wof:placetype":"locality"
},
  "geometry": {"coordinates":[-12.5139,12.4159],"type":"Point"}
}