{
  "type": "Feature",
  "properties": {
    "gn:admin1_code":"18.0",
    "gn:asciiname":"Fassane",
    "gn:country_code":"SN",
    "gn:dem":22,
    "gn:feature_class":"P",
    "gn:feature_code":"PPL",
    "gn:name":"Fassane",
    "gn:population":0,
    "gn:timezone":"Africa/Dakar",
    "iso:country":"SN",
    "wof:name":"Fassane",
    "wof:placetype":"locality"
},
  "geometry": {"coordinates":[-15.58167,12.49111],"type":"Point"}
}