{
  "type": "Feature",
  "properties": {
    "gn:admin1_code":"15.0",
    "gn:asciiname":"Tiengolel Demba Djibi",
    "gn:country_code":"SN",
    "gn:dem":83,
    "gn:feature_class":"P",
    "gn:feature_code":"PPL",
    "gn:name":"Tiengolel Demba Djibi",
    "gn:population":0,
    "gn:timezone":"Africa/Dakar",
    "iso:country":"SN",
    "name:und_x_variant":[
        "Tiengolel Dinba Djibi",
        "Tiengolel Demba Djibi"
    ],
    "wof:lang_x_official":[
        "wol",
        "fra"
    ],
    "wof:lang_x_spoken":[
        "wol",
        "fra"
    ],
    "wof:name":"Tiengolel Demba Djibi",
    "wof:placetype":"locality"
},
  "geometry": {"coordinates":[-12.71049,14.71004],"type":"Point"}
}