{
  "type": "Feature",
  "properties": {
    "gn:admin1_code":"5.0",
    "gn:asciiname":"Mbailadji",
    "gn:country_code":"SN",
    "gn:dem":62,
    "gn:feature_class":"P",
    "gn:feature_code":"PPL",
    "gn:name":"Mba\u00efladji",
    "gn:population":0,
    "gn:timezone":"Africa/Dakar",
    "iso:country":"SN",
    "wof:name":"Mbailadji",
    "wof:placetype":"locality"
},
  "geometry": {"coordinates":[-12.77754,14.26014],"type":"Point"}
}