{
  "type": "Feature",
  "properties": {
    "gn:admin1_code":"13.0",
    "gn:asciiname":"Tiel",
    "gn:cc2":"SN",
    "gn:country_code":"SN",
    "gn:dem":46,
    "gn:feature_class":"P",
    "gn:feature_code":"PPL",
    "gn:name":"Ti\u00e8l",
    "gn:population":0,
    "gn:timezone":"Africa/Dakar",
    "iso:country":"SN",
    "name:und_x_variant":[
        "Thiel",
        "Ti\u00e8l"
    ],
    "wof:name":"Tiel",
    "wof:placetype":"locality"
},
  "geometry": {"coordinates":[-15.06667,14.93333],"type":"Point"}
}