{
  "type": "Feature",
  "properties": {
    "gn:admin1_code":"13.0",
    "gn:asciiname":"Tiel",
    "gn:cc2":"SN",
    "gn:country_code":"SN",
    "gn:dem":46,
    "gn:feature_class":"P",
    "gn:feature_code":"PPL",
    "gn:name":"Ti\u00e8l",
    "gn:population":0,
    "gn:timezone":"Africa/Dakar",
    "iso:country":"SN",
    "name:afr_x_preferred":[
        "Tiel"
    ],
    "name:ara_x_preferred":[
        "\u062a\u064a\u0644"
    ],
    "name:cat_x_preferred":[
        "Tiel"
    ],
    "name:ceb_x_preferred":[
        "Gemeente Tiel"
    ],
    "name:deu_x_preferred":[
        "Tiel"
    ],
    "name:epo_x_preferred":[
        "Tiel"
    ],
    "name:eus_x_preferred":[
        "Tiel"
    ],
    "name:fas_x_preferred":[
        "\u062a\u06cc\u0644"
    ],
    "name:fra_x_preferred":[
        "Tiel"
    ],
    "name:fry_x_preferred":[
        "Tiel"
    ],
    "name:hye_x_preferred":[
        "\u0539\u056b\u056c"
    ],
    "name:ind_x_preferred":[
        "Tiel"
    ],
    "name:ita_x_preferred":[
        "Tiel"
    ],
    "name:jav_x_preferred":[
        "Tiel"
    ],
    "name:jpn_x_preferred":[
        "\u30c6\u30a3\u30fc\u30eb"
    ],
    "name:kor_x_preferred":[
        "\ud2f8"
    ],
    "name:lim_x_preferred":[
        "Tiel"
    ],
    "name:msa_x_preferred":[
        "Tiel"
    ],
    "name:nds_x_preferred":[
        "Tiel"
    ],
    "name:nld_x_preferred":[
        "Tiel"
    ],
    "name:pol_x_preferred":[
        "Tiel"
    ],
    "name:por_x_preferred":[
        "Tiel"
    ],
    "name:ron_x_preferred":[
        "Tiel"
    ],
    "name:rus_x_preferred":[
        "\u0422\u0438\u043b"
    ],
    "name:sqi_x_preferred":[
        "Tiel"
    ],
    "name:stq_x_preferred":[
        "Tiel"
    ],
    "name:swe_x_preferred":[
        "Tiel"
    ],
    "name:tur_x_preferred":[
        "Tiel"
    ],
    "name:und_x_variant":[
        "Thiel",
        "Ti\u00e8l"
    ],
    "name:vie_x_preferred":[
        "Tiel"
    ],
    "name:vol_x_preferred":[
        "Tiel"
    ],
    "name:war_x_preferred":[
        "Tiel"
    ],
    "name:zho_x_preferred":[
        "\u8482\u723e"
    ],
    "wof:name":"Tiel",
    "wof:placetype":"locality"
},
  "geometry": {"coordinates":[-15.06667,14.93333],"type":"Point"}
}