{
  "type": "Feature",
  "properties": {
    "gn:admin1_code":"5.0",
    "gn:asciiname":"Bankouba",
    "gn:country_code":"SN",
    "gn:dem":78,
    "gn:feature_class":"P",
    "gn:feature_code":"PPL",
    "gn:name":"Bankouba",
    "gn:population":0,
    "gn:timezone":"Africa/Dakar",
    "iso:country":"SN",
    "wof:name":"Bankouba",
    "wof:placetype":"locality"
},
  "geometry": {"coordinates":[-12.2824,13.87987],"type":"Point"}
}