{
  "type": "Feature",
  "properties": {
    "gn:admin1_code":"15.0",
    "gn:asciiname":"Doumga Ouro Alfa",
    "gn:country_code":"SN",
    "gn:dem":24,
    "gn:feature_class":"P",
    "gn:feature_code":"PPL",
    "gn:name":"Doumga Ouro Alfa",
    "gn:population":0,
    "gn:timezone":"Africa/Dakar",
    "iso:country":"SN",
    "name:und_x_variant":[
        "Doumgo Ouro Alfa",
        "Doumga Ouro Alfa"
    ],
    "wof:lang_x_official":[
        "wol",
        "fra"
    ],
    "wof:lang_x_spoken":[
        "wol",
        "fra"
    ],
    "wof:name":"Doumga Ouro Alfa",
    "wof:placetype":"locality"
},
  "geometry": {"coordinates":[-13.45144,15.83038],"type":"Point"}
}