{
  "type": "Feature",
  "properties": {
    "gn:admin1_code":"13.0",
    "gn:asciiname":"Mbeuleukhe",
    "gn:country_code":"SN",
    "gn:dem":17,
    "gn:feature_class":"P",
    "gn:feature_code":"PPL",
    "gn:name":"Mbeuleukh\u00e9",
    "gn:population":0,
    "gn:timezone":"Africa/Dakar",
    "iso:country":"SN",
    "name:und_x_variant":[
        "Mbeulak\u00e9",
        "Mbeulakh\u00e9",
        "Mbeulekh\u00e9",
        "Mbeuleukh\u00e9"
    ],
    "wof:name":"Mbeuleukhe",
    "wof:placetype":"locality"
},
  "geometry": {"coordinates":[-15.3492,15.6487],"type":"Point"}
}