{
  "type": "Feature",
  "properties": {
    "gn:admin1_code":"7.0",
    "gn:asciiname":"Bayene Diak",
    "gn:country_code":"SN",
    "gn:dem":18,
    "gn:feature_class":"P",
    "gn:feature_code":"PPL",
    "gn:name":"Bay\u00e8ne Diak",
    "gn:population":0,
    "gn:timezone":"Africa/Dakar",
    "iso:country":"SN",
    "wof:name":"Bayene Diak",
    "wof:placetype":"locality"
},
  "geometry": {"coordinates":[-16.75,14.66667],"type":"Point"}
}