{
  "type": "Feature",
  "properties": {
    "gn:admin1_code":"11.0",
    "gn:asciiname":"Diabel Sambou",
    "gn:cc2":"SN",
    "gn:country_code":"SN",
    "gn:dem":24,
    "gn:feature_class":"P",
    "gn:feature_code":"PPL",
    "gn:name":"Diabel Sambou",
    "gn:population":0,
    "gn:timezone":"Africa/Dakar",
    "iso:country":"SN",
    "name:und_x_variant":[
        "Djabel Sambou",
        "Diabel Sambou"
    ],
    "wof:name":"Diabel Sambou",
    "wof:placetype":"locality"
},
  "geometry": {"coordinates":[-14.68333,12.85],"type":"Point"}
}