{
  "type": "Feature",
  "properties": {
    "gn:admin1_code":"12.0",
    "gn:asciiname":"Silinkine",
    "gn:cc2":"SN",
    "gn:country_code":"SN",
    "gn:dem":18,
    "gn:feature_class":"P",
    "gn:feature_code":"PPL",
    "gn:name":"Silinkine",
    "gn:population":0,
    "gn:timezone":"Africa/Dakar",
    "iso:country":"SN",
    "name:und_x_variant":[
        "Silinki",
        "Silinkine"
    ],
    "wof:name":"Silinkine",
    "wof:placetype":"locality"
},
  "geometry": {"coordinates":[-16.01139,12.95583],"type":"Point"}
}