{
  "type": "Feature",
  "properties": {
    "gn:admin1_code":"7.0",
    "gn:asciiname":"Ndiok Thiam",
    "gn:cc2":"SN",
    "gn:country_code":"SN",
    "gn:dem":35,
    "gn:feature_class":"P",
    "gn:feature_code":"PPL",
    "gn:name":"Ndiok Thiam",
    "gn:population":0,
    "gn:timezone":"Africa/Dakar",
    "iso:country":"SN",
    "name:und_x_variant":[
        "N\u2019Diok",
        "Ndiok Thiam"
    ],
    "wof:lang_x_official":[
        "wol",
        "fra"
    ],
    "wof:lang_x_spoken":[
        "wol",
        "fra"
    ],
    "wof:name":"Ndiok Thiam",
    "wof:placetype":"locality"
},
  "geometry": {"coordinates":[-16.28333,15.21667],"type":"Point"}
}