{
  "type": "Feature",
  "properties": {
    "gn:admin1_code":"13.0",
    "gn:asciiname":"Yapal",
    "gn:country_code":"SN",
    "gn:dem":49,
    "gn:feature_class":"P",
    "gn:feature_code":"PPL",
    "gn:name":"Yapal",
    "gn:population":0,
    "gn:timezone":"Africa/Dakar",
    "iso:country":"SN",
    "name:ara_x_preferred":[
        "\u064a\u0627\u0628\u0644"
    ],
    "name:ceb_x_preferred":[
        "Y\u0101pal"
    ],
    "name:ckb_x_preferred":[
        "\u06cc\u0627\u067e\u06d5\u06b5"
    ],
    "name:fas_x_preferred":[
        "\u06cc\u0627\u067e\u0644"
    ],
    "name:swe_x_preferred":[
        "Y\u0101pal"
    ],
    "wof:lang_x_official":[
        "wol",
        "fra"
    ],
    "wof:lang_x_spoken":[
        "wol",
        "fra"
    ],
    "wof:name":"Yapal",
    "wof:placetype":"locality"
},
  "geometry": {"coordinates":[-15.8741,15.1831],"type":"Point"}
}