{
  "type": "Feature",
  "properties": {
    "gn:admin1_code":"13.0",
    "gn:asciiname":"Koeli",
    "gn:country_code":"SN",
    "gn:dem":35,
    "gn:feature_class":"P",
    "gn:feature_code":"PPL",
    "gn:name":"Ko\u00e9li",
    "gn:population":0,
    "gn:timezone":"Africa/Dakar",
    "iso:country":"SN",
    "name:und_x_variant":[
        "Co\u00ebli",
        "Ko\u00e9li"
    ],
    "wof:name":"Koeli",
    "wof:placetype":"locality"
},
  "geometry": {"coordinates":[-15.5107,15.7421],"type":"Point"}
}