{
  "type": "Feature",
  "properties": {
    "gn:admin1_code":"18.0",
    "gn:asciiname":"Diareng",
    "gn:country_code":"SN",
    "gn:dem":11,
    "gn:feature_class":"P",
    "gn:feature_code":"PPL",
    "gn:name":"Diar\u00e8ng",
    "gn:population":0,
    "gn:timezone":"Africa/Dakar",
    "iso:country":"SN",
    "name:und_x_variant":[
        "Diar\u00e8ne",
        "Diar\u00e8ng"
    ],
    "wof:name":"Diareng",
    "wof:placetype":"locality"
},
  "geometry": {"coordinates":[-15.36333,12.81139],"type":"Point"}
}