{
  "type": "Feature",
  "properties": {
    "gn:admin1_code":"13.0",
    "gn:asciiname":"Dek Reye",
    "gn:country_code":"SN",
    "gn:dem":43,
    "gn:feature_class":"P",
    "gn:feature_code":"PPL",
    "gn:name":"D\u00e8k R\u00e8ye",
    "gn:population":0,
    "gn:timezone":"Africa/Dakar",
    "iso:country":"SN",
    "name:und_x_variant":[
        "Nd\u00e9gu\u00e9-Diey",
        "D\u00e8gue Reye",
        "Nd\u00e8gue Reye",
        "D\u00e8k R\u00e8ye"
    ],
    "wof:name":"Dek Reye",
    "wof:placetype":"locality"
},
  "geometry": {"coordinates":[-15.4579,15.6026],"type":"Point"}
}