{
  "type": "Feature",
  "properties": {
    "gn:admin1_code":"11.0",
    "gn:asciiname":"Niandinndia Dimbel",
    "gn:country_code":"SN",
    "gn:dem":49,
    "gn:feature_class":"P",
    "gn:feature_code":"PPL",
    "gn:name":"Niandinndia Dimbel",
    "gn:population":0,
    "gn:timezone":"Africa/Dakar",
    "iso:country":"SN",
    "wof:name":"Niandinndia Dimbel",
    "wof:placetype":"locality"
},
  "geometry": {"coordinates":[-14.48333,12.71667],"type":"Point"}
}