{
  "type": "Feature",
  "properties": {
    "gn:admin1_code":"7.0",
    "gn:asciiname":"Merina Diop",
    "gn:country_code":"SN",
    "gn:dem":27,
    "gn:feature_class":"P",
    "gn:feature_code":"PPL",
    "gn:name":"M\u00e9rina Diop",
    "gn:population":0,
    "gn:timezone":"Africa/Dakar",
    "iso:country":"SN",
    "wof:name":"Merina Diop",
    "wof:placetype":"locality"
},
  "geometry": {"coordinates":[-16.45,15.05],"type":"Point"}
}