{
  "type": "Feature",
  "properties": {
    "gn:admin1_code":"1.0",
    "gn:asciiname":"Ndoukhoura Wolof",
    "gn:country_code":"SN",
    "gn:dem":11,
    "gn:feature_class":"P",
    "gn:feature_code":"PPL",
    "gn:name":"Ndoukhoura Wolof",
    "gn:population":0,
    "gn:timezone":"Africa/Dakar",
    "iso:country":"SN",
    "name:und_x_variant":[
        "Ndoukhoura Ouolof"
    ],
    "wof:name":"Ndoukhoura Wolof",
    "wof:placetype":"locality"
},
  "geometry": {"coordinates":[-17.16726,14.68113],"type":"Point"}
}