{
  "type": "Feature",
  "properties": {
    "gn:admin1_code":"17.0",
    "gn:asciiname":"Fadiga",
    "gn:country_code":"SN",
    "gn:dem":112,
    "gn:feature_class":"P",
    "gn:feature_code":"PPL",
    "gn:name":"Fadiga",
    "gn:population":0,
    "gn:timezone":"Africa/Dakar",
    "iso:country":"SN",
    "name:und_x_variant":[
        "Fatika",
        "Eatika",
        "Fadiga"
    ],
    "wof:name":"Fadiga",
    "wof:placetype":"locality"
},
  "geometry": {"coordinates":[-12.2039,12.5535],"type":"Point"}
}