{
  "type": "Feature",
  "properties": {
    "gn:admin1_code":"12.0",
    "gn:asciiname":"Borofaye",
    "gn:cc2":"SN",
    "gn:country_code":"SN",
    "gn:dem":16,
    "gn:feature_class":"P",
    "gn:feature_code":"PPL",
    "gn:name":"Borofaye",
    "gn:population":0,
    "gn:timezone":"Africa/Dakar",
    "iso:country":"SN",
    "name:und_x_variant":[
        "Bourofaye",
        "Borofaye"
    ],
    "wof:name":"Borofaye",
    "wof:placetype":"locality"
},
  "geometry": {"coordinates":[-16.29,12.4925],"type":"Point"}
}