{
  "type": "Feature",
  "properties": {
    "gn:admin1_code":"12.0",
    "gn:asciiname":"Kaboukout",
    "gn:cc2":"SN",
    "gn:country_code":"SN",
    "gn:dem":10,
    "gn:feature_class":"P",
    "gn:feature_code":"PPL",
    "gn:name":"Kaboukout",
    "gn:population":0,
    "gn:timezone":"Africa/Dakar",
    "iso:country":"SN",
    "name:und_x_variant":[
        "Kaboukoute",
        "Kaboukout"
    ],
    "wof:lang_x_official":[
        "wol",
        "fra"
    ],
    "wof:lang_x_spoken":[
        "wol",
        "fra"
    ],
    "wof:name":"Kaboukout",
    "wof:placetype":"locality"
},
  "geometry": {"coordinates":[-16.68361,12.48361],"type":"Point"}
}