{
  "type": "Feature",
  "properties": {
    "gn:admin1_code":"12.0",
    "gn:asciiname":"Balankine",
    "gn:cc2":"SN",
    "gn:country_code":"SN",
    "gn:dem":15,
    "gn:feature_class":"P",
    "gn:feature_code":"PPL",
    "gn:name":"Balankine",
    "gn:population":0,
    "gn:timezone":"Africa/Dakar",
    "iso:country":"SN",
    "name:und_x_variant":[
        "Balankine Sud",
        "Balankine"
    ],
    "wof:name":"Balankine",
    "wof:placetype":"locality"
},
  "geometry": {"coordinates":[-15.98611,12.88917],"type":"Point"}
}