{
  "type": "Feature",
  "properties": {
    "gn:admin1_code":"14.0",
    "gn:asciiname":"Boulinaye",
    "gn:country_code":"SN",
    "gn:dem":13,
    "gn:feature_class":"P",
    "gn:feature_code":"PPL",
    "gn:name":"Boulinaye",
    "gn:population":0,
    "gn:timezone":"Africa/Dakar",
    "iso:country":"SN",
    "wof:name":"Boulinaye",
    "wof:placetype":"locality"
},
  "geometry": {"coordinates":[-14.30732,16.39182000000001],"type":"Point"}
}