{
  "type": "Feature",
  "properties": {
    "gn:admin1_code":"7.0",
    "gn:asciiname":"Taiba Rhabe",
    "gn:cc2":"SN",
    "gn:country_code":"SN",
    "gn:dem":59,
    "gn:feature_class":"P",
    "gn:feature_code":"PPL",
    "gn:name":"Ta\u00efba Rhabe",
    "gn:population":0,
    "gn:timezone":"Africa/Dakar",
    "iso:country":"SN",
    "name:und_x_variant":[
        "Ta\u00efba Kahabe",
        "Ta\u00efba Rhabe"
    ],
    "wof:lang_x_official":[
        "wol",
        "fra"
    ],
    "wof:lang_x_spoken":[
        "wol",
        "fra"
    ],
    "wof:name":"Taiba Rhabe",
    "wof:placetype":"locality"
},
  "geometry": {"coordinates":[-16.86667000000001,15.03333],"type":"Point"}
}