{
  "type": "Feature",
  "properties": {
    "gn:admin1_code":"5.0",
    "gn:asciiname":"Gourel Sadio",
    "gn:country_code":"SN",
    "gn:dem":55,
    "gn:feature_class":"P",
    "gn:feature_code":"PPL",
    "gn:name":"Gourel Sadio",
    "gn:population":0,
    "gn:timezone":"Africa/Dakar",
    "iso:country":"SN",
    "wof:name":"Gourel Sadio",
    "wof:placetype":"locality"
},
  "geometry": {"coordinates":[-12.75217,14.10423],"type":"Point"}
}