{
  "type": "Feature",
  "properties": {
    "gn:admin1_code":"9.0",
    "gn:asciiname":"Dioulouf Doundou",
    "gn:country_code":"SN",
    "gn:dem":-1,
    "gn:feature_class":"P",
    "gn:feature_code":"PPL",
    "gn:name":"Dioulouf Doundou",
    "gn:population":0,
    "gn:timezone":"Africa/Dakar",
    "iso:country":"SN",
    "wof:name":"Dioulouf Doundou",
    "wof:placetype":"locality"
},
  "geometry": {"coordinates":[-16.51667,14.33333],"type":"Point"}
}