{
  "type": "Feature",
  "properties": {
    "gn:admin1_code":"10.0",
    "gn:asciiname":"Pakatiar Ndavene",
    "gn:country_code":"SN",
    "gn:dem":24,
    "gn:feature_class":"P",
    "gn:feature_code":"PPL",
    "gn:name":"Pakatiar Ndav\u00e8ne",
    "gn:population":0,
    "gn:timezone":"Africa/Dakar",
    "iso:country":"SN",
    "wof:name":"Pakatiar Ndavene",
    "wof:placetype":"locality"
},
  "geometry": {"coordinates":[-15.81667,13.93333],"type":"Point"}
}