{
  "type": "Feature",
  "properties": {
    "gn:admin1_code":"7.0",
    "gn:asciiname":"Keur Matar",
    "gn:country_code":"SN",
    "gn:dem":45,
    "gn:feature_class":"P",
    "gn:feature_code":"PPL",
    "gn:name":"Keur Matar",
    "gn:population":0,
    "gn:timezone":"Africa/Dakar",
    "iso:country":"SN",
    "wof:name":"Keur Matar",
    "wof:placetype":"locality"
},
  "geometry": {"coordinates":[-16.86667000000001,14.78333],"type":"Point"}
}