{
  "type": "Feature",
  "properties": {
    "gn:admin1_code":"14.0",
    "gn:asciiname":"Darou Mboumbaye",
    "gn:cc2":"SN",
    "gn:country_code":"SN",
    "gn:dem":0,
    "gn:feature_class":"P",
    "gn:feature_code":"PPL",
    "gn:name":"Darou Mboumbaye",
    "gn:population":0,
    "gn:timezone":"Africa/Dakar",
    "iso:country":"SN",
    "name:und_x_variant":[
        "Mboumbaye",
        "Darou Mboumbaye"
    ],
    "wof:lang_x_official":[
        "wol",
        "fra"
    ],
    "wof:lang_x_spoken":[
        "wol",
        "fra"
    ],
    "wof:name":"Darou Mboumbaye",
    "wof:placetype":"locality"
},
  "geometry": {"coordinates":[-16.51667,15.83778],"type":"Point"}
}